Workbook

Sheet Guide
A1: BI Migration Estimator v2
A2: Quotable fixed-price estimate for BI report and semantic-model migrations.
B4: How to use
B5: 1. Setup | C5: Enter engagement details, iteration length, team and ramp settings, SIT/UAT/deployment cadence, automation % by phase and cost mode.
B6: 2. Scope | C6: One row per migration pair. Pick or type the source and target BI tool and data platform, then inventory, complexity mix, rationalisation, semantic models, security and AI readiness. Example rows are provided - overwrite them.
B7: 3. Risks | C7: List named risks with impact hours and probability. Expected hours become the risk reserve.
B8: 4. Roles | C8: Choose the rate-card row for each plan role and adjust the role mix per phase (each row totals 100%).
B9: 5. Checks | C9: Fix every FAIL. The Summary banner turns green only when all checks pass.
B10: 6. Summary | C10: Read the price, effort, duration, team and dates. Print Summary and Assumptions for the proposal.
B11: 7. Plan | C11: Review the weekly headcount. Use the manual adjustment rows to reshape the team; the reconciliation check flags gaps over the tolerance.
B13: Colour key
B14: Input | C14: Yellow cell with blue text: editable input (all other cells are locked; sheets are protected without a password).
B15: Calculated | C15: Black text: formula - do not overwrite.
B16: Header | C16: Table header.
B18: Tabs
B19: Summary | C19: One-page quotable view.
B20: Setup | C20: Engagement-wide inputs.
B21: Scope | C21: Migration pairs (up to 20).
B22: Risks | C22: Risk register.
B23: Roles | C23: Plan roles, rate selection and role mix by phase.
B24: Rates | C24: Rate card (bill rates, USD/h).
B25: Lists | C25: Tools, archetypes, known pair factors, data platforms.
B26: Baseline | C26: Reference values with status: Carried / Reshaped / New proposal / User decision.
B27: Effort | C27: Hours per pair and phase; programme-level hours; totals.
B28: Schedule | C28: Iterations, waves, phase windows, milestones.
B29: Plan | C29: Weekly hours and headcount by role.
B30: Cost | C30: Cost by role and phase; price build-up; payment milestones.
... B34: ChangeLog | C34: Version history.
B36: Method
C37: Report development = full-effort pages x mix-weighted hours per page x pair factor x data-platform uplift x report-type factor x (1 - learning gain) x (1 - automation saving), plus derived and merge hours.
C38: Semantic models = target models x mix-weighted model hours x approach share x pair factor x platform uplift, plus consolidation hours, less automation saving.
C39: Iterations: report hours / (peak team x hours per week) plus half the ramp weeks, divided by iteration length (or fixed directly).
C40: SIT runs one iteration behind development and UAT two behind; both are sized per iteration (crew x weeks), plus a final regression and UAT cycle.
C41: Automation saving per phase = automation % x automatable cap, so automation never removes the review and validation work.
C42: No step tiers: initiation and analysis interpolate between the old calculator's tier values.

Sheet Summary
B1: ="BI Migration Estimate - "&Client -> BI Migration Estimate - Example Client
B2: =Opportunity&" | "&EstVersion&" | "&TEXT(EstDate,"dd-mmm-yyyy")&" | Start "&TEXT(StartDate,"dd-mmm-yyyy")&" | All money in "&Currency -> BI modernisation programme | v2.0-draft | 13-Oct-2026 | Start 04-Jan-2027 | All money in USD
B4: =IF(FailCount=0,"VALID ESTIMATE - all checks pass","NOT VALID - "&FailCount&" check(s) failing: see the Checks tab") -> VALID ESTIMATE - all checks pass
B6: Fixed price | D6: Total effort (hours) | H6: Duration (working weeks) | J6: Planned end date
B7: =FixedPrice -> 1069220.9 | D7: =TotalHrs -> 17010.763 | H7: =DurationWeeks -> 36 | J7: =EndDate -> 46654
B9: Development iterations | D9: Releases | H9: Peak team (FTE) | J9: Average team (FTE)
B10: =IterCount&" x "&IterLen&" wk" -> 10 x 2 wk | D10: =Releases -> 2 | H10: =PeakTeam -> 18.5 | J10: =AvgTeam -> 9.8194444
B12: ="Average team during report iterations: "&TEXT(AvgDevTeam,"0.0")&" FTE | Contingency "&TEXT(ContPct,"0.0%")&" | Onsite share "&TEXT(OnsiteShare,"0.0%")&" | Cost mode: "&CostMode -> Average team during report iterations: 14.4 FTE | Contingency 18.1% | Onsite share 1.2% | Cost mode: Role mix
B14: Effort and cost by phase | H14: Team and cost by role
B15: Phase | C15: Hours | D15: % of hours | E15: Cost (USD) | F15: Weeks (start-end) | H15: Role | I15: Location | J15: Hours | K15: Rate (USD/h) | L15: Cost (USD)
B16: Initiation & assessment | C16: =INDEX(PhaseHours,1) -> 693 | D16: =IF(TotalBaseHrs>0,C16/TotalBaseHrs,0) -> 0.048378304 | E16: =INDEX(PhaseCost,1) -> 67983.3 | F16: =IF(C16>0,INDEX(PhStart,1)&" - "&INDEX(PhEnd,1),"") -> 1 - 6 | H16: =Cost!B6 -> Delivery manager / PM | I16: =Cost!C6 -> India | J16: =Cost!D6 -> 1440 | K16: =Cost!E6 -> 82 | L16: =Cost!F6 -> 118080
B17: Architecture & design | C17: =INDEX(PhaseHours,2) -> 128 | D17: =IF(TotalBaseHrs>0,C17/TotalBaseHrs,0) -> 0.0089356753 | E17: =INDEX(PhaseCost,2) -> 13510.4 | F17: =IF(C17>0,INDEX(PhStart,2)&" - "&INDEX(PhEnd,2),"") -> 4 - 5 | H17: =Cost!B7 -> Onsite architect | I17: =Cost!C7 -> USA | J17: =Cost!D7 -> 170.6 | K17: =Cost!E7 -> 185 | L17: =Cost!F7 -> 31561
B18: Semantic model build & consolidation | C18: =INDEX(PhaseHours,3) -> 2377.94 | D18: =IF(TotalBaseHrs>0,C18/TotalBaseHrs,0) -> 0.1660039 | E18: =INDEX(PhaseCost,3) -> 147432.28 | F18: =IF(C18>0,INDEX(PhStart,3)&" - "&INDEX(PhEnd,3),"") -> 7 - 18 | H18: =Cost!B8 -> Solution architect | I18: =Cost!C8 -> India | J18: =Cost!D8 -> 259.1 | K18: =Cost!E8 -> 87 | L18: =Cost!F8 -> 22541.7
B19: Report development & unit validation | C19: =INDEX(PhaseHours,4) -> 6206.6629 | D19: =IF(TotalBaseHrs>0,C19/TotalBaseHrs,0) -> 0.43328691 | E19: =INDEX(PhaseCost,4) -> 345090.46 | F19: =IF(C19>0,INDEX(PhStart,4)&" - "&INDEX(PhEnd,4),"") -> 9 - 28 | H19: =Cost!B9 -> BI architect | I19: =Cost!C9 -> India | J19: =Cost!D9 -> 765.891 | K19: =Cost!E9 -> 70 | L19: =Cost!F9 -> 53612.37
B20: SIT & optimization | C20: =INDEX(PhaseHours,5) -> 1840 | D20: =IF(TotalBaseHrs>0,C20/TotalBaseHrs,0) -> 0.12845033 | E20: =INDEX(PhaseCost,5) -> 105340 | F20: =IF(C20>0,INDEX(PhStart,5)&" - "&INDEX(PhEnd,5),"") -> 11 - 31 | H20: =Cost!B10 -> Lead | I20: =Cost!C10 -> India | J20: =Cost!D10 -> 1693.2573 | K20: =Cost!E10 -> 70 | L20: =Cost!F10 -> 118528.01
B21: UAT support | C21: =INDEX(PhaseHours,6) -> 440 | D21: =IF(TotalBaseHrs>0,C21/TotalBaseHrs,0) -> 0.030716384 | E21: =INDEX(PhaseCost,6) -> 25872 | F21: =IF(C21>0,INDEX(PhStart,6)&" - "&INDEX(PhEnd,6),"") -> 13 - 34 | H21: =Cost!B11 -> Sr. engineer | I21: =Cost!C11 -> India | J21: =Cost!D11 -> 3884.1689 | K21: =Cost!E11 -> 62 | L21: =Cost!F11 -> 240818.47
B22: Deployment support | C22: =INDEX(PhaseHours,7) -> 400 | D22: =IF(TotalBaseHrs>0,C22/TotalBaseHrs,0) -> 0.027923985 | E22: =INDEX(PhaseCost,7) -> 25760 | F22: =IF(C22>0,INDEX(PhStart,7)&" - "&INDEX(PhEnd,7),"") -> 13 - 34 | H22: =Cost!B12 -> Engineer | I22: =Cost!C12 -> India | J22: =Cost!D12 -> 4823.5857 | K22: =Cost!E12 -> 50 | L22: =Cost!F12 -> 241179.29
B23: Hypercare | C23: =INDEX(PhaseHours,8) -> 320 | D23: =IF(TotalBaseHrs>0,C23/TotalBaseHrs,0) -> 0.022339188 | E23: =INDEX(PhaseCost,8) -> 19520 | F23: =IF(C23>0,INDEX(PhStart,8)&" - "&INDEX(PhEnd,8),"") -> 27 - 36 | H23: =Cost!B13 -> QA engineer | I23: =Cost!C13 -> India | J23: =Cost!D13 -> 1288 | K23: =Cost!E13 -> 57.5 | L23: =Cost!F13 -> 74060
B24: Security, operations & handover | C24: =INDEX(PhaseHours,9) -> 351 | D24: =IF(TotalBaseHrs>0,C24/TotalBaseHrs,0) -> 0.024503297 | E24: =INDEX(PhaseCost,9) -> 23446.8 | F24: =IF(C24>0,INDEX(PhStart,9)&" - "&INDEX(PhEnd,9),"") -> 9 - 34 | H24: Total | J24: =RoleHrsTotal -> 14324.603 | L24: =RoleCostTotal -> 900380.84
B25: AI readiness | C25: =INDEX(PhaseHours,10) -> 128 | D25: =IF(TotalBaseHrs>0,C25/TotalBaseHrs,0) -> 0.0089356753 | E25: =INDEX(PhaseCost,10) -> 8345.6 | F25: =IF(C25>0,INDEX(PhStart,10)&" - "&INDEX(PhEnd,10),"") -> 9 - 28
B26: Project management | C26: =INDEX(PhaseHours,11) -> 1440 | D26: =IF(TotalBaseHrs>0,C26/TotalBaseHrs,0) -> 0.10052635 | E26: =INDEX(PhaseCost,11) -> 118080 | F26: =IF(C26>0,INDEX(PhStart,11)&" - "&INDEX(PhEnd,11),"") -> 1 - 36
B27: Base effort | C27: =TotalBaseHrs -> 14324.603 | E27: =BaseCost -> 900380.84 | H27: Key dates
B28: Contingency | C28: =ContHrs -> 2596.1602 | E28: =ContCost -> 163183.08 | H28: Milestone | I28: Week | J28: Date
B29: Risk reserve | C29: =RiskHrs -> 90 | E29: =RiskCost -> 5656.9998 | H29: =INDEX(MilestoneLabels,1) -> Assessment sign-off | I29: =INDEX(MilestoneWeeks,1) -> 6 | J29: =INDEX(MilestoneDates,1) -> 46437
B30: Discount | E30: =DiscountAmt -> 0 | H30: =INDEX(MilestoneLabels,2) -> Architecture sign-off | I30: =INDEX(MilestoneWeeks,2) -> 5 | J30: =INDEX(MilestoneDates,2) -> 46430
B31: Pass-throughs | E31: =PassThrough -> 0 | H31: =INDEX(MilestoneLabels,3) -> First semantic models ready | I31: =INDEX(MilestoneWeeks,3) -> 8 | J31: =INDEX(MilestoneDates,3) -> 46451
B32: FIXED PRICE | C32: =TotalHrs -> 17010.763 | E32: =FixedPrice -> 1069220.9 | H32: =INDEX(MilestoneLabels,4) -> First report iteration starts | I32: =INDEX(MilestoneWeeks,4) -> 9 | J32: =INDEX(MilestoneDates,4) -> 46458
H33: =INDEX(MilestoneLabels,5) -> Last report iteration ends | I33: =INDEX(MilestoneWeeks,5) -> 28 | J33: =INDEX(MilestoneDates,5) -> 46598
H34: =INDEX(MilestoneLabels,6) -> Wave 1 go-live | I34: =INDEX(MilestoneWeeks,6) -> 26 | J34: =INDEX(MilestoneDates,6) -> 46584
H35: =INDEX(MilestoneLabels,7) -> Wave 2 go-live | I35: =INDEX(MilestoneWeeks,7) -> 34 | J35: =INDEX(MilestoneDates,7) -> 46640
B36: Effort by migration pair | H36: =INDEX(MilestoneLabels,8) -> Wave 3 go-live | I36: =INDEX(MilestoneWeeks,8) | J36: =INDEX(MilestoneDates,8)
B37: Pair | C37: Source -> target | D37: Reports to build | E37: Hours (incl. shared) | F37: Contingency % | H37: =INDEX(MilestoneLabels,9) -> Wave 4 go-live | I37: =INDEX(MilestoneWeeks,9) | J37: =INDEX(MilestoneDates,9)
B38: =IF(Effort!C7=1,Effort!B7,"") -> Finance OBIEE to Power BI | C38: =IF(Effort!C7=1,Scope!$C7&" -> "&Scope!$D7,"") -> OBIEE -> Power BI | D38: =IF(Effort!C7=1,Effort!R7,"") -> 280 | E38: =IF(Effort!C7=1,Effort!AP7,"") -> 9849.9056 | F38: =IF(Effort!C7=1,Effort!AN7,"") -> 0.15 | H38: =INDEX(MilestoneLabels,10) -> Wave 5 go-live | I38: =INDEX(MilestoneWeeks,10) | J38: =INDEX(MilestoneDates,10)
B39: =IF(Effort!C8=1,Effort!B8,"") -> Sales Tableau to Power BI | C39: =IF(Effort!C8=1,Scope!$C8&" -> "&Scope!$D8,"") -> Tableau -> Power BI | D39: =IF(Effort!C8=1,Effort!R8,"") -> 175 | E39: =IF(Effort!C8=1,Effort!AP8,"") -> 4474.6973 | F39: =IF(Effort!C8=1,Effort!AN8,"") -> 0.25 | H39: =INDEX(MilestoneLabels,11) -> Hypercare exit / programme end | I39: =INDEX(MilestoneWeeks,11) -> 36 | J39: =INDEX(MilestoneDates,11) -> 46654
B40: =IF(Effort!C9=1,Effort!B9,"") | C40: =IF(Effort!C9=1,Scope!$C9&" -> "&Scope!$D9,"") | D40: =IF(Effort!C9=1,Effort!R9,"") | E40: =IF(Effort!C9=1,Effort!AP9,"") | F40: =IF(Effort!C9=1,Effort!AN9,"")
B41: =IF(Effort!C10=1,Effort!B10,"") | C41: =IF(Effort!C10=1,Scope!$C10&" -> "&Scope!$D10,"") | D41: =IF(Effort!C10=1,Effort!R10,"") | E41: =IF(Effort!C10=1,Effort!AP10,"") | F41: =IF(Effort!C10=1,Effort!AN10,"")
B42: =IF(Effort!C11=1,Effort!B11,"") | C42: =IF(Effort!C11=1,Scope!$C11&" -> "&Scope!$D11,"") | D42: =IF(Effort!C11=1,Effort!R11,"") | E42: =IF(Effort!C11=1,Effort!AP11,"") | F42: =IF(Effort!C11=1,Effort!AN11,"")
B43: =IF(Effort!C12=1,Effort!B12,"") | C43: =IF(Effort!C12=1,Scope!$C12&" -> "&Scope!$D12,"") | D43: =IF(Effort!C12=1,Effort!R12,"") | E43: =IF(Effort!C12=1,Effort!AP12,"") | F43: =IF(Effort!C12=1,Effort!AN12,"")
B44: =IF(Effort!C13=1,Effort!B13,"") | C44: =IF(Effort!C13=1,Scope!$C13&" -> "&Scope!$D13,"") | D44: =IF(Effort!C13=1,Effort!R13,"") | E44: =IF(Effort!C13=1,Effort!AP13,"") | F44: =IF(Effort!C13=1,Effort!AN13,"")
B45: =IF(Effort!C14=1,Effort!B14,"") | C45: =IF(Effort!C14=1,Scope!$C14&" -> "&Scope!$D14,"") | D45: =IF(Effort!C14=1,Effort!R14,"") | E45: =IF(Effort!C14=1,Effort!AP14,"") | F45: =IF(Effort!C14=1,Effort!AN14,"")
B46: =IF(Effort!C15=1,Effort!B15,"") | C46: =IF(Effort!C15=1,Scope!$C15&" -> "&Scope!$D15,"") | D46: =IF(Effort!C15=1,Effort!R15,"") | E46: =IF(Effort!C15=1,Effort!AP15,"") | F46: =IF(Effort!C15=1,Effort!AN15,"")
B47: =IF(Effort!C16=1,Effort!B16,"") | C47: =IF(Effort!C16=1,Scope!$C16&" -> "&Scope!$D16,"") | D47: =IF(Effort!C16=1,Effort!R16,"") | E47: =IF(Effort!C16=1,Effort!AP16,"") | F47: =IF(Effort!C16=1,Effort!AN16,"")
B48: =IF(Effort!C17=1,Effort!B17,"") | C48: =IF(Effort!C17=1,Scope!$C17&" -> "&Scope!$D17,"") | D48: =IF(Effort!C17=1,Effort!R17,"") | E48: =IF(Effort!C17=1,Effort!AP17,"") | F48: =IF(Effort!C17=1,Effort!AN17,"")
B49: =IF(Effort!C18=1,Effort!B18,"") | C49: =IF(Effort!C18=1,Scope!$C18&" -> "&Scope!$D18,"") | D49: =IF(Effort!C18=1,Effort!R18,"") | E49: =IF(Effort!C18=1,Effort!AP18,"") | F49: =IF(Effort!C18=1,Effort!AN18,"")
B50: =IF(Effort!C19=1,Effort!B19,"") | C50: =IF(Effort!C19=1,Scope!$C19&" -> "&Scope!$D19,"") | D50: =IF(Effort!C19=1,Effort!R19,"") | E50: =IF(Effort!C19=1,Effort!AP19,"") | F50: =IF(Effort!C19=1,Effort!AN19,"")
B51: =IF(Effort!C20=1,Effort!B20,"") | C51: =IF(Effort!C20=1,Scope!$C20&" -> "&Scope!$D20,"") | D51: =IF(Effort!C20=1,Effort!R20,"") | E51: =IF(Effort!C20=1,Effort!AP20,"") | F51: =IF(Effort!C20=1,Effort!AN20,"")
... B57: =IF(Effort!C26=1,Effort!B26,"") | C57: =IF(Effort!C26=1,Scope!$C26&" -> "&Scope!$D26,"") | D57: =IF(Effort!C26=1,Effort!R26,"") | E57: =IF(Effort!C26=1,Effort!AP26,"") | F57: =IF(Effort!C26=1,Effort!AN26,"")

Sheet Setup
A1: Setup
A2: Engagement-wide settings. Yellow cells are inputs; hover a cell for guidance.
B4: Engagement
B5: Client | C5: Example Client
B6: Opportunity | C6: BI modernisation programme
B7: Estimate version | C7: v2.0-draft
B8: Prepared by
B9: Estimate date | C9: 46308
B10: Currency | C10: USD
B11: Planned start date (Monday) | C11: 46391
B13: Delivery parameters
B14: Iteration length (weeks) | C14: 2
B15: Productive hours per person-week | C15: 40
B16: Holiday allowance (stretches calendar dates only) | C16: 0.04
B17: Engagement type | C17: Pure BI
B18: Solve mode | C18: Fix team, compute iterations
B19: Peak report-development team (FTE) - used when fixing team | C19: 10
B20: Development iterations - used when fixing iterations | C20: 8
B21: Ramp-up weeks (report development) | C21: 3
B22: Ramp-down weeks (report development) | C22: 3
B23: Assessment team (FTE) | C23: 3
B24: Architecture team (FTE) | C24: 2
B25: Architecture overlap with assessment | C25: 0.5
B26: Model lead time before report iterations (weeks) | C26: 2
B27: Headcount rounding step (0 = no rounding) | C27: 0.5
B28: PM FTE (pure BI engagements) | C28: 1
B30: SIT, UAT and deployment support (sized per development iteration)
B31: SIT weeks per iteration | C31: 1
B32: SIT minimum engineers | C32: 1
B33: SIT crew sizing (% of dev hours per iteration) | C33: 0.15
B34: SIT fixed hours per iteration (environments, regression) | C34: 8
B35: Final regression cycle (weeks) | C35: 1
B36: UAT support weeks per iteration | C36: 1
B37: UAT engineers when volume <= threshold | C37: 1
B38: UAT engineers when volume > threshold | C38: 2
B39: Volume threshold (report pages per iteration) | C39: 150
B40: Final UAT cycle (weeks) | C40: 1
B41: Deployment support weeks per iteration | C41: 1
B42: Deployment support engineers | C42: 1
B43: Deployment pipeline available? | C43: Yes
B44: Hypercare weeks per go-live | C44: 2
B45: Hypercare crew (FTE) | C45: 2
B47: Automation by phase (global; pairs may override assessment, semantic and report automation on Scope)
B48: Phase | C48: Automation % | D48: Automatable cap | E48: Effective saving
B49: Assessment | C49: 0 | D49: =CapAssess -> 0.6 | E49: =C49*D49 -> 0
B50: Semantic model | C50: 0 | D50: =CapSem -> 0.4 | E50: =C50*D50 -> 0
B51: Report development | C51: 0 | D51: =CapRep -> 0.6 | E51: =C51*D51 -> 0
B52: SIT | C52: 0 | D52: =CapSIT -> 0.3 | E52: =C52*D52 -> 0
B53: UAT support | C53: 0 | D53: =CapUAT -> 0.2 | E53: =C53*D53 -> 0
B54: Deployment support | C54: 0 | D54: =CapDep -> 0.6 | E54: =C54*D54 -> 0
B56: Cost
B57: Cost mode | C57: Role mix
B58: Blended rate (USD/h) - used in Blended mode | C58: 60
B59: Discount on bill rates | C59: 0
B60: Pass-through: tools / licences (USD) | C60: 0
B61: Pass-through: travel (USD) | C61: 0
B62: Pass-through: other (USD) | C62: 0
B64: Payment milestones (must total 100%)
B65: Contract signature | C65: 0.1
B66: Assessment sign-off | C66: 0.15
B67: Architecture sign-off | C67: 0.1
B68: Mid-development | C68: 0.25
B69: Final go-live | C69: 0.3
B70: Hypercare exit | C70: 0.1
B71: Total | C71: =SUM(C65:C70) -> 1

Sheet Scope
A1: Scope
A2: One row per migration pair (source BI tool + data platform -> target BI tool + data platform). Rows with a source, target and report count are active.
A3: Mixes are fractions that total 100% per row. Retired + Consolidated <= 100%; Derived applies to what remains. Blank automation override = use Setup.
A5: Pair | H5: Report inventory | L5: Report complexity | P5: Rationalisation | S5: Semantic layer | Y5: Security, ops, AI | AC5: Overrides and confidence
A6: # | B6: Pair name | C6: Source BI tool | D6: Target BI tool | E6: Source data platform | F6: Target data platform | G6: Release wave (1-5) | H6: Reports in inventory | I6: Avg pages (sheets) per report | J6: % paginated | K6: % with custom SQL | L6: % Simple | M6: % Medium | N6: % Complex | O6: % Very Complex | P6: % Retired | Q6: % Consolidated | R6: % Derived | S6: Source semantic models / SQL datasets | T6: Model % Simple | U6: Model % Medium | V6: Model % Complex | W6: Model % Very Complex | X6: Target semantic models | Y6: Security model | Z6: Schedules / subscriptions / alerts | AA6: User groups | AB6: AI readiness | AC6: Pair factor override | AD6: Override reason | AE6: Automation override - Assessment | AF6: Automation override - Semantic | AG6: Automation override - Reports | AH6: Input confidence | AI6: Notes
A7: 1 | B7: Finance OBIEE to Power BI | C7: OBIEE | D7: Power BI | E7: Oracle | F7: Snowflake | G7: 1 | H7: 400 | I7: 3 | J7: 0.1 | K7: 0.15 | L7: 0.4 | M7: 0.35 | N7: 0.2 | O7: 0.05 | P7: 0.2 | Q7: 0.1 | R7: 0.1 | S7: 12 | T7: 0.3 | U7: 0.4 | V7: 0.2 | W7: 0.1 | X7: 8 | Y7: Row-level | Z7: 150 | AA7: 20 | AB7: Basic | AH7: Customer inventory | AI7: Example row - replace with real scope
A8: 2 | B8: Sales Tableau to Power BI | C8: Tableau | D8: Power BI | E8: Amazon Redshift | F8: Snowflake | G8: 2 | H8: 250 | I8: 2 | J8: 0 | K8: 0.1 | L8: 0.5 | M8: 0.3 | N8: 0.15 | O8: 0.05 | P8: 0.25 | Q8: 0.05 | R8: 0.1 | S8: 40 | T8: 0.5 | U8: 0.3 | V8: 0.15 | W8: 0.05 | X8: 10 | Y8: Role-based | Z8: 60 | AA8: 10 | AB8: None | AH8: Verbal estimate | AI8: Example row - replace with real scope
A9: 3
A10: 4
A11: 5
A12: 6
A13: 7
A14: 8
A15: 9
A16: 10
A17: 11
A18: 12
A19: 13
A20: 14
... A26: 20

Sheet Risks
A1: Risks
A2: Named risks priced at expected value (impact hours x probability). Example rows - replace with the engagement's risks.
A5: # | B5: Risk | C5: Impact (hours) | D5: Probability | E5: Expected hours | F5: Owner | G5: Mitigation
A6: 1 | B6: Target data platform tables not ready when report iterations start | C6: 200 | D6: 0.3 | E6: =N(C6)*N(D6) -> 60 | F6: Customer | G6: Model-lead gate; mock data for unit tests
A7: 2 | B7: Custom visuals / extensions with no target equivalent | C7: 120 | D7: 0.25 | E7: =N(C7)*N(D7) -> 30 | F7: BI lead | G7: Identify in assessment; agree alternatives
A8: 3 | E8: =N(C8)*N(D8) -> 0
A9: 4 | E9: =N(C9)*N(D9) -> 0
A10: 5 | E10: =N(C10)*N(D10) -> 0
A11: 6 | E11: =N(C11)*N(D11) -> 0
A12: 7 | E12: =N(C12)*N(D12) -> 0
A13: 8 | E13: =N(C13)*N(D13) -> 0
A14: 9 | E14: =N(C14)*N(D14) -> 0
A15: 10 | E15: =N(C15)*N(D15) -> 0
A16: 11 | E16: =N(C16)*N(D16) -> 0
A17: 12 | E17: =N(C17)*N(D17) -> 0
A18: 13 | E18: =N(C18)*N(D18) -> 0
A19: 14 | E19: =N(C19)*N(D19) -> 0
A20: 15 | E20: =N(C20)*N(D20) -> 0
D21: Total | E21: =SUM(E6:E20) -> 90

Sheet Roles
A1: Roles
A2: Plan roles (each priced from one rate-card row) and the share of each phase's hours carried by each role.
A4: Plan roles
A5: # | B5: Plan role | C5: Rate-card key (Role | Grade | Location) | D5: Rate (USD/h) | E5: Location
A6: 1 | B6: Delivery manager / PM | C6: MSE I | G12 | India | D6: =IFERROR(INDEX(RateVals,MATCH(C6,RateKeys,0)),0) -> 82 | E6: =IFERROR(INDEX(RateLocs,MATCH(C6,RateKeys,0)),"") -> India
A7: 2 | B7: Onsite architect | C7: Architect II | G12 | USA | D7: =IFERROR(INDEX(RateVals,MATCH(C7,RateKeys,0)),0) -> 185 | E7: =IFERROR(INDEX(RateLocs,MATCH(C7,RateKeys,0)),"") -> USA
A8: 3 | B8: Solution architect | C8: Sr. Architect I | G13 | India | D8: =IFERROR(INDEX(RateVals,MATCH(C8,RateKeys,0)),0) -> 87 | E8: =IFERROR(INDEX(RateLocs,MATCH(C8,RateKeys,0)),"") -> India
A9: 4 | B9: BI architect | C9: Architect II | G11 | India | D9: =IFERROR(INDEX(RateVals,MATCH(C9,RateKeys,0)),0) -> 70 | E9: =IFERROR(INDEX(RateLocs,MATCH(C9,RateKeys,0)),"") -> India
A10: 5 | B10: Lead | C10: Lead II | G11 | India | D10: =IFERROR(INDEX(RateVals,MATCH(C10,RateKeys,0)),0) -> 70 | E10: =IFERROR(INDEX(RateLocs,MATCH(C10,RateKeys,0)),"") -> India
A11: 6 | B11: Sr. engineer | C11: Sr. Engineer II | G10 | India | D11: =IFERROR(INDEX(RateVals,MATCH(C11,RateKeys,0)),0) -> 62 | E11: =IFERROR(INDEX(RateLocs,MATCH(C11,RateKeys,0)),"") -> India
A12: 7 | B12: Engineer | C12: Engineer II | G8 | India | D12: =IFERROR(INDEX(RateVals,MATCH(C12,RateKeys,0)),0) -> 50 | E12: =IFERROR(INDEX(RateLocs,MATCH(C12,RateKeys,0)),"") -> India
A13: 8 | B13: QA engineer | C13: Sr. Engineer I | G9 | India | D13: =IFERROR(INDEX(RateVals,MATCH(C13,RateKeys,0)),0) -> 57.5 | E13: =IFERROR(INDEX(RateLocs,MATCH(C13,RateKeys,0)),"") -> India
A16: Role mix by phase (share of phase hours; each row must total 100%)
A17: # | B17: Phase | C17: =B6 -> Delivery manager / PM | D17: =B7 -> Onsite architect | E17: =B8 -> Solution architect | F17: =B9 -> BI architect | G17: =B10 -> Lead | H17: =B11 -> Sr. engineer | I17: =B12 -> Engineer | J17: =B13 -> QA engineer | K17: Total
A18: 1 | B18: Initiation & assessment | C18: 0 | D18: 0.2 | E18: 0.3 | F18: 0.3 | G18: 0.2 | H18: 0 | I18: 0 | J18: 0 | K18: =SUM(C18:J18) -> 1
A19: 2 | B19: Architecture & design | C19: 0 | D19: 0.25 | E19: 0.4 | F19: 0.35 | G19: 0 | H19: 0 | I19: 0 | J19: 0 | K19: =SUM(C19:J19) -> 1
A20: 3 | B20: Semantic model build & consolidation | C20: 0 | D20: 0 | E20: 0 | F20: 0.15 | G20: 0.15 | H20: 0.5 | I20: 0.2 | J20: 0 | K20: =SUM(C20:J20) -> 1
A21: 4 | B21: Report development & unit validation | C21: 0 | D21: 0 | E21: 0 | F21: 0 | G21: 0.1 | H21: 0.3 | I21: 0.6 | J21: 0 | K21: =SUM(C21:J21) -> 1
A22: 5 | B22: SIT & optimization | C22: 0 | D22: 0 | E22: 0 | F22: 0 | G22: 0.1 | H22: 0 | I22: 0.2 | J22: 0.7 | K22: =SUM(C22:J22) -> 1
A23: 6 | B23: UAT support | C23: 0 | D23: 0 | E23: 0 | F23: 0 | G23: 0.2 | H23: 0.4 | I23: 0.4 | J23: 0 | K23: =SUM(C23:J23) -> 1
A24: 7 | B24: Deployment support | C24: 0 | D24: 0 | E24: 0 | F24: 0 | G24: 0.3 | H24: 0.7 | I24: 0 | J24: 0 | K24: =SUM(C24:J24) -> 1
A25: 8 | B25: Hypercare | C25: 0 | D25: 0 | E25: 0 | F25: 0 | G25: 0.25 | H25: 0.5 | I25: 0.25 | J25: 0 | K25: =SUM(C25:J25) -> 1
A26: 9 | B26: Security, operations & handover | C26: 0 | D26: 0 | E26: 0 | F26: 0.3 | G26: 0.3 | H26: 0.4 | I26: 0 | J26: 0 | K26: =SUM(C26:J26) -> 1
A27: 10 | B27: AI readiness | C27: 0 | D27: 0 | E27: 0 | F27: 0.4 | G27: 0 | H27: 0.6 | I27: 0 | J27: 0 | K27: =SUM(C27:J27) -> 1
A28: 11 | B28: Project management | C28: 1 | D28: 0 | E28: 0 | F28: 0 | G28: 0 | H28: 0 | I28: 0 | J28: 0 | K28: =SUM(C28:J28) -> 1

Sheet Rates
A1: Rates
A2: Rate card (bill rates, USD per hour) as provided. Key = Role | Grade | Location is what the Roles tab selects.
A4: Role | B4: Grade | C4: Location | D4: Rate (USD/h) | E4: Key | G4: Notes
A5: MSE II | B5: G13 | C5: India | D5: 87 | E5: =IF(A5="","",A5&" | "&B5&" | "&C5) -> MSE II | G13 | India | G5: Source: rate card supplied by the user (bill rates, USD/h). Lead I rows added from the requirements review. MSE = Manager Software Engineer.
A6: MSE I | B6: G12 | C6: India | D6: 82 | E6: =IF(A6="","",A6&" | "&B6&" | "&C6) -> MSE I | G12 | India
A7: Architect II | B7: G12 | C7: India | D7: 70 | E7: =IF(A7="","",A7&" | "&B7&" | "&C7) -> Architect II | G12 | India
A8: Architect I | B8: G11 | C8: India | D8: 65 | E8: =IF(A8="","",A8&" | "&B8&" | "&C8) -> Architect I | G11 | India
A9: Lead II | B9: G11 | C9: India | D9: 70 | E9: =IF(A9="","",A9&" | "&B9&" | "&C9) -> Lead II | G11 | India
A10: Lead II | B10: G10 | C10: India | D10: 70 | E10: =IF(A10="","",A10&" | "&B10&" | "&C10) -> Lead II | G10 | India
A11: Lead I | B11: G10 | C11: India | D11: 62 | E11: =IF(A11="","",A11&" | "&B11&" | "&C11) -> Lead I | G10 | India
A12: Lead I | B12: G9 | C12: India | D12: 62 | E12: =IF(A12="","",A12&" | "&B12&" | "&C12) -> Lead I | G9 | India
A13: Sr. Engineer II | B13: G10 | C13: India | D13: 62 | E13: =IF(A13="","",A13&" | "&B13&" | "&C13) -> Sr. Engineer II | G10 | India
A14: Sr. Engineer II | B14: G9 | C14: India | D14: 62 | E14: =IF(A14="","",A14&" | "&B14&" | "&C14) -> Sr. Engineer II | G9 | India
A15: Sr. Engineer I | B15: G9 | C15: India | D15: 57.5 | E15: =IF(A15="","",A15&" | "&B15&" | "&C15) -> Sr. Engineer I | G9 | India
A16: Sr. Engineer I | B16: G8 | C16: India | D16: 57.5 | E16: =IF(A16="","",A16&" | "&B16&" | "&C16) -> Sr. Engineer I | G8 | India
A17: Engineer II | B17: G8 | C17: India | D17: 50 | E17: =IF(A17="","",A17&" | "&B17&" | "&C17) -> Engineer II | G8 | India
... A28: MSE II | B28: G13 | C28: USA | D28: 210 | E28: =IF(A28="","",A28&" | "&B28&" | "&C28) -> MSE II | G13 | USA
E29: =IF(A29="","",A29&" | "&B29&" | "&C29)
E30: =IF(A30="","",A30&" | "&B30&" | "&C30)
E31: =IF(A31="","",A31&" | "&B31&" | "&C31)
E32: =IF(A32="","",A32&" | "&B32&" | "&C32)
E33: =IF(A33="","",A33&" | "&B33&" | "&C33)
E34: =IF(A34="","",A34&" | "&B34&" | "&C34)
E35: =IF(A35="","",A35&" | "&B35&" | "&C35)
E36: =IF(A36="","",A36&" | "&B36&" | "&C36)
E37: =IF(A37="","",A37&" | "&B37&" | "&C37)
E38: =IF(A38="","",A38&" | "&B38&" | "&C38)

Sheet Lists
A1: Lists
A2: Reference lists behind the drop-downs. BI team maintains; add rows in the blank space - no formula changes needed.
A4: BI tools and archetypes | D4: Archetypes | F4: Pair factor fallback by archetype (source row x target column) - proposal, BI team to confirm | L4: Known pair factors (seeded from old calculator BD7:BD21) | Q4: Data platforms
A5: BI tool | B5: Archetype | D5: Archetype | F5: Source \ Target | G5: Enterprise semantic-layer | H5: Paginated / pixel-perfect | I5: Modern visual / self-service | J5: Modern code-based semantic | L5: Source BI tool | M5: Target BI tool | N5: Factor | O5: Key | Q5: Data platform | S5: YesNo | T5: EngTypes | U5: SolveModes | V5: CostModes | W5: IterLens
A6: SAP BusinessObjects | B6: Enterprise semantic-layer | D6: Enterprise semantic-layer | F6: Enterprise semantic-layer | G6: 1.1 | H6: 1 | I6: 1.1 | J6: 1.2 | L6: OBIEE | M6: Power BI | N6: 1 | O6: =IF(L6="","",L6&"|"&M6) -> OBIEE|Power BI | Q6: Oracle | S6: Yes | T6: Pure BI | U6: Fix team, compute iterations | V6: Role mix | W6: 1
A7: OBIEE | B7: Enterprise semantic-layer | D7: Paginated / pixel-perfect | F7: Paginated / pixel-perfect | G7: 1 | H7: 0.9 | I7: 1.05 | J7: 1.2 | L7: Cognos | M7: Power BI | N7: 1.1 | O7: =IF(L7="","",L7&"|"&M7) -> Cognos|Power BI | Q7: SQL Server | S7: No | T7: Bundled with ETL/EDW programme | U7: Fix iterations, compute team | V7: Blended | W7: 2
A8: Oracle Analytics Server | B8: Enterprise semantic-layer | D8: Modern visual / self-service | F8: Modern visual / self-service | G8: 1.1 | H8: 1 | I8: 0.95 | J8: 1.1 | L8: SAP BusinessObjects | M8: Power BI | N8: 1.25 | O8: =IF(L8="","",L8&"|"&M8) -> SAP BusinessObjects|Power BI | Q8: Teradata
A9: MicroStrategy | B9: Enterprise semantic-layer | D9: Modern code-based semantic | F9: Modern code-based semantic | G9: 1 | H9: 1 | I9: 1 | J9: 1 | L9: Tableau | M9: Power BI | N9: 0.95 | O9: =IF(L9="","",L9&"|"&M9) -> Tableau|Power BI | Q9: Netezza
A10: Cognos | B10: Enterprise semantic-layer | L10: SSRS | M10: Power BI | N10: 1.05 | O10: =IF(L10="","",L10&"|"&M10) -> SSRS|Power BI | Q10: DB2
A11: SSRS | B11: Paginated / pixel-perfect | L11: OBIEE | M11: QuickSight | N11: 1.2 | O11: =IF(L11="","",L11&"|"&M11) -> OBIEE|QuickSight | Q11: SAP HANA
A12: Crystal Reports | B12: Paginated / pixel-perfect | F12: Semantic-model approach by archetype (source row x target column) | L12: Cognos | M12: QuickSight | N12: 1.25 | O12: =IF(L12="","",L12&"|"&M12) -> Cognos|QuickSight | Q12: Snowflake
A13: Tableau | B13: Modern visual / self-service | F13: Source \ Target | G13: Enterprise semantic-layer | H13: Paginated / pixel-perfect | I13: Modern visual / self-service | J13: Modern code-based semantic | L13: Tableau | M13: QuickSight | N13: 1.1 | O13: =IF(L13="","",L13&"|"&M13) -> Tableau|QuickSight | Q13: Databricks
A14: Power BI | B14: Modern visual / self-service | F14: Enterprise semantic-layer | G14: Redesign | H14: Redesign | I14: Redesign | J14: Author (LookML) | L14: SSRS | M14: QuickSight | N14: 1.2 | O14: =IF(L14="","",L14&"|"&M14) -> SSRS|QuickSight | Q14: Google BigQuery
A15: QuickSight | B15: Modern visual / self-service | F15: Paginated / pixel-perfect | G15: Shared datasets | H15: Shared datasets | I15: Shared datasets | J15: Author (LookML) | L15: SAP BusinessObjects | M15: QuickSight | N15: 1.3 | O15: =IF(L15="","",L15&"|"&M15) -> SAP BusinessObjects|QuickSight | Q15: Amazon Redshift
A16: Qlik Sense | B16: Modern visual / self-service | F16: Modern visual / self-service | G16: Redesign | H16: Shared datasets | I16: Translate | J16: Author (LookML) | L16: Cognos | M16: Looker | N16: 1.25 | O16: =IF(L16="","",L16&"|"&M16) -> Cognos|Looker | Q16: Azure Synapse
A17: QlikView | B17: Modern visual / self-service | F17: Modern code-based semantic | G17: Translate | H17: Shared datasets | I17: Translate | J17: Translate | L17: OBIEE | M17: Looker | N17: 1.2 | O17: =IF(L17="","",L17&"|"&M17) -> OBIEE|Looker | Q17: Microsoft Fabric
A18: Looker Studio | B18: Modern visual / self-service | L18: Tableau | M18: Looker | N18: 1.1 | O18: =IF(L18="","",L18&"|"&M18) -> Tableau|Looker | Q18: PostgreSQL
A19: Looker | B19: Modern code-based semantic | L19: SSRS | M19: Looker | N19: 1.2 | O19: =IF(L19="","",L19&"|"&M19) -> SSRS|Looker | Q19: Other
L20: SAP BusinessObjects | M20: Looker | N20: 1.3 | O20: =IF(L20="","",L20&"|"&M20) -> SAP BusinessObjects|Looker
O21: =IF(L21="","",L21&"|"&M21)
O22: =IF(L22="","",L22&"|"&M22)
O23: =IF(L23="","",L23&"|"&M23)
O24: =IF(L24="","",L24&"|"&M24)
O25: =IF(L25="","",L25&"|"&M25)
O26: =IF(L26="","",L26&"|"&M26)
O27: =IF(L27="","",L27&"|"&M27)
O28: =IF(L28="","",L28&"|"&M28)
O29: =IF(L29="","",L29&"|"&M29)
O30: =IF(L30="","",L30&"|"&M30)
O31: =IF(L31="","",L31&"|"&M31)
O32: =IF(L32="","",L32&"|"&M32)
... O45: =IF(L45="","",L45&"|"&M45)

Sheet Baseline
A1: Baseline
A2: Reference values used by the engine. Status shows where each value came from. Change values here only with BI-team sign-off.
A4: Parameter | B4: Value | C4: Unit | D4: Status | E4: Source / note
A6: Report development
A7: Hours per report page - Simple | B7: 3.625 | C7: h / page | D7: Carried | E7: Old calculator F5
A8: Hours per report page - Medium | B8: 6.625 | C8: h / page | D8: Carried | E8: Old calculator F6
A9: Hours per report page - Complex | B9: 9.125 | C9: h / page | D9: Carried | E9: Old calculator F7
A10: Hours per report page - Very Complex | B10: 12.625 | C10: h / page | D10: Carried | E10: Old calculator F8
A11: Hours per derived (similar) report page | B11: 1 | C11: h / page | D11: Carried | E11: Old calculator F9
A12: Learning gain - quarter 1 of iterations | B12: 0 | C12: % saving | D12: Reshaped | E12: User decision 0/10/15/20% (old file 0/15/20/25% by page-tier phase). Applied by quarter of the iteration run.
A13: Learning gain - quarter 2 of iterations | B13: 0.1 | C13: % saving | D13: Reshaped | E13: User decision 0/10/15/20% (old file 0/15/20/25% by page-tier phase). Applied by quarter of the iteration run.
A14: Learning gain - quarter 3 of iterations | B14: 0.15 | C14: % saving | D14: Reshaped | E14: User decision 0/10/15/20% (old file 0/15/20/25% by page-tier phase). Applied by quarter of the iteration run.
A15: Learning gain - quarter 4 of iterations | B15: 0.2 | C15: % saving | D15: Reshaped | E15: User decision 0/10/15/20% (old file 0/15/20/25% by page-tier phase). Applied by quarter of the iteration run.
A16: Average learning gain (effort is spread evenly over iterations) | B16: =AVERAGE(LearnQ) -> 0.1125 | D16: Calculated
A17: Paginated report effort factor | B17: 1.2 | C17: x | D17: New proposal | E17: Paginated / pixel-perfect pages vs interactive pages
A18: Data-platform change uplift on custom-SQL reports | B18: 0.25 | C18: % uplift | D18: New proposal | E18: Applied to the custom-SQL share when source and target data platforms differ
A19: Merge hours per consolidated report | B19: 2 | C19: h / report | D19: New proposal | E19: Effort to fold a consolidated report into the report that absorbs it
A21: Semantic models
A22: Model build hours - Simple | B22: 80 | C22: h / model | D22: New proposal | E22: Replaces old 16/40/80 by reports-per-model (E16); SOP minimum 80 h
A23: Model build hours - Medium | B23: 120 | C23: h / model | D23: New proposal | E23: Replaces old 16/40/80 by reports-per-model (E16); SOP minimum 80 h
A24: Model build hours - Complex | B24: 200 | C24: h / model | D24: New proposal | E24: Replaces old 16/40/80 by reports-per-model (E16); SOP minimum 80 h
A25: Model build hours - Very Complex | B25: 320 | C25: h / model | D25: New proposal | E25: Replaces old 16/40/80 by reports-per-model (E16); SOP minimum 80 h
A26: Consolidation hours per source model merged | B26: 16 | C26: h / model | D26: New proposal | E26: Applied to (source models - target models)
A27: Data-platform change uplift on semantic models | B27: 0.15 | C27: % uplift | D27: New proposal | E27: When source and target data platforms differ
A28: Redesign | B28: 1 | C28: share of build h | D28: New proposal | E28: Semantic-model approach share of full build hours
A29: Translate | B29: 0.4 | C29: share of build h | D29: New proposal | E29: Semantic-model approach share of full build hours
A30: Author (LookML) | B30: 1 | C30: share of build h | D30: New proposal | E30: Semantic-model approach share of full build hours
A31: Shared datasets | B31: 0.3 | C31: share of build h | D31: New proposal | E31: Semantic-model approach share of full build hours
A33: Initiation and assessment (interpolation anchors on inventory pages)
A34: Anchor | B34: Pages | C34: Initiation h | D34: Analysis h | E34: Source
A35: Anchor 1 | B35: 100 | C35: 40 | D35: 80 | E35: Reshaped: old tier values E14/E15 become straight-line anchors (no cliffs)
A36: Anchor 2 | B36: 500 | C36: 60 | D36: 160 | E36: Reshaped: old tier values E14/E15 become straight-line anchors (no cliffs)
A37: Anchor 3 | B37: 1000 | C37: 80 | D37: 240 | E37: Reshaped: old tier values E14/E15 become straight-line anchors (no cliffs)
A38: Anchor 4 | B38: 5000 | C38: 120 | D38: 360 | E38: Reshaped: old tier values E14/E15 become straight-line anchors (no cliffs)
A39: Anchor 5 | B39: 10000 | C39: 160 | D39: 480 | E39: Reshaped: old tier values E14/E15 become straight-line anchors (no cliffs)
A40: Assessment hours per source semantic model | B40: 4 | C40: h / model | D40: New proposal | E40: Inventorying universes / RPD subject areas / packages / SQL datasets
A42: Architecture, security, operations, AI readiness
A43: Architecture hours per distinct target BI tool | B43: 80 | C43: h / tool | D43: New proposal | E43: Tenant/workspace design, security, connectivity, CI/CD, performance, standards
A44: Architecture hours per migration pair | B44: 24 | C44: h / pair | D44: New proposal | E44: Pair-specific design decisions
A45: None | B45: 0 | C45: h / target model | D45: New proposal | E45: Security model build and testing per target semantic model
A46: Role-based | B46: 4 | C46: h / target model | D46: New proposal | E46: Security model build and testing per target semantic model
A47: Row-level | B47: 12 | C47: h / target model | D47: New proposal | E47: Security model build and testing per target semantic model
A48: Row + object-level | B48: 20 | C48: h / target model | D48: New proposal | E48: Security model build and testing per target semantic model
A49: Hours per schedule / subscription / alert | B49: 0.5 | C49: h / item | D49: New proposal | E49: Recreate in target
A50: Hours per user group | B50: 1 | C50: h / group | D50: New proposal | E50: Groups, workspace access
A51: Training and handover per pair | B51: 40 | C51: h / pair | D51: New proposal | E51: Demo, documentation, knowledge transfer
A52: None | B52: 0 | C52: h / target model | D52: Placeholder | E52: AI readiness (descriptions, synonyms, Copilot / Q&A / Amazon Q / Gemini set-up). No baseline yet - BI team to set.
A53: Basic | B53: 16 | C53: h / target model | D53: Placeholder | E53: AI readiness (descriptions, synonyms, Copilot / Q&A / Amazon Q / Gemini set-up). No baseline yet - BI team to set.
A54: Advanced | B54: 40 | C54: h / target model | D54: Placeholder | E54: AI readiness (descriptions, synonyms, Copilot / Q&A / Amazon Q / Gemini set-up). No baseline yet - BI team to set.
A56: Automation and deployment
A57: Automatable share cap - Assessment | B57: 0.6 | C57: % of phase | D57: User decision | E57: Max share of the phase automation can remove (requirements Q6)
A58: Automatable share cap - Semantic model | B58: 0.4 | C58: % of phase | D58: User decision | E58: Max share of the phase automation can remove (requirements Q6)
A59: Automatable share cap - Report development | B59: 0.6 | C59: % of phase | D59: User decision | E59: Max share of the phase automation can remove (requirements Q6)
A60: Automatable share cap - SIT | B60: 0.3 | C60: % of phase | D60: User decision | E60: Max share of the phase automation can remove (requirements Q6)
A61: Automatable share cap - UAT support | B61: 0.2 | C61: % of phase | D61: User decision | E61: Max share of the phase automation can remove (requirements Q6)
A62: Automatable share cap - Deployment support | B62: 0.6 | C62: % of phase | D62: User decision | E62: Max share of the phase automation can remove (requirements Q6)
A63: Automation tool set-up per pair (when any automation > 0) | B63: 40 | C63: h / pair | D63: New proposal | E63: Accelerator configuration and runs
A64: Manual deployment hours per report (no pipeline) | B64: 0.5 | C64: h / report | D64: Carried | E64: Old calculator E20
A66: Contingency and controls
A67: Tool-assessed | B67: 0.1 | C67: contingency | D67: New proposal | E67: Replaces old flat 15% (B39). Driven by each pair's input confidence.
A68: Customer inventory | B68: 0.15 | C68: contingency | D68: New proposal | E68: Replaces old flat 15% (B39). Driven by each pair's input confidence.
A69: Verbal estimate | B69: 0.25 | C69: contingency | D69: New proposal | E69: Replaces old flat 15% (B39). Driven by each pair's input confidence.
A70: Pair factor override - minimum | B70: 0.7 | C70: x | D70: New proposal | E70: Overrides are clamped to this range
A71: Pair factor override - maximum | B71: 2 | C71: x | D71: New proposal
A72: Plan reconciliation tolerance | B72: 0.05 | C72: +/- % | D72: New proposal | E72: Plan hours vs estimate hours

Sheet Effort
A1: Effort
A2: Hours per pair and per phase. Locked - every value is calculated from Scope, Setup and Baseline.
A6: # | B6: Pair | C6: Active | D6: Source archetype | E6: Target archetype | F6: Suggested pair factor | G6: Pair factor used | H6: Semantic approach | I6: Approach share | J6: Data platform change | K6: Report platform uplift | L6: Model platform uplift | M6: Report-type factor | N6: Saving - assessment | O6: Saving - semantic | P6: Saving - reports | Q6: Inventory pages | R6: Reports to build | S6: Derived reports | T6: Full-effort reports | U6: Full-effort pages | V6: Derived pages | W6: Consolidated reports | X6: Mix-weighted h / page | Y6: Report base hours | Z6: Merge hours | AA6: REPORT DEVELOPMENT h | AB6: Target models | AC6: Mix-weighted h / model | AD6: Model build hours | AE6: Consolidation hours | AF6: SEMANTIC MODEL h | AG6: ASSESSMENT (analysis) h | AH6: SECURITY, OPS & HANDOVER h | AI6: AI READINESS h | AJ6: Automation set-up h | AK6: Pair direct hours | AL6: Development hours (semantic + reports) | AM6: Wave | AN6: Contingency % | AO6: Allocated programme hours | AP6: PAIR TOTAL h (before contingency) | AQ6: Contingency h | AR6: Flag: mix not 100% | AS6: Flag: rationalisation > 100% | AT6: Flag: unmapped tool | AU6: Flag: override without reason | AV6: Flag: pages < 1 or no target model
A7: =Scope!$A7 -> 1 | B7: =IF(Scope!$B7="","",Scope!$B7) -> Finance OBIEE to Power BI | C7: =IF(AND(Scope!$C7<>"",Scope!$D7<>"",N(Scope!$H7)>0),1,0) -> 1 | D7: =IF(C7=0,"",IFERROR(INDEX(ToolArch,MATCH(Scope!$C7,ToolNames,0)),"Unmapped")) -> Enterprise semantic-layer | E7: =IF(C7=0,"",IFERROR(INDEX(ToolArch,MATCH(Scope!$D7,ToolNames,0)),"Unmapped")) -> Modern visual / self-service | F7: =IF(C7=0,0,IFERROR(INDEX(KnownFactor,MATCH(Scope!$C7&"|"&Scope!$D7,KnownKey,0)),IFERROR(INDEX(ArchFactor,MATCH(D7,ArchNames,0),MATCH(E7,ArchNames,0)),1))) -> 1 | G7: =IF(C7=0,0,IF(N(Scope!$AC7)>0,MIN(FactorMax,MAX(FactorMin,Scope!$AC7)),F7)) -> 1 | H7: =IF(C7=0,"",IFERROR(INDEX(ApproachMatrix,MATCH(D7,ArchNames,0),MATCH(E7,ArchNames,0)),"Redesign")) -> Redesign | I7: =IF(C7=0,0,IFERROR(INDEX(ApproachShares,MATCH(H7,ApproachNames,0)),1)) -> 1 | J7: =IF(AND(C7=1,Scope!$E7<>"",Scope!$F7<>"",Scope!$E7<>Scope!$F7),1,0) -> 1 | K7: =1+J7*N(Scope!$K7)*DPRepUplift -> 1.0375 | L7: =1+J7*DPModelUplift -> 1.15 | M7: =1+N(Scope!$J7)*(PaginatedFactor-1) -> 1.02 | N7: =IF(Scope!$AE7="",AutoAssess,Scope!$AE7)*CapAssess -> 0 | O7: =IF(Scope!$AF7="",AutoSem,Scope!$AF7)*CapSem -> 0 | P7: =IF(Scope!$AG7="",AutoRep,Scope!$AG7)*CapRep -> 0 | Q7: =C7*N(Scope!$H7)*N(Scope!$I7) -> 1200 | R7: =C7*N(Scope!$H7)*MAX(0,1-N(Scope!$P7)-N(Scope!$Q7)) -> 280 | S7: =R7*N(Scope!$R7) -> 28 | T7: =R7-S7 -> 252 | U7: =T7*N(Scope!$I7) -> 756 | V7: =S7*N(Scope!$I7) -> 84 | W7: =C7*N(Scope!$H7)*N(Scope!$Q7) -> 40 | X7: =N(Scope!$L7)*INDEX(HrsPage,1)+N(Scope!$M7)*INDEX(HrsPage,2)+N(Scope!$N7)*INDEX(HrsPage,3)+N(Scope!$O7)*INDEX(HrsPage,4) -> 6.225 | Y7: =(U7*X7*K7*M7+V7*HrsDerived)*G7 -> 5064.2303 | Z7: =W7*MergeHrs*G7 -> 80 | AA7: =Y7*(1-LearnAvg)*(1-P7)+Z7 -> 4574.5044 | AB7: =C7*N(Scope!$X7) -> 8 | AC7: =N(Scope!$T7)*INDEX(ModelHrs,1)+N(Scope!$U7)*INDEX(ModelHrs,2)+N(Scope!$V7)*INDEX(ModelHrs,3)+N(Scope!$W7)*INDEX(ModelHrs,4) -> 144 | AD7: =AB7*AC7*I7*G7*L7 -> 1324.8 | AE7: =C7*MAX(0,N(Scope!$S7)-N(Scope!$X7))*ConsolHrs*G7 -> 64 | AF7: =(AD7+AE7)*(1-O7) -> 1388.8 | AG7: =IF(C7=0,0,(IF(Q7<=INDEX(AnchorPages,1),INDEX(AnchorAnalysis,1),IF(Q7>=INDEX(AnchorPages,5),INDEX(AnchorAnalysis,5)+(Q7-INDEX(AnchorPages,5))*(INDEX(AnchorAnalysis,5)-INDEX(AnchorAnalysis,4))/(INDEX(AnchorPages,5)-INDEX(AnchorPages,4)),INDEX(AnchorAnalysis,MATCH(Q7,AnchorPages,1))+(Q7-INDEX(AnchorPages,MATCH(Q7,AnchorPages,1)))*(INDEX(AnchorAnalysis,MATCH(Q7,AnchorPages,1)+1)-INDEX(AnchorAnalysis,MATCH(Q7,AnchorPages,1)))/(INDEX(AnchorPages,MATCH(Q7,AnchorPages,1)+1)-INDEX(AnchorPages,MATCH(Q7,AnchorPages,1)))))*G7+N(Scope!$S7)*AssessPerModel)*(1-N7)) -> 294 | AH7: =IF(C7=0,0,AB7*IFERROR(INDEX(SecHrs,MATCH(Scope!$Y7,SecNames,0)),0)+N(Scope!$Z7)*SchedHrs+N(Scope!$AA7)*GroupHrs+HandoverHrs) -> 231 | AI7: =AB7*IFERROR(INDEX(AIHrs,MATCH(Scope!$AB7,AINames,0)),0) -> 128 | AJ7: =IF(AND(C7=1,MAX(N7,O7,P7,AutoSIT,AutoUAT,AutoDep)>0),AutoSetupHrs,0) -> 0 | AK7: =AA7+AF7+AG7+AH7+AI7+AJ7 -> 6616.3044 | AL7: =AA7+AF7 -> 5963.3044 | AM7: =IF(C7=0,0,MIN(5,MAX(1,INT(N(Scope!$G7))))) -> 1 | AN7: =IF(C7=0,0,IFERROR(INDEX(ConfPct,MATCH(Scope!$AH7,ConfNames,0)),MAX(ConfPct))) -> 0.15 | AO7: =IF(SUM($AL$7:$AL$26)>0,AL7/SUM($AL$7:$AL$26)*ProgSharedHrs,0) -> 3233.6012 | AP7: =AK7+AO7 -> 9849.9056 | AQ7: =AP7*AN7 -> 1477.4858 | AR7: =IF(C7=0,0,IF(OR(ABS(N(Scope!$L7)+N(Scope!$M7)+N(Scope!$N7)+N(Scope!$O7)-1)>0.001,AND(N(Scope!$X7)>0,ABS(N(Scope!$T7)+N(Scope!$U7)+N(Scope!$V7)+N(Scope!$W7)-1)>0.001)),1,0)) -> 0 | AS7: =IF(AND(C7=1,N(Scope!$P7)+N(Scope!$Q7)>1),1,0) -> 0 | AT7: =IF(AND(C7=1,OR(D7="Unmapped",E7="Unmapped")),1,0) -> 0 | AU7: =IF(AND(C7=1,N(Scope!$AC7)>0,ROUND(N(Scope!$AC7)-F7,4)<>0,Scope!$AD7=""),1,0) -> 0 | AV7: =IF(AND(C7=1,OR(N(Scope!$I7)<1,N(Scope!$X7)<1)),1,0) -> 0
A8: =Scope!$A8 -> 2 | B8: =IF(Scope!$B8="","",Scope!$B8) -> Sales Tableau to Power BI | C8: =IF(AND(Scope!$C8<>"",Scope!$D8<>"",N(Scope!$H8)>0),1,0) -> 1 | D8: =IF(C8=0,"",IFERROR(INDEX(ToolArch,MATCH(Scope!$C8,ToolNames,0)),"Unmapped")) -> Modern visual / self-service | E8: =IF(C8=0,"",IFERROR(INDEX(ToolArch,MATCH(Scope!$D8,ToolNames,0)),"Unmapped")) -> Modern visual / self-service | F8: =IF(C8=0,0,IFERROR(INDEX(KnownFactor,MATCH(Scope!$C8&"|"&Scope!$D8,KnownKey,0)),IFERROR(INDEX(ArchFactor,MATCH(D8,ArchNames,0),MATCH(E8,ArchNames,0)),1))) -> 0.95 | G8: =IF(C8=0,0,IF(N(Scope!$AC8)>0,MIN(FactorMax,MAX(FactorMin,Scope!$AC8)),F8)) -> 0.95 | H8: =IF(C8=0,"",IFERROR(INDEX(ApproachMatrix,MATCH(D8,ArchNames,0),MATCH(E8,ArchNames,0)),"Redesign")) -> Translate | I8: =IF(C8=0,0,IFERROR(INDEX(ApproachShares,MATCH(H8,ApproachNames,0)),1)) -> 0.4 | J8: =IF(AND(C8=1,Scope!$E8<>"",Scope!$F8<>"",Scope!$E8<>Scope!$F8),1,0) -> 1 | K8: =1+J8*N(Scope!$K8)*DPRepUplift -> 1.025 | L8: =1+J8*DPModelUplift -> 1.15 | M8: =1+N(Scope!$J8)*(PaginatedFactor-1) -> 1 | N8: =IF(Scope!$AE8="",AutoAssess,Scope!$AE8)*CapAssess -> 0 | O8: =IF(Scope!$AF8="",AutoSem,Scope!$AF8)*CapSem -> 0 | P8: =IF(Scope!$AG8="",AutoRep,Scope!$AG8)*CapRep -> 0 | Q8: =C8*N(Scope!$H8)*N(Scope!$I8) -> 500 | R8: =C8*N(Scope!$H8)*MAX(0,1-N(Scope!$P8)-N(Scope!$Q8)) -> 175 | S8: =R8*N(Scope!$R8) -> 17.5 | T8: =R8-S8 -> 157.5 | U8: =T8*N(Scope!$I8) -> 315 | V8: =S8*N(Scope!$I8) -> 35 | W8: =C8*N(Scope!$H8)*N(Scope!$Q8) -> 12.5 | X8: =N(Scope!$L8)*INDEX(HrsPage,1)+N(Scope!$M8)*INDEX(HrsPage,2)+N(Scope!$N8)*INDEX(HrsPage,3)+N(Scope!$O8)*INDEX(HrsPage,4) -> 5.8 | Y8: =(U8*X8*K8*M8+V8*HrsDerived)*G8 -> 1812.2912 | Z8: =W8*MergeHrs*G8 -> 23.75 | AA8: =Y8*(1-LearnAvg)*(1-P8)+Z8 -> 1632.1585 | AB8: =C8*N(Scope!$X8) -> 10 | AC8: =N(Scope!$T8)*INDEX(ModelHrs,1)+N(Scope!$U8)*INDEX(ModelHrs,2)+N(Scope!$V8)*INDEX(ModelHrs,3)+N(Scope!$W8)*INDEX(ModelHrs,4) -> 122 | AD8: =AB8*AC8*I8*G8*L8 -> 533.14 | AE8: =C8*MAX(0,N(Scope!$S8)-N(Scope!$X8))*ConsolHrs*G8 -> 456 | AF8: =(AD8+AE8)*(1-O8) -> 989.14 | AG8: =IF(C8=0,0,(IF(Q8<=INDEX(AnchorPages,1),INDEX(AnchorAnalysis,1),IF(Q8>=INDEX(AnchorPages,5),INDEX(AnchorAnalysis,5)+(Q8-INDEX(AnchorPages,5))*(INDEX(AnchorAnalysis,5)-INDEX(AnchorAnalysis,4))/(INDEX(AnchorPages,5)-INDEX(AnchorPages,4)),INDEX(AnchorAnalysis,MATCH(Q8,AnchorPages,1))+(Q8-INDEX(AnchorPages,MATCH(Q8,AnchorPages,1)))*(INDEX(AnchorAnalysis,MATCH(Q8,AnchorPages,1)+1)-INDEX(AnchorAnalysis,MATCH(Q8,AnchorPages,1)))/(INDEX(AnchorPages,MATCH(Q8,AnchorPages,1)+1)-INDEX(AnchorPages,MATCH(Q8,AnchorPages,1)))))*G8+N(Scope!$S8)*AssessPerModel)*(1-N8)) -> 312 | AH8: =IF(C8=0,0,AB8*IFERROR(INDEX(SecHrs,MATCH(Scope!$Y8,SecNames,0)),0)+N(Scope!$Z8)*SchedHrs+N(Scope!$AA8)*GroupHrs+HandoverHrs) -> 120 | AI8: =AB8*IFERROR(INDEX(AIHrs,MATCH(Scope!$AB8,AINames,0)),0) -> 0 | AJ8: =IF(AND(C8=1,MAX(N8,O8,P8,AutoSIT,AutoUAT,AutoDep)>0),AutoSetupHrs,0) -> 0 | AK8: =AA8+AF8+AG8+AH8+AI8+AJ8 -> 3053.2985 | AL8: =AA8+AF8 -> 2621.2985 | AM8: =IF(C8=0,0,MIN(5,MAX(1,INT(N(Scope!$G8))))) -> 2 | AN8: =IF(C8=0,0,IFERROR(INDEX(ConfPct,MATCH(Scope!$AH8,ConfNames,0)),MAX(ConfPct))) -> 0.25 | AO8: =IF(SUM($AL$7:$AL$26)>0,AL8/SUM($AL$7:$AL$26)*ProgSharedHrs,0) -> 1421.3988 | AP8: =AK8+AO8 -> 4474.6973 | AQ8: =AP8*AN8 -> 1118.6743 | AR8: =IF(C8=0,0,IF(OR(ABS(N(Scope!$L8)+N(Scope!$M8)+N(Scope!$N8)+N(Scope!$O8)-1)>0.001,AND(N(Scope!$X8)>0,ABS(N(Scope!$T8)+N(Scope!$U8)+N(Scope!$V8)+N(Scope!$W8)-1)>0.001)),1,0)) -> 0 | AS8: =IF(AND(C8=1,N(Scope!$P8)+N(Scope!$Q8)>1),1,0) -> 0 | AT8: =IF(AND(C8=1,OR(D8="Unmapped",E8="Unmapped")),1,0) -> 0 | AU8: =IF(AND(C8=1,N(Scope!$AC8)>0,ROUND(N(Scope!$AC8)-F8,4)<>0,Scope!$AD8=""),1,0) -> 0 | AV8: =IF(AND(C8=1,OR(N(Scope!$I8)<1,N(Scope!$X8)<1)),1,0) -> 0
A9: =Scope!$A9 -> 3 | B9: =IF(Scope!$B9="","",Scope!$B9) | C9: =IF(AND(Scope!$C9<>"",Scope!$D9<>"",N(Scope!$H9)>0),1,0) -> 0 | D9: =IF(C9=0,"",IFERROR(INDEX(ToolArch,MATCH(Scope!$C9,ToolNames,0)),"Unmapped")) | E9: =IF(C9=0,"",IFERROR(INDEX(ToolArch,MATCH(Scope!$D9,ToolNames,0)),"Unmapped")) | F9: =IF(C9=0,0,IFERROR(INDEX(KnownFactor,MATCH(Scope!$C9&"|"&Scope!$D9,KnownKey,0)),IFERROR(INDEX(ArchFactor,MATCH(D9,ArchNames,0),MATCH(E9,ArchNames,0)),1))) -> 0 | G9: =IF(C9=0,0,IF(N(Scope!$AC9)>0,MIN(FactorMax,MAX(FactorMin,Scope!$AC9)),F9)) -> 0 | H9: =IF(C9=0,"",IFERROR(INDEX(ApproachMatrix,MATCH(D9,ArchNames,0),MATCH(E9,ArchNames,0)),"Redesign")) | I9: =IF(C9=0,0,IFERROR(INDEX(ApproachShares,MATCH(H9,ApproachNames,0)),1)) -> 0 | J9: =IF(AND(C9=1,Scope!$E9<>"",Scope!$F9<>"",Scope!$E9<>Scope!$F9),1,0) -> 0 | K9: =1+J9*N(Scope!$K9)*DPRepUplift -> 1 | L9: =1+J9*DPModelUplift -> 1 | M9: =1+N(Scope!$J9)*(PaginatedFactor-1) -> 1 | N9: =IF(Scope!$AE9="",AutoAssess,Scope!$AE9)*CapAssess -> 0 | O9: =IF(Scope!$AF9="",AutoSem,Scope!$AF9)*CapSem -> 0 | P9: =IF(Scope!$AG9="",AutoRep,Scope!$AG9)*CapRep -> 0 | Q9: =C9*N(Scope!$H9)*N(Scope!$I9) -> 0 | R9: =C9*N(Scope!$H9)*MAX(0,1-N(Scope!$P9)-N(Scope!$Q9)) -> 0 | S9: =R9*N(Scope!$R9) -> 0 | T9: =R9-S9 -> 0 | U9: =T9*N(Scope!$I9) -> 0 | V9: =S9*N(Scope!$I9) -> 0 | W9: =C9*N(Scope!$H9)*N(Scope!$Q9) -> 0 | X9: =N(Scope!$L9)*INDEX(HrsPage,1)+N(Scope!$M9)*INDEX(HrsPage,2)+N(Scope!$N9)*INDEX(HrsPage,3)+N(Scope!$O9)*INDEX(HrsPage,4) -> 0 | Y9: =(U9*X9*K9*M9+V9*HrsDerived)*G9 -> 0 | Z9: =W9*MergeHrs*G9 -> 0 | AA9: =Y9*(1-LearnAvg)*(1-P9)+Z9 -> 0 | AB9: =C9*N(Scope!$X9) -> 0 | AC9: =N(Scope!$T9)*INDEX(ModelHrs,1)+N(Scope!$U9)*INDEX(ModelHrs,2)+N(Scope!$V9)*INDEX(ModelHrs,3)+N(Scope!$W9)*INDEX(ModelHrs,4) -> 0 | AD9: =AB9*AC9*I9*G9*L9 -> 0 | AE9: =C9*MAX(0,N(Scope!$S9)-N(Scope!$X9))*ConsolHrs*G9 -> 0 | AF9: =(AD9+AE9)*(1-O9) -> 0 | AG9: =IF(C9=0,0,(IF(Q9<=INDEX(AnchorPages,1),INDEX(AnchorAnalysis,1),IF(Q9>=INDEX(AnchorPages,5),INDEX(AnchorAnalysis,5)+(Q9-INDEX(AnchorPages,5))*(INDEX(AnchorAnalysis,5)-INDEX(AnchorAnalysis,4))/(INDEX(AnchorPages,5)-INDEX(AnchorPages,4)),INDEX(AnchorAnalysis,MATCH(Q9,AnchorPages,1))+(Q9-INDEX(AnchorPages,MATCH(Q9,AnchorPages,1)))*(INDEX(AnchorAnalysis,MATCH(Q9,AnchorPages,1)+1)-INDEX(AnchorAnalysis,MATCH(Q9,AnchorPages,1)))/(INDEX(AnchorPages,MATCH(Q9,AnchorPages,1)+1)-INDEX(AnchorPages,MATCH(Q9,AnchorPages,1)))))*G9+N(Scope!$S9)*AssessPerModel)*(1-N9)) -> 0 | AH9: =IF(C9=0,0,AB9*IFERROR(INDEX(SecHrs,MATCH(Scope!$Y9,SecNames,0)),0)+N(Scope!$Z9)*SchedHrs+N(Scope!$AA9)*GroupHrs+HandoverHrs) -> 0 | AI9: =AB9*IFERROR(INDEX(AIHrs,MATCH(Scope!$AB9,AINames,0)),0) -> 0 | AJ9: =IF(AND(C9=1,MAX(N9,O9,P9,AutoSIT,AutoUAT,AutoDep)>0),AutoSetupHrs,0) -> 0 | AK9: =AA9+AF9+AG9+AH9+AI9+AJ9 -> 0 | AL9: =AA9+AF9 -> 0 | AM9: =IF(C9=0,0,MIN(5,MAX(1,INT(N(Scope!$G9))))) -> 0 | AN9: =IF(C9=0,0,IFERROR(INDEX(ConfPct,MATCH(Scope!$AH9,ConfNames,0)),MAX(ConfPct))) -> 0 | AO9: =IF(SUM($AL$7:$AL$26)>0,AL9/SUM($AL$7:$AL$26)*ProgSharedHrs,0) -> 0 | AP9: =AK9+AO9 -> 0 | AQ9: =AP9*AN9 -> 0 | AR9: =IF(C9=0,0,IF(OR(ABS(N(Scope!$L9)+N(Scope!$M9)+N(Scope!$N9)+N(Scope!$O9)-1)>0.001,AND(N(Scope!$X9)>0,ABS(N(Scope!$T9)+N(Scope!$U9)+N(Scope!$V9)+N(Scope!$W9)-1)>0.001)),1,0)) -> 0 | AS9: =IF(AND(C9=1,N(Scope!$P9)+N(Scope!$Q9)>1),1,0) -> 0 | AT9: =IF(AND(C9=1,OR(D9="Unmapped",E9="Unmapped")),1,0) -> 0 | AU9: =IF(AND(C9=1,N(Scope!$AC9)>0,ROUND(N(Scope!$AC9)-F9,4)<>0,Scope!$AD9=""),1,0) -> 0 | AV9: =IF(AND(C9=1,OR(N(Scope!$I9)<1,N(Scope!$X9)<1)),1,0) -> 0
A10: =Scope!$A10 -> 4 | B10: =IF(Scope!$B10="","",Scope!$B10) | C10: =IF(AND(Scope!$C10<>"",Scope!$D10<>"",N(Scope!$H10)>0),1,0) -> 0 | D10: =IF(C10=0,"",IFERROR(INDEX(ToolArch,MATCH(Scope!$C10,ToolNames,0)),"Unmapped")) | E10: =IF(C10=0,"",IFERROR(INDEX(ToolArch,MATCH(Scope!$D10,ToolNames,0)),"Unmapped")) | F10: =IF(C10=0,0,IFERROR(INDEX(KnownFactor,MATCH(Scope!$C10&"|"&Scope!$D10,KnownKey,0)),IFERROR(INDEX(ArchFactor,MATCH(D10,ArchNames,0),MATCH(E10,ArchNames,0)),1))) -> 0 | G10: =IF(C10=0,0,IF(N(Scope!$AC10)>0,MIN(FactorMax,MAX(FactorMin,Scope!$AC10)),F10)) -> 0 | H10: =IF(C10=0,"",IFERROR(INDEX(ApproachMatrix,MATCH(D10,ArchNames,0),MATCH(E10,ArchNames,0)),"Redesign")) | I10: =IF(C10=0,0,IFERROR(INDEX(ApproachShares,MATCH(H10,ApproachNames,0)),1)) -> 0 | J10: =IF(AND(C10=1,Scope!$E10<>"",Scope!$F10<>"",Scope!$E10<>Scope!$F10),1,0) -> 0 | K10: =1+J10*N(Scope!$K10)*DPRepUplift -> 1 | L10: =1+J10*DPModelUplift -> 1 | M10: =1+N(Scope!$J10)*(PaginatedFactor-1) -> 1 | N10: =IF(Scope!$AE10="",AutoAssess,Scope!$AE10)*CapAssess -> 0 | O10: =IF(Scope!$AF10="",AutoSem,Scope!$AF10)*CapSem -> 0 | P10: =IF(Scope!$AG10="",AutoRep,Scope!$AG10)*CapRep -> 0 | Q10: =C10*N(Scope!$H10)*N(Scope!$I10) -> 0 | R10: =C10*N(Scope!$H10)*MAX(0,1-N(Scope!$P10)-N(Scope!$Q10)) -> 0 | S10: =R10*N(Scope!$R10) -> 0 | T10: =R10-S10 -> 0 | U10: =T10*N(Scope!$I10) -> 0 | V10: =S10*N(Scope!$I10) -> 0 | W10: =C10*N(Scope!$H10)*N(Scope!$Q10) -> 0 | X10: =N(Scope!$L10)*INDEX(HrsPage,1)+N(Scope!$M10)*INDEX(HrsPage,2)+N(Scope!$N10)*INDEX(HrsPage,3)+N(Scope!$O10)*INDEX(HrsPage,4) -> 0 | Y10: =(U10*X10*K10*M10+V10*HrsDerived)*G10 -> 0 | Z10: =W10*MergeHrs*G10 -> 0 | AA10: =Y10*(1-LearnAvg)*(1-P10)+Z10 -> 0 | AB10: =C10*N(Scope!$X10) -> 0 | AC10: =N(Scope!$T10)*INDEX(ModelHrs,1)+N(Scope!$U10)*INDEX(ModelHrs,2)+N(Scope!$V10)*INDEX(ModelHrs,3)+N(Scope!$W10)*INDEX(ModelHrs,4) -> 0 | AD10: =AB10*AC10*I10*G10*L10 -> 0 | AE10: =C10*MAX(0,N(Scope!$S10)-N(Scope!$X10))*ConsolHrs*G10 -> 0 | AF10: =(AD10+AE10)*(1-O10) -> 0 | AG10: =IF(C10=0,0,(IF(Q10<=INDEX(AnchorPages,1),INDEX(AnchorAnalysis,1),IF(Q10>=INDEX(AnchorPages,5),INDEX(AnchorAnalysis,5)+(Q10-INDEX(AnchorPages,5))*(INDEX(AnchorAnalysis,5)-INDEX(AnchorAnalysis,4))/(INDEX(AnchorPages,5)-INDEX(AnchorPages,4)),INDEX(AnchorAnalysis,MATCH(Q10,AnchorPages,1))+(Q10-INDEX(AnchorPages,MATCH(Q10,AnchorPages,1)))*(INDEX(AnchorAnalysis,MATCH(Q10,AnchorPages,1)+1)-INDEX(AnchorAnalysis,MATCH(Q10,AnchorPages,1)))/(INDEX(AnchorPages,MATCH(Q10,AnchorPages,1)+1)-INDEX(AnchorPages,MATCH(Q10,AnchorPages,1)))))*G10+N(Scope!$S10)*AssessPerModel)*(1-N10)) -> 0 | AH10: =IF(C10=0,0,AB10*IFERROR(INDEX(SecHrs,MATCH(Scope!$Y10,SecNames,0)),0)+N(Scope!$Z10)*SchedHrs+N(Scope!$AA10)*GroupHrs+HandoverHrs) -> 0 | AI10: =AB10*IFERROR(INDEX(AIHrs,MATCH(Scope!$AB10,AINames,0)),0) -> 0 | AJ10: =IF(AND(C10=1,MAX(N10,O10,P10,AutoSIT,AutoUAT,AutoDep)>0),AutoSetupHrs,0) -> 0 | AK10: =AA10+AF10+AG10+AH10+AI10+AJ10 -> 0 | AL10: =AA10+AF10 -> 0 | AM10: =IF(C10=0,0,MIN(5,MAX(1,INT(N(Scope!$G10))))) -> 0 | AN10: =IF(C10=0,0,IFERROR(INDEX(ConfPct,MATCH(Scope!$AH10,ConfNames,0)),MAX(ConfPct))) -> 0 | AO10: =IF(SUM($AL$7:$AL$26)>0,AL10/SUM($AL$7:$AL$26)*ProgSharedHrs,0) -> 0 | AP10: =AK10+AO10 -> 0 | AQ10: =AP10*AN10 -> 0 | AR10: =IF(C10=0,0,IF(OR(ABS(N(Scope!$L10)+N(Scope!$M10)+N(Scope!$N10)+N(Scope!$O10)-1)>0.001,AND(N(Scope!$X10)>0,ABS(N(Scope!$T10)+N(Scope!$U10)+N(Scope!$V10)+N(Scope!$W10)-1)>0.001)),1,0)) -> 0 | AS10: =IF(AND(C10=1,N(Scope!$P10)+N(Scope!$Q10)>1),1,0) -> 0 | AT10: =IF(AND(C10=1,OR(D10="Unmapped",E10="Unmapped")),1,0) -> 0 | AU10: =IF(AND(C10=1,N(Scope!$AC10)>0,ROUND(N(Scope!$AC10)-F10,4)<>0,Scope!$AD10=""),1,0) -> 0 | AV10: =IF(AND(C10=1,OR(N(Scope!$I10)<1,N(Scope!$X10)<1)),1,0) -> 0
A11: =Scope!$A11 -> 5 | B11: =IF(Scope!$B11="","",Scope!$B11) | C11: =IF(AND(Scope!$C11<>"",Scope!$D11<>"",N(Scope!$H11)>0),1,0) -> 0 | D11: =IF(C11=0,"",IFERROR(INDEX(ToolArch,MATCH(Scope!$C11,ToolNames,0)),"Unmapped")) | E11: =IF(C11=0,"",IFERROR(INDEX(ToolArch,MATCH(Scope!$D11,ToolNames,0)),"Unmapped")) | F11: =IF(C11=0,0,IFERROR(INDEX(KnownFactor,MATCH(Scope!$C11&"|"&Scope!$D11,KnownKey,0)),IFERROR(INDEX(ArchFactor,MATCH(D11,ArchNames,0),MATCH(E11,ArchNames,0)),1))) -> 0 | G11: =IF(C11=0,0,IF(N(Scope!$AC11)>0,MIN(FactorMax,MAX(FactorMin,Scope!$AC11)),F11)) -> 0 | H11: =IF(C11=0,"",IFERROR(INDEX(ApproachMatrix,MATCH(D11,ArchNames,0),MATCH(E11,ArchNames,0)),"Redesign")) | I11: =IF(C11=0,0,IFERROR(INDEX(ApproachShares,MATCH(H11,ApproachNames,0)),1)) -> 0 | J11: =IF(AND(C11=1,Scope!$E11<>"",Scope!$F11<>"",Scope!$E11<>Scope!$F11),1,0) -> 0 | K11: =1+J11*N(Scope!$K11)*DPRepUplift -> 1 | L11: =1+J11*DPModelUplift -> 1 | M11: =1+N(Scope!$J11)*(PaginatedFactor-1) -> 1 | N11: =IF(Scope!$AE11="",AutoAssess,Scope!$AE11)*CapAssess -> 0 | O11: =IF(Scope!$AF11="",AutoSem,Scope!$AF11)*CapSem -> 0 | P11: =IF(Scope!$AG11="",AutoRep,Scope!$AG11)*CapRep -> 0 | Q11: =C11*N(Scope!$H11)*N(Scope!$I11) -> 0 | R11: =C11*N(Scope!$H11)*MAX(0,1-N(Scope!$P11)-N(Scope!$Q11)) -> 0 | S11: =R11*N(Scope!$R11) -> 0 | T11: =R11-S11 -> 0 | U11: =T11*N(Scope!$I11) -> 0 | V11: =S11*N(Scope!$I11) -> 0 | W11: =C11*N(Scope!$H11)*N(Scope!$Q11) -> 0 | X11: =N(Scope!$L11)*INDEX(HrsPage,1)+N(Scope!$M11)*INDEX(HrsPage,2)+N(Scope!$N11)*INDEX(HrsPage,3)+N(Scope!$O11)*INDEX(HrsPage,4) -> 0 | Y11: =(U11*X11*K11*M11+V11*HrsDerived)*G11 -> 0 | Z11: =W11*MergeHrs*G11 -> 0 | AA11: =Y11*(1-LearnAvg)*(1-P11)+Z11 -> 0 | AB11: =C11*N(Scope!$X11) -> 0 | AC11: =N(Scope!$T11)*INDEX(ModelHrs,1)+N(Scope!$U11)*INDEX(ModelHrs,2)+N(Scope!$V11)*INDEX(ModelHrs,3)+N(Scope!$W11)*INDEX(ModelHrs,4) -> 0 | AD11: =AB11*AC11*I11*G11*L11 -> 0 | AE11: =C11*MAX(0,N(Scope!$S11)-N(Scope!$X11))*ConsolHrs*G11 -> 0 | AF11: =(AD11+AE11)*(1-O11) -> 0 | AG11: =IF(C11=0,0,(IF(Q11<=INDEX(AnchorPages,1),INDEX(AnchorAnalysis,1),IF(Q11>=INDEX(AnchorPages,5),INDEX(AnchorAnalysis,5)+(Q11-INDEX(AnchorPages,5))*(INDEX(AnchorAnalysis,5)-INDEX(AnchorAnalysis,4))/(INDEX(AnchorPages,5)-INDEX(AnchorPages,4)),INDEX(AnchorAnalysis,MATCH(Q11,AnchorPages,1))+(Q11-INDEX(AnchorPages,MATCH(Q11,AnchorPages,1)))*(INDEX(AnchorAnalysis,MATCH(Q11,AnchorPages,1)+1)-INDEX(AnchorAnalysis,MATCH(Q11,AnchorPages,1)))/(INDEX(AnchorPages,MATCH(Q11,AnchorPages,1)+1)-INDEX(AnchorPages,MATCH(Q11,AnchorPages,1)))))*G11+N(Scope!$S11)*AssessPerModel)*(1-N11)) -> 0 | AH11: =IF(C11=0,0,AB11*IFERROR(INDEX(SecHrs,MATCH(Scope!$Y11,SecNames,0)),0)+N(Scope!$Z11)*SchedHrs+N(Scope!$AA11)*GroupHrs+HandoverHrs) -> 0 | AI11: =AB11*IFERROR(INDEX(AIHrs,MATCH(Scope!$AB11,AINames,0)),0) -> 0 | AJ11: =IF(AND(C11=1,MAX(N11,O11,P11,AutoSIT,AutoUAT,AutoDep)>0),AutoSetupHrs,0) -> 0 | AK11: =AA11+AF11+AG11+AH11+AI11+AJ11 -> 0 | AL11: =AA11+AF11 -> 0 | AM11: =IF(C11=0,0,MIN(5,MAX(1,INT(N(Scope!$G11))))) -> 0 | AN11: =IF(C11=0,0,IFERROR(INDEX(ConfPct,MATCH(Scope!$AH11,ConfNames,0)),MAX(ConfPct))) -> 0 | AO11: =IF(SUM($AL$7:$AL$26)>0,AL11/SUM($AL$7:$AL$26)*ProgSharedHrs,0) -> 0 | AP11: =AK11+AO11 -> 0 | AQ11: =AP11*AN11 -> 0 | AR11: =IF(C11=0,0,IF(OR(ABS(N(Scope!$L11)+N(Scope!$M11)+N(Scope!$N11)+N(Scope!$O11)-1)>0.001,AND(N(Scope!$X11)>0,ABS(N(Scope!$T11)+N(Scope!$U11)+N(Scope!$V11)+N(Scope!$W11)-1)>0.001)),1,0)) -> 0 | AS11: =IF(AND(C11=1,N(Scope!$P11)+N(Scope!$Q11)>1),1,0) -> 0 | AT11: =IF(AND(C11=1,OR(D11="Unmapped",E11="Unmapped")),1,0) -> 0 | AU11: =IF(AND(C11=1,N(Scope!$AC11)>0,ROUND(N(Scope!$AC11)-F11,4)<>0,Scope!$AD11=""),1,0) -> 0 | AV11: =IF(AND(C11=1,OR(N(Scope!$I11)<1,N(Scope!$X11)<1)),1,0) -> 0
A12: =Scope!$A12 -> 6 | B12: =IF(Scope!$B12="","",Scope!$B12) | C12: =IF(AND(Scope!$C12<>"",Scope!$D12<>"",N(Scope!$H12)>0),1,0) -> 0 | D12: =IF(C12=0,"",IFERROR(INDEX(ToolArch,MATCH(Scope!$C12,ToolNames,0)),"Unmapped")) | E12: =IF(C12=0,"",IFERROR(INDEX(ToolArch,MATCH(Scope!$D12,ToolNames,0)),"Unmapped")) | F12: =IF(C12=0,0,IFERROR(INDEX(KnownFactor,MATCH(Scope!$C12&"|"&Scope!$D12,KnownKey,0)),IFERROR(INDEX(ArchFactor,MATCH(D12,ArchNames,0),MATCH(E12,ArchNames,0)),1))) -> 0 | G12: =IF(C12=0,0,IF(N(Scope!$AC12)>0,MIN(FactorMax,MAX(FactorMin,Scope!$AC12)),F12)) -> 0 | H12: =IF(C12=0,"",IFERROR(INDEX(ApproachMatrix,MATCH(D12,ArchNames,0),MATCH(E12,ArchNames,0)),"Redesign")) | I12: =IF(C12=0,0,IFERROR(INDEX(ApproachShares,MATCH(H12,ApproachNames,0)),1)) -> 0 | J12: =IF(AND(C12=1,Scope!$E12<>"",Scope!$F12<>"",Scope!$E12<>Scope!$F12),1,0) -> 0 | K12: =1+J12*N(Scope!$K12)*DPRepUplift -> 1 | L12: =1+J12*DPModelUplift -> 1 | M12: =1+N(Scope!$J12)*(PaginatedFactor-1) -> 1 | N12: =IF(Scope!$AE12="",AutoAssess,Scope!$AE12)*CapAssess -> 0 | O12: =IF(Scope!$AF12="",AutoSem,Scope!$AF12)*CapSem -> 0 | P12: =IF(Scope!$AG12="",AutoRep,Scope!$AG12)*CapRep -> 0 | Q12: =C12*N(Scope!$H12)*N(Scope!$I12) -> 0 | R12: =C12*N(Scope!$H12)*MAX(0,1-N(Scope!$P12)-N(Scope!$Q12)) -> 0 | S12: =R12*N(Scope!$R12) -> 0 | T12: =R12-S12 -> 0 | U12: =T12*N(Scope!$I12) -> 0 | V12: =S12*N(Scope!$I12) -> 0 | W12: =C12*N(Scope!$H12)*N(Scope!$Q12) -> 0 | X12: =N(Scope!$L12)*INDEX(HrsPage,1)+N(Scope!$M12)*INDEX(HrsPage,2)+N(Scope!$N12)*INDEX(HrsPage,3)+N(Scope!$O12)*INDEX(HrsPage,4) -> 0 | Y12: =(U12*X12*K12*M12+V12*HrsDerived)*G12 -> 0 | Z12: =W12*MergeHrs*G12 -> 0 | AA12: =Y12*(1-LearnAvg)*(1-P12)+Z12 -> 0 | AB12: =C12*N(Scope!$X12) -> 0 | AC12: =N(Scope!$T12)*INDEX(ModelHrs,1)+N(Scope!$U12)*INDEX(ModelHrs,2)+N(Scope!$V12)*INDEX(ModelHrs,3)+N(Scope!$W12)*INDEX(ModelHrs,4) -> 0 | AD12: =AB12*AC12*I12*G12*L12 -> 0 | AE12: =C12*MAX(0,N(Scope!$S12)-N(Scope!$X12))*ConsolHrs*G12 -> 0 | AF12: =(AD12+AE12)*(1-O12) -> 0 | AG12: =IF(C12=0,0,(IF(Q12<=INDEX(AnchorPages,1),INDEX(AnchorAnalysis,1),IF(Q12>=INDEX(AnchorPages,5),INDEX(AnchorAnalysis,5)+(Q12-INDEX(AnchorPages,5))*(INDEX(AnchorAnalysis,5)-INDEX(AnchorAnalysis,4))/(INDEX(AnchorPages,5)-INDEX(AnchorPages,4)),INDEX(AnchorAnalysis,MATCH(Q12,AnchorPages,1))+(Q12-INDEX(AnchorPages,MATCH(Q12,AnchorPages,1)))*(INDEX(AnchorAnalysis,MATCH(Q12,AnchorPages,1)+1)-INDEX(AnchorAnalysis,MATCH(Q12,AnchorPages,1)))/(INDEX(AnchorPages,MATCH(Q12,AnchorPages,1)+1)-INDEX(AnchorPages,MATCH(Q12,AnchorPages,1)))))*G12+N(Scope!$S12)*AssessPerModel)*(1-N12)) -> 0 | AH12: =IF(C12=0,0,AB12*IFERROR(INDEX(SecHrs,MATCH(Scope!$Y12,SecNames,0)),0)+N(Scope!$Z12)*SchedHrs+N(Scope!$AA12)*GroupHrs+HandoverHrs) -> 0 | AI12: =AB12*IFERROR(INDEX(AIHrs,MATCH(Scope!$AB12,AINames,0)),0) -> 0 | AJ12: =IF(AND(C12=1,MAX(N12,O12,P12,AutoSIT,AutoUAT,AutoDep)>0),AutoSetupHrs,0) -> 0 | AK12: =AA12+AF12+AG12+AH12+AI12+AJ12 -> 0 | AL12: =AA12+AF12 -> 0 | AM12: =IF(C12=0,0,MIN(5,MAX(1,INT(N(Scope!$G12))))) -> 0 | AN12: =IF(C12=0,0,IFERROR(INDEX(ConfPct,MATCH(Scope!$AH12,ConfNames,0)),MAX(ConfPct))) -> 0 | AO12: =IF(SUM($AL$7:$AL$26)>0,AL12/SUM($AL$7:$AL$26)*ProgSharedHrs,0) -> 0 | AP12: =AK12+AO12 -> 0 | AQ12: =AP12*AN12 -> 0 | AR12: =IF(C12=0,0,IF(OR(ABS(N(Scope!$L12)+N(Scope!$M12)+N(Scope!$N12)+N(Scope!$O12)-1)>0.001,AND(N(Scope!$X12)>0,ABS(N(Scope!$T12)+N(Scope!$U12)+N(Scope!$V12)+N(Scope!$W12)-1)>0.001)),1,0)) -> 0 | AS12: =IF(AND(C12=1,N(Scope!$P12)+N(Scope!$Q12)>1),1,0) -> 0 | AT12: =IF(AND(C12=1,OR(D12="Unmapped",E12="Unmapped")),1,0) -> 0 | AU12: =IF(AND(C12=1,N(Scope!$AC12)>0,ROUND(N(Scope!$AC12)-F12,4)<>0,Scope!$AD12=""),1,0) -> 0 | AV12: =IF(AND(C12=1,OR(N(Scope!$I12)<1,N(Scope!$X12)<1)),1,0) -> 0
A13: =Scope!$A13 -> 7 | B13: =IF(Scope!$B13="","",Scope!$B13) | C13: =IF(AND(Scope!$C13<>"",Scope!$D13<>"",N(Scope!$H13)>0),1,0) -> 0 | D13: =IF(C13=0,"",IFERROR(INDEX(ToolArch,MATCH(Scope!$C13,ToolNames,0)),"Unmapped")) | E13: =IF(C13=0,"",IFERROR(INDEX(ToolArch,MATCH(Scope!$D13,ToolNames,0)),"Unmapped")) | F13: =IF(C13=0,0,IFERROR(INDEX(KnownFactor,MATCH(Scope!$C13&"|"&Scope!$D13,KnownKey,0)),IFERROR(INDEX(ArchFactor,MATCH(D13,ArchNames,0),MATCH(E13,ArchNames,0)),1))) -> 0 | G13: =IF(C13=0,0,IF(N(Scope!$AC13)>0,MIN(FactorMax,MAX(FactorMin,Scope!$AC13)),F13)) -> 0 | H13: =IF(C13=0,"",IFERROR(INDEX(ApproachMatrix,MATCH(D13,ArchNames,0),MATCH(E13,ArchNames,0)),"Redesign")) | I13: =IF(C13=0,0,IFERROR(INDEX(ApproachShares,MATCH(H13,ApproachNames,0)),1)) -> 0 | J13: =IF(AND(C13=1,Scope!$E13<>"",Scope!$F13<>"",Scope!$E13<>Scope!$F13),1,0) -> 0 | K13: =1+J13*N(Scope!$K13)*DPRepUplift -> 1 | L13: =1+J13*DPModelUplift -> 1 | M13: =1+N(Scope!$J13)*(PaginatedFactor-1) -> 1 | N13: =IF(Scope!$AE13="",AutoAssess,Scope!$AE13)*CapAssess -> 0 | O13: =IF(Scope!$AF13="",AutoSem,Scope!$AF13)*CapSem -> 0 | P13: =IF(Scope!$AG13="",AutoRep,Scope!$AG13)*CapRep -> 0 | Q13: =C13*N(Scope!$H13)*N(Scope!$I13) -> 0 | R13: =C13*N(Scope!$H13)*MAX(0,1-N(Scope!$P13)-N(Scope!$Q13)) -> 0 | S13: =R13*N(Scope!$R13) -> 0 | T13: =R13-S13 -> 0 | U13: =T13*N(Scope!$I13) -> 0 | V13: =S13*N(Scope!$I13) -> 0 | W13: =C13*N(Scope!$H13)*N(Scope!$Q13) -> 0 | X13: =N(Scope!$L13)*INDEX(HrsPage,1)+N(Scope!$M13)*INDEX(HrsPage,2)+N(Scope!$N13)*INDEX(HrsPage,3)+N(Scope!$O13)*INDEX(HrsPage,4) -> 0 | Y13: =(U13*X13*K13*M13+V13*HrsDerived)*G13 -> 0 | Z13: =W13*MergeHrs*G13 -> 0 | AA13: =Y13*(1-LearnAvg)*(1-P13)+Z13 -> 0 | AB13: =C13*N(Scope!$X13) -> 0 | AC13: =N(Scope!$T13)*INDEX(ModelHrs,1)+N(Scope!$U13)*INDEX(ModelHrs,2)+N(Scope!$V13)*INDEX(ModelHrs,3)+N(Scope!$W13)*INDEX(ModelHrs,4) -> 0 | AD13: =AB13*AC13*I13*G13*L13 -> 0 | AE13: =C13*MAX(0,N(Scope!$S13)-N(Scope!$X13))*ConsolHrs*G13 -> 0 | AF13: =(AD13+AE13)*(1-O13) -> 0 | AG13: =IF(C13=0,0,(IF(Q13<=INDEX(AnchorPages,1),INDEX(AnchorAnalysis,1),IF(Q13>=INDEX(AnchorPages,5),INDEX(AnchorAnalysis,5)+(Q13-INDEX(AnchorPages,5))*(INDEX(AnchorAnalysis,5)-INDEX(AnchorAnalysis,4))/(INDEX(AnchorPages,5)-INDEX(AnchorPages,4)),INDEX(AnchorAnalysis,MATCH(Q13,AnchorPages,1))+(Q13-INDEX(AnchorPages,MATCH(Q13,AnchorPages,1)))*(INDEX(AnchorAnalysis,MATCH(Q13,AnchorPages,1)+1)-INDEX(AnchorAnalysis,MATCH(Q13,AnchorPages,1)))/(INDEX(AnchorPages,MATCH(Q13,AnchorPages,1)+1)-INDEX(AnchorPages,MATCH(Q13,AnchorPages,1)))))*G13+N(Scope!$S13)*AssessPerModel)*(1-N13)) -> 0 | AH13: =IF(C13=0,0,AB13*IFERROR(INDEX(SecHrs,MATCH(Scope!$Y13,SecNames,0)),0)+N(Scope!$Z13)*SchedHrs+N(Scope!$AA13)*GroupHrs+HandoverHrs) -> 0 | AI13: =AB13*IFERROR(INDEX(AIHrs,MATCH(Scope!$AB13,AINames,0)),0) -> 0 | AJ13: =IF(AND(C13=1,MAX(N13,O13,P13,AutoSIT,AutoUAT,AutoDep)>0),AutoSetupHrs,0) -> 0 | AK13: =AA13+AF13+AG13+AH13+AI13+AJ13 -> 0 | AL13: =AA13+AF13 -> 0 | AM13: =IF(C13=0,0,MIN(5,MAX(1,INT(N(Scope!$G13))))) -> 0 | AN13: =IF(C13=0,0,IFERROR(INDEX(ConfPct,MATCH(Scope!$AH13,ConfNames,0)),MAX(ConfPct))) -> 0 | AO13: =IF(SUM($AL$7:$AL$26)>0,AL13/SUM($AL$7:$AL$26)*ProgSharedHrs,0) -> 0 | AP13: =AK13+AO13 -> 0 | AQ13: =AP13*AN13 -> 0 | AR13: =IF(C13=0,0,IF(OR(ABS(N(Scope!$L13)+N(Scope!$M13)+N(Scope!$N13)+N(Scope!$O13)-1)>0.001,AND(N(Scope!$X13)>0,ABS(N(Scope!$T13)+N(Scope!$U13)+N(Scope!$V13)+N(Scope!$W13)-1)>0.001)),1,0)) -> 0 | AS13: =IF(AND(C13=1,N(Scope!$P13)+N(Scope!$Q13)>1),1,0) -> 0 | AT13: =IF(AND(C13=1,OR(D13="Unmapped",E13="Unmapped")),1,0) -> 0 | AU13: =IF(AND(C13=1,N(Scope!$AC13)>0,ROUND(N(Scope!$AC13)-F13,4)<>0,Scope!$AD13=""),1,0) -> 0 | AV13: =IF(AND(C13=1,OR(N(Scope!$I13)<1,N(Scope!$X13)<1)),1,0) -> 0
A14: =Scope!$A14 -> 8 | B14: =IF(Scope!$B14="","",Scope!$B14) | C14: =IF(AND(Scope!$C14<>"",Scope!$D14<>"",N(Scope!$H14)>0),1,0) -> 0 | D14: =IF(C14=0,"",IFERROR(INDEX(ToolArch,MATCH(Scope!$C14,ToolNames,0)),"Unmapped")) | E14: =IF(C14=0,"",IFERROR(INDEX(ToolArch,MATCH(Scope!$D14,ToolNames,0)),"Unmapped")) | F14: =IF(C14=0,0,IFERROR(INDEX(KnownFactor,MATCH(Scope!$C14&"|"&Scope!$D14,KnownKey,0)),IFERROR(INDEX(ArchFactor,MATCH(D14,ArchNames,0),MATCH(E14,ArchNames,0)),1))) -> 0 | G14: =IF(C14=0,0,IF(N(Scope!$AC14)>0,MIN(FactorMax,MAX(FactorMin,Scope!$AC14)),F14)) -> 0 | H14: =IF(C14=0,"",IFERROR(INDEX(ApproachMatrix,MATCH(D14,ArchNames,0),MATCH(E14,ArchNames,0)),"Redesign")) | I14: =IF(C14=0,0,IFERROR(INDEX(ApproachShares,MATCH(H14,ApproachNames,0)),1)) -> 0 | J14: =IF(AND(C14=1,Scope!$E14<>"",Scope!$F14<>"",Scope!$E14<>Scope!$F14),1,0) -> 0 | K14: =1+J14*N(Scope!$K14)*DPRepUplift -> 1 | L14: =1+J14*DPModelUplift -> 1 | M14: =1+N(Scope!$J14)*(PaginatedFactor-1) -> 1 | N14: =IF(Scope!$AE14="",AutoAssess,Scope!$AE14)*CapAssess -> 0 | O14: =IF(Scope!$AF14="",AutoSem,Scope!$AF14)*CapSem -> 0 | P14: =IF(Scope!$AG14="",AutoRep,Scope!$AG14)*CapRep -> 0 | Q14: =C14*N(Scope!$H14)*N(Scope!$I14) -> 0 | R14: =C14*N(Scope!$H14)*MAX(0,1-N(Scope!$P14)-N(Scope!$Q14)) -> 0 | S14: =R14*N(Scope!$R14) -> 0 | T14: =R14-S14 -> 0 | U14: =T14*N(Scope!$I14) -> 0 | V14: =S14*N(Scope!$I14) -> 0 | W14: =C14*N(Scope!$H14)*N(Scope!$Q14) -> 0 | X14: =N(Scope!$L14)*INDEX(HrsPage,1)+N(Scope!$M14)*INDEX(HrsPage,2)+N(Scope!$N14)*INDEX(HrsPage,3)+N(Scope!$O14)*INDEX(HrsPage,4) -> 0 | Y14: =(U14*X14*K14*M14+V14*HrsDerived)*G14 -> 0 | Z14: =W14*MergeHrs*G14 -> 0 | AA14: =Y14*(1-LearnAvg)*(1-P14)+Z14 -> 0 | AB14: =C14*N(Scope!$X14) -> 0 | AC14: =N(Scope!$T14)*INDEX(ModelHrs,1)+N(Scope!$U14)*INDEX(ModelHrs,2)+N(Scope!$V14)*INDEX(ModelHrs,3)+N(Scope!$W14)*INDEX(ModelHrs,4) -> 0 | AD14: =AB14*AC14*I14*G14*L14 -> 0 | AE14: =C14*MAX(0,N(Scope!$S14)-N(Scope!$X14))*ConsolHrs*G14 -> 0 | AF14: =(AD14+AE14)*(1-O14) -> 0 | AG14: =IF(C14=0,0,(IF(Q14<=INDEX(AnchorPages,1),INDEX(AnchorAnalysis,1),IF(Q14>=INDEX(AnchorPages,5),INDEX(AnchorAnalysis,5)+(Q14-INDEX(AnchorPages,5))*(INDEX(AnchorAnalysis,5)-INDEX(AnchorAnalysis,4))/(INDEX(AnchorPages,5)-INDEX(AnchorPages,4)),INDEX(AnchorAnalysis,MATCH(Q14,AnchorPages,1))+(Q14-INDEX(AnchorPages,MATCH(Q14,AnchorPages,1)))*(INDEX(AnchorAnalysis,MATCH(Q14,AnchorPages,1)+1)-INDEX(AnchorAnalysis,MATCH(Q14,AnchorPages,1)))/(INDEX(AnchorPages,MATCH(Q14,AnchorPages,1)+1)-INDEX(AnchorPages,MATCH(Q14,AnchorPages,1)))))*G14+N(Scope!$S14)*AssessPerModel)*(1-N14)) -> 0 | AH14: =IF(C14=0,0,AB14*IFERROR(INDEX(SecHrs,MATCH(Scope!$Y14,SecNames,0)),0)+N(Scope!$Z14)*SchedHrs+N(Scope!$AA14)*GroupHrs+HandoverHrs) -> 0 | AI14: =AB14*IFERROR(INDEX(AIHrs,MATCH(Scope!$AB14,AINames,0)),0) -> 0 | AJ14: =IF(AND(C14=1,MAX(N14,O14,P14,AutoSIT,AutoUAT,AutoDep)>0),AutoSetupHrs,0) -> 0 | AK14: =AA14+AF14+AG14+AH14+AI14+AJ14 -> 0 | AL14: =AA14+AF14 -> 0 | AM14: =IF(C14=0,0,MIN(5,MAX(1,INT(N(Scope!$G14))))) -> 0 | AN14: =IF(C14=0,0,IFERROR(INDEX(ConfPct,MATCH(Scope!$AH14,ConfNames,0)),MAX(ConfPct))) -> 0 | AO14: =IF(SUM($AL$7:$AL$26)>0,AL14/SUM($AL$7:$AL$26)*ProgSharedHrs,0) -> 0 | AP14: =AK14+AO14 -> 0 | AQ14: =AP14*AN14 -> 0 | AR14: =IF(C14=0,0,IF(OR(ABS(N(Scope!$L14)+N(Scope!$M14)+N(Scope!$N14)+N(Scope!$O14)-1)>0.001,AND(N(Scope!$X14)>0,ABS(N(Scope!$T14)+N(Scope!$U14)+N(Scope!$V14)+N(Scope!$W14)-1)>0.001)),1,0)) -> 0 | AS14: =IF(AND(C14=1,N(Scope!$P14)+N(Scope!$Q14)>1),1,0) -> 0 | AT14: =IF(AND(C14=1,OR(D14="Unmapped",E14="Unmapped")),1,0) -> 0 | AU14: =IF(AND(C14=1,N(Scope!$AC14)>0,ROUND(N(Scope!$AC14)-F14,4)<>0,Scope!$AD14=""),1,0) -> 0 | AV14: =IF(AND(C14=1,OR(N(Scope!$I14)<1,N(Scope!$X14)<1)),1,0) -> 0
A15: =Scope!$A15 -> 9 | B15: =IF(Scope!$B15="","",Scope!$B15) | C15: =IF(AND(Scope!$C15<>"",Scope!$D15<>"",N(Scope!$H15)>0),1,0) -> 0 | D15: =IF(C15=0,"",IFERROR(INDEX(ToolArch,MATCH(Scope!$C15,ToolNames,0)),"Unmapped")) | E15: =IF(C15=0,"",IFERROR(INDEX(ToolArch,MATCH(Scope!$D15,ToolNames,0)),"Unmapped")) | F15: =IF(C15=0,0,IFERROR(INDEX(KnownFactor,MATCH(Scope!$C15&"|"&Scope!$D15,KnownKey,0)),IFERROR(INDEX(ArchFactor,MATCH(D15,ArchNames,0),MATCH(E15,ArchNames,0)),1))) -> 0 | G15: =IF(C15=0,0,IF(N(Scope!$AC15)>0,MIN(FactorMax,MAX(FactorMin,Scope!$AC15)),F15)) -> 0 | H15: =IF(C15=0,"",IFERROR(INDEX(ApproachMatrix,MATCH(D15,ArchNames,0),MATCH(E15,ArchNames,0)),"Redesign")) | I15: =IF(C15=0,0,IFERROR(INDEX(ApproachShares,MATCH(H15,ApproachNames,0)),1)) -> 0 | J15: =IF(AND(C15=1,Scope!$E15<>"",Scope!$F15<>"",Scope!$E15<>Scope!$F15),1,0) -> 0 | K15: =1+J15*N(Scope!$K15)*DPRepUplift -> 1 | L15: =1+J15*DPModelUplift -> 1 | M15: =1+N(Scope!$J15)*(PaginatedFactor-1) -> 1 | N15: =IF(Scope!$AE15="",AutoAssess,Scope!$AE15)*CapAssess -> 0 | O15: =IF(Scope!$AF15="",AutoSem,Scope!$AF15)*CapSem -> 0 | P15: =IF(Scope!$AG15="",AutoRep,Scope!$AG15)*CapRep -> 0 | Q15: =C15*N(Scope!$H15)*N(Scope!$I15) -> 0 | R15: =C15*N(Scope!$H15)*MAX(0,1-N(Scope!$P15)-N(Scope!$Q15)) -> 0 | S15: =R15*N(Scope!$R15) -> 0 | T15: =R15-S15 -> 0 | U15: =T15*N(Scope!$I15) -> 0 | V15: =S15*N(Scope!$I15) -> 0 | W15: =C15*N(Scope!$H15)*N(Scope!$Q15) -> 0 | X15: =N(Scope!$L15)*INDEX(HrsPage,1)+N(Scope!$M15)*INDEX(HrsPage,2)+N(Scope!$N15)*INDEX(HrsPage,3)+N(Scope!$O15)*INDEX(HrsPage,4) -> 0 | Y15: =(U15*X15*K15*M15+V15*HrsDerived)*G15 -> 0 | Z15: =W15*MergeHrs*G15 -> 0 | AA15: =Y15*(1-LearnAvg)*(1-P15)+Z15 -> 0 | AB15: =C15*N(Scope!$X15) -> 0 | AC15: =N(Scope!$T15)*INDEX(ModelHrs,1)+N(Scope!$U15)*INDEX(ModelHrs,2)+N(Scope!$V15)*INDEX(ModelHrs,3)+N(Scope!$W15)*INDEX(ModelHrs,4) -> 0 | AD15: =AB15*AC15*I15*G15*L15 -> 0 | AE15: =C15*MAX(0,N(Scope!$S15)-N(Scope!$X15))*ConsolHrs*G15 -> 0 | AF15: =(AD15+AE15)*(1-O15) -> 0 | AG15: =IF(C15=0,0,(IF(Q15<=INDEX(AnchorPages,1),INDEX(AnchorAnalysis,1),IF(Q15>=INDEX(AnchorPages,5),INDEX(AnchorAnalysis,5)+(Q15-INDEX(AnchorPages,5))*(INDEX(AnchorAnalysis,5)-INDEX(AnchorAnalysis,4))/(INDEX(AnchorPages,5)-INDEX(AnchorPages,4)),INDEX(AnchorAnalysis,MATCH(Q15,AnchorPages,1))+(Q15-INDEX(AnchorPages,MATCH(Q15,AnchorPages,1)))*(INDEX(AnchorAnalysis,MATCH(Q15,AnchorPages,1)+1)-INDEX(AnchorAnalysis,MATCH(Q15,AnchorPages,1)))/(INDEX(AnchorPages,MATCH(Q15,AnchorPages,1)+1)-INDEX(AnchorPages,MATCH(Q15,AnchorPages,1)))))*G15+N(Scope!$S15)*AssessPerModel)*(1-N15)) -> 0 | AH15: =IF(C15=0,0,AB15*IFERROR(INDEX(SecHrs,MATCH(Scope!$Y15,SecNames,0)),0)+N(Scope!$Z15)*SchedHrs+N(Scope!$AA15)*GroupHrs+HandoverHrs) -> 0 | AI15: =AB15*IFERROR(INDEX(AIHrs,MATCH(Scope!$AB15,AINames,0)),0) -> 0 | AJ15: =IF(AND(C15=1,MAX(N15,O15,P15,AutoSIT,AutoUAT,AutoDep)>0),AutoSetupHrs,0) -> 0 | AK15: =AA15+AF15+AG15+AH15+AI15+AJ15 -> 0 | AL15: =AA15+AF15 -> 0 | AM15: =IF(C15=0,0,MIN(5,MAX(1,INT(N(Scope!$G15))))) -> 0 | AN15: =IF(C15=0,0,IFERROR(INDEX(ConfPct,MATCH(Scope!$AH15,ConfNames,0)),MAX(ConfPct))) -> 0 | AO15: =IF(SUM($AL$7:$AL$26)>0,AL15/SUM($AL$7:$AL$26)*ProgSharedHrs,0) -> 0 | AP15: =AK15+AO15 -> 0 | AQ15: =AP15*AN15 -> 0 | AR15: =IF(C15=0,0,IF(OR(ABS(N(Scope!$L15)+N(Scope!$M15)+N(Scope!$N15)+N(Scope!$O15)-1)>0.001,AND(N(Scope!$X15)>0,ABS(N(Scope!$T15)+N(Scope!$U15)+N(Scope!$V15)+N(Scope!$W15)-1)>0.001)),1,0)) -> 0 | AS15: =IF(AND(C15=1,N(Scope!$P15)+N(Scope!$Q15)>1),1,0) -> 0 | AT15: =IF(AND(C15=1,OR(D15="Unmapped",E15="Unmapped")),1,0) -> 0 | AU15: =IF(AND(C15=1,N(Scope!$AC15)>0,ROUND(N(Scope!$AC15)-F15,4)<>0,Scope!$AD15=""),1,0) -> 0 | AV15: =IF(AND(C15=1,OR(N(Scope!$I15)<1,N(Scope!$X15)<1)),1,0) -> 0
A16: =Scope!$A16 -> 10 | B16: =IF(Scope!$B16="","",Scope!$B16) | C16: =IF(AND(Scope!$C16<>"",Scope!$D16<>"",N(Scope!$H16)>0),1,0) -> 0 | D16: =IF(C16=0,"",IFERROR(INDEX(ToolArch,MATCH(Scope!$C16,ToolNames,0)),"Unmapped")) | E16: =IF(C16=0,"",IFERROR(INDEX(ToolArch,MATCH(Scope!$D16,ToolNames,0)),"Unmapped")) | F16: =IF(C16=0,0,IFERROR(INDEX(KnownFactor,MATCH(Scope!$C16&"|"&Scope!$D16,KnownKey,0)),IFERROR(INDEX(ArchFactor,MATCH(D16,ArchNames,0),MATCH(E16,ArchNames,0)),1))) -> 0 | G16: =IF(C16=0,0,IF(N(Scope!$AC16)>0,MIN(FactorMax,MAX(FactorMin,Scope!$AC16)),F16)) -> 0 | H16: =IF(C16=0,"",IFERROR(INDEX(ApproachMatrix,MATCH(D16,ArchNames,0),MATCH(E16,ArchNames,0)),"Redesign")) | I16: =IF(C16=0,0,IFERROR(INDEX(ApproachShares,MATCH(H16,ApproachNames,0)),1)) -> 0 | J16: =IF(AND(C16=1,Scope!$E16<>"",Scope!$F16<>"",Scope!$E16<>Scope!$F16),1,0) -> 0 | K16: =1+J16*N(Scope!$K16)*DPRepUplift -> 1 | L16: =1+J16*DPModelUplift -> 1 | M16: =1+N(Scope!$J16)*(PaginatedFactor-1) -> 1 | N16: =IF(Scope!$AE16="",AutoAssess,Scope!$AE16)*CapAssess -> 0 | O16: =IF(Scope!$AF16="",AutoSem,Scope!$AF16)*CapSem -> 0 | P16: =IF(Scope!$AG16="",AutoRep,Scope!$AG16)*CapRep -> 0 | Q16: =C16*N(Scope!$H16)*N(Scope!$I16) -> 0 | R16: =C16*N(Scope!$H16)*MAX(0,1-N(Scope!$P16)-N(Scope!$Q16)) -> 0 | S16: =R16*N(Scope!$R16) -> 0 | T16: =R16-S16 -> 0 | U16: =T16*N(Scope!$I16) -> 0 | V16: =S16*N(Scope!$I16) -> 0 | W16: =C16*N(Scope!$H16)*N(Scope!$Q16) -> 0 | X16: =N(Scope!$L16)*INDEX(HrsPage,1)+N(Scope!$M16)*INDEX(HrsPage,2)+N(Scope!$N16)*INDEX(HrsPage,3)+N(Scope!$O16)*INDEX(HrsPage,4) -> 0 | Y16: =(U16*X16*K16*M16+V16*HrsDerived)*G16 -> 0 | Z16: =W16*MergeHrs*G16 -> 0 | AA16: =Y16*(1-LearnAvg)*(1-P16)+Z16 -> 0 | AB16: =C16*N(Scope!$X16) -> 0 | AC16: =N(Scope!$T16)*INDEX(ModelHrs,1)+N(Scope!$U16)*INDEX(ModelHrs,2)+N(Scope!$V16)*INDEX(ModelHrs,3)+N(Scope!$W16)*INDEX(ModelHrs,4) -> 0 | AD16: =AB16*AC16*I16*G16*L16 -> 0 | AE16: =C16*MAX(0,N(Scope!$S16)-N(Scope!$X16))*ConsolHrs*G16 -> 0 | AF16: =(AD16+AE16)*(1-O16) -> 0 | AG16: =IF(C16=0,0,(IF(Q16<=INDEX(AnchorPages,1),INDEX(AnchorAnalysis,1),IF(Q16>=INDEX(AnchorPages,5),INDEX(AnchorAnalysis,5)+(Q16-INDEX(AnchorPages,5))*(INDEX(AnchorAnalysis,5)-INDEX(AnchorAnalysis,4))/(INDEX(AnchorPages,5)-INDEX(AnchorPages,4)),INDEX(AnchorAnalysis,MATCH(Q16,AnchorPages,1))+(Q16-INDEX(AnchorPages,MATCH(Q16,AnchorPages,1)))*(INDEX(AnchorAnalysis,MATCH(Q16,AnchorPages,1)+1)-INDEX(AnchorAnalysis,MATCH(Q16,AnchorPages,1)))/(INDEX(AnchorPages,MATCH(Q16,AnchorPages,1)+1)-INDEX(AnchorPages,MATCH(Q16,AnchorPages,1)))))*G16+N(Scope!$S16)*AssessPerModel)*(1-N16)) -> 0 | AH16: =IF(C16=0,0,AB16*IFERROR(INDEX(SecHrs,MATCH(Scope!$Y16,SecNames,0)),0)+N(Scope!$Z16)*SchedHrs+N(Scope!$AA16)*GroupHrs+HandoverHrs) -> 0 | AI16: =AB16*IFERROR(INDEX(AIHrs,MATCH(Scope!$AB16,AINames,0)),0) -> 0 | AJ16: =IF(AND(C16=1,MAX(N16,O16,P16,AutoSIT,AutoUAT,AutoDep)>0),AutoSetupHrs,0) -> 0 | AK16: =AA16+AF16+AG16+AH16+AI16+AJ16 -> 0 | AL16: =AA16+AF16 -> 0 | AM16: =IF(C16=0,0,MIN(5,MAX(1,INT(N(Scope!$G16))))) -> 0 | AN16: =IF(C16=0,0,IFERROR(INDEX(ConfPct,MATCH(Scope!$AH16,ConfNames,0)),MAX(ConfPct))) -> 0 | AO16: =IF(SUM($AL$7:$AL$26)>0,AL16/SUM($AL$7:$AL$26)*ProgSharedHrs,0) -> 0 | AP16: =AK16+AO16 -> 0 | AQ16: =AP16*AN16 -> 0 | AR16: =IF(C16=0,0,IF(OR(ABS(N(Scope!$L16)+N(Scope!$M16)+N(Scope!$N16)+N(Scope!$O16)-1)>0.001,AND(N(Scope!$X16)>0,ABS(N(Scope!$T16)+N(Scope!$U16)+N(Scope!$V16)+N(Scope!$W16)-1)>0.001)),1,0)) -> 0 | AS16: =IF(AND(C16=1,N(Scope!$P16)+N(Scope!$Q16)>1),1,0) -> 0 | AT16: =IF(AND(C16=1,OR(D16="Unmapped",E16="Unmapped")),1,0) -> 0 | AU16: =IF(AND(C16=1,N(Scope!$AC16)>0,ROUND(N(Scope!$AC16)-F16,4)<>0,Scope!$AD16=""),1,0) -> 0 | AV16: =IF(AND(C16=1,OR(N(Scope!$I16)<1,N(Scope!$X16)<1)),1,0) -> 0
A17: =Scope!$A17 -> 11 | B17: =IF(Scope!$B17="","",Scope!$B17) | C17: =IF(AND(Scope!$C17<>"",Scope!$D17<>"",N(Scope!$H17)>0),1,0) -> 0 | D17: =IF(C17=0,"",IFERROR(INDEX(ToolArch,MATCH(Scope!$C17,ToolNames,0)),"Unmapped")) | E17: =IF(C17=0,"",IFERROR(INDEX(ToolArch,MATCH(Scope!$D17,ToolNames,0)),"Unmapped")) | F17: =IF(C17=0,0,IFERROR(INDEX(KnownFactor,MATCH(Scope!$C17&"|"&Scope!$D17,KnownKey,0)),IFERROR(INDEX(ArchFactor,MATCH(D17,ArchNames,0),MATCH(E17,ArchNames,0)),1))) -> 0 | G17: =IF(C17=0,0,IF(N(Scope!$AC17)>0,MIN(FactorMax,MAX(FactorMin,Scope!$AC17)),F17)) -> 0 | H17: =IF(C17=0,"",IFERROR(INDEX(ApproachMatrix,MATCH(D17,ArchNames,0),MATCH(E17,ArchNames,0)),"Redesign")) | I17: =IF(C17=0,0,IFERROR(INDEX(ApproachShares,MATCH(H17,ApproachNames,0)),1)) -> 0 | J17: =IF(AND(C17=1,Scope!$E17<>"",Scope!$F17<>"",Scope!$E17<>Scope!$F17),1,0) -> 0 | K17: =1+J17*N(Scope!$K17)*DPRepUplift -> 1 | L17: =1+J17*DPModelUplift -> 1 | M17: =1+N(Scope!$J17)*(PaginatedFactor-1) -> 1 | N17: =IF(Scope!$AE17="",AutoAssess,Scope!$AE17)*CapAssess -> 0 | O17: =IF(Scope!$AF17="",AutoSem,Scope!$AF17)*CapSem -> 0 | P17: =IF(Scope!$AG17="",AutoRep,Scope!$AG17)*CapRep -> 0 | Q17: =C17*N(Scope!$H17)*N(Scope!$I17) -> 0 | R17: =C17*N(Scope!$H17)*MAX(0,1-N(Scope!$P17)-N(Scope!$Q17)) -> 0 | S17: =R17*N(Scope!$R17) -> 0 | T17: =R17-S17 -> 0 | U17: =T17*N(Scope!$I17) -> 0 | V17: =S17*N(Scope!$I17) -> 0 | W17: =C17*N(Scope!$H17)*N(Scope!$Q17) -> 0 | X17: =N(Scope!$L17)*INDEX(HrsPage,1)+N(Scope!$M17)*INDEX(HrsPage,2)+N(Scope!$N17)*INDEX(HrsPage,3)+N(Scope!$O17)*INDEX(HrsPage,4) -> 0 | Y17: =(U17*X17*K17*M17+V17*HrsDerived)*G17 -> 0 | Z17: =W17*MergeHrs*G17 -> 0 | AA17: =Y17*(1-LearnAvg)*(1-P17)+Z17 -> 0 | AB17: =C17*N(Scope!$X17) -> 0 | AC17: =N(Scope!$T17)*INDEX(ModelHrs,1)+N(Scope!$U17)*INDEX(ModelHrs,2)+N(Scope!$V17)*INDEX(ModelHrs,3)+N(Scope!$W17)*INDEX(ModelHrs,4) -> 0 | AD17: =AB17*AC17*I17*G17*L17 -> 0 | AE17: =C17*MAX(0,N(Scope!$S17)-N(Scope!$X17))*ConsolHrs*G17 -> 0 | AF17: =(AD17+AE17)*(1-O17) -> 0 | AG17: =IF(C17=0,0,(IF(Q17<=INDEX(AnchorPages,1),INDEX(AnchorAnalysis,1),IF(Q17>=INDEX(AnchorPages,5),INDEX(AnchorAnalysis,5)+(Q17-INDEX(AnchorPages,5))*(INDEX(AnchorAnalysis,5)-INDEX(AnchorAnalysis,4))/(INDEX(AnchorPages,5)-INDEX(AnchorPages,4)),INDEX(AnchorAnalysis,MATCH(Q17,AnchorPages,1))+(Q17-INDEX(AnchorPages,MATCH(Q17,AnchorPages,1)))*(INDEX(AnchorAnalysis,MATCH(Q17,AnchorPages,1)+1)-INDEX(AnchorAnalysis,MATCH(Q17,AnchorPages,1)))/(INDEX(AnchorPages,MATCH(Q17,AnchorPages,1)+1)-INDEX(AnchorPages,MATCH(Q17,AnchorPages,1)))))*G17+N(Scope!$S17)*AssessPerModel)*(1-N17)) -> 0 | AH17: =IF(C17=0,0,AB17*IFERROR(INDEX(SecHrs,MATCH(Scope!$Y17,SecNames,0)),0)+N(Scope!$Z17)*SchedHrs+N(Scope!$AA17)*GroupHrs+HandoverHrs) -> 0 | AI17: =AB17*IFERROR(INDEX(AIHrs,MATCH(Scope!$AB17,AINames,0)),0) -> 0 | AJ17: =IF(AND(C17=1,MAX(N17,O17,P17,AutoSIT,AutoUAT,AutoDep)>0),AutoSetupHrs,0) -> 0 | AK17: =AA17+AF17+AG17+AH17+AI17+AJ17 -> 0 | AL17: =AA17+AF17 -> 0 | AM17: =IF(C17=0,0,MIN(5,MAX(1,INT(N(Scope!$G17))))) -> 0 | AN17: =IF(C17=0,0,IFERROR(INDEX(ConfPct,MATCH(Scope!$AH17,ConfNames,0)),MAX(ConfPct))) -> 0 | AO17: =IF(SUM($AL$7:$AL$26)>0,AL17/SUM($AL$7:$AL$26)*ProgSharedHrs,0) -> 0 | AP17: =AK17+AO17 -> 0 | AQ17: =AP17*AN17 -> 0 | AR17: =IF(C17=0,0,IF(OR(ABS(N(Scope!$L17)+N(Scope!$M17)+N(Scope!$N17)+N(Scope!$O17)-1)>0.001,AND(N(Scope!$X17)>0,ABS(N(Scope!$T17)+N(Scope!$U17)+N(Scope!$V17)+N(Scope!$W17)-1)>0.001)),1,0)) -> 0 | AS17: =IF(AND(C17=1,N(Scope!$P17)+N(Scope!$Q17)>1),1,0) -> 0 | AT17: =IF(AND(C17=1,OR(D17="Unmapped",E17="Unmapped")),1,0) -> 0 | AU17: =IF(AND(C17=1,N(Scope!$AC17)>0,ROUND(N(Scope!$AC17)-F17,4)<>0,Scope!$AD17=""),1,0) -> 0 | AV17: =IF(AND(C17=1,OR(N(Scope!$I17)<1,N(Scope!$X17)<1)),1,0) -> 0
A18: =Scope!$A18 -> 12 | B18: =IF(Scope!$B18="","",Scope!$B18) | C18: =IF(AND(Scope!$C18<>"",Scope!$D18<>"",N(Scope!$H18)>0),1,0) -> 0 | D18: =IF(C18=0,"",IFERROR(INDEX(ToolArch,MATCH(Scope!$C18,ToolNames,0)),"Unmapped")) | E18: =IF(C18=0,"",IFERROR(INDEX(ToolArch,MATCH(Scope!$D18,ToolNames,0)),"Unmapped")) | F18: =IF(C18=0,0,IFERROR(INDEX(KnownFactor,MATCH(Scope!$C18&"|"&Scope!$D18,KnownKey,0)),IFERROR(INDEX(ArchFactor,MATCH(D18,ArchNames,0),MATCH(E18,ArchNames,0)),1))) -> 0 | G18: =IF(C18=0,0,IF(N(Scope!$AC18)>0,MIN(FactorMax,MAX(FactorMin,Scope!$AC18)),F18)) -> 0 | H18: =IF(C18=0,"",IFERROR(INDEX(ApproachMatrix,MATCH(D18,ArchNames,0),MATCH(E18,ArchNames,0)),"Redesign")) | I18: =IF(C18=0,0,IFERROR(INDEX(ApproachShares,MATCH(H18,ApproachNames,0)),1)) -> 0 | J18: =IF(AND(C18=1,Scope!$E18<>"",Scope!$F18<>"",Scope!$E18<>Scope!$F18),1,0) -> 0 | K18: =1+J18*N(Scope!$K18)*DPRepUplift -> 1 | L18: =1+J18*DPModelUplift -> 1 | M18: =1+N(Scope!$J18)*(PaginatedFactor-1) -> 1 | N18: =IF(Scope!$AE18="",AutoAssess,Scope!$AE18)*CapAssess -> 0 | O18: =IF(Scope!$AF18="",AutoSem,Scope!$AF18)*CapSem -> 0 | P18: =IF(Scope!$AG18="",AutoRep,Scope!$AG18)*CapRep -> 0 | Q18: =C18*N(Scope!$H18)*N(Scope!$I18) -> 0 | R18: =C18*N(Scope!$H18)*MAX(0,1-N(Scope!$P18)-N(Scope!$Q18)) -> 0 | S18: =R18*N(Scope!$R18) -> 0 | T18: =R18-S18 -> 0 | U18: =T18*N(Scope!$I18) -> 0 | V18: =S18*N(Scope!$I18) -> 0 | W18: =C18*N(Scope!$H18)*N(Scope!$Q18) -> 0 | X18: =N(Scope!$L18)*INDEX(HrsPage,1)+N(Scope!$M18)*INDEX(HrsPage,2)+N(Scope!$N18)*INDEX(HrsPage,3)+N(Scope!$O18)*INDEX(HrsPage,4) -> 0 | Y18: =(U18*X18*K18*M18+V18*HrsDerived)*G18 -> 0 | Z18: =W18*MergeHrs*G18 -> 0 | AA18: =Y18*(1-LearnAvg)*(1-P18)+Z18 -> 0 | AB18: =C18*N(Scope!$X18) -> 0 | AC18: =N(Scope!$T18)*INDEX(ModelHrs,1)+N(Scope!$U18)*INDEX(ModelHrs,2)+N(Scope!$V18)*INDEX(ModelHrs,3)+N(Scope!$W18)*INDEX(ModelHrs,4) -> 0 | AD18: =AB18*AC18*I18*G18*L18 -> 0 | AE18: =C18*MAX(0,N(Scope!$S18)-N(Scope!$X18))*ConsolHrs*G18 -> 0 | AF18: =(AD18+AE18)*(1-O18) -> 0 | AG18: =IF(C18=0,0,(IF(Q18<=INDEX(AnchorPages,1),INDEX(AnchorAnalysis,1),IF(Q18>=INDEX(AnchorPages,5),INDEX(AnchorAnalysis,5)+(Q18-INDEX(AnchorPages,5))*(INDEX(AnchorAnalysis,5)-INDEX(AnchorAnalysis,4))/(INDEX(AnchorPages,5)-INDEX(AnchorPages,4)),INDEX(AnchorAnalysis,MATCH(Q18,AnchorPages,1))+(Q18-INDEX(AnchorPages,MATCH(Q18,AnchorPages,1)))*(INDEX(AnchorAnalysis,MATCH(Q18,AnchorPages,1)+1)-INDEX(AnchorAnalysis,MATCH(Q18,AnchorPages,1)))/(INDEX(AnchorPages,MATCH(Q18,AnchorPages,1)+1)-INDEX(AnchorPages,MATCH(Q18,AnchorPages,1)))))*G18+N(Scope!$S18)*AssessPerModel)*(1-N18)) -> 0 | AH18: =IF(C18=0,0,AB18*IFERROR(INDEX(SecHrs,MATCH(Scope!$Y18,SecNames,0)),0)+N(Scope!$Z18)*SchedHrs+N(Scope!$AA18)*GroupHrs+HandoverHrs) -> 0 | AI18: =AB18*IFERROR(INDEX(AIHrs,MATCH(Scope!$AB18,AINames,0)),0) -> 0 | AJ18: =IF(AND(C18=1,MAX(N18,O18,P18,AutoSIT,AutoUAT,AutoDep)>0),AutoSetupHrs,0) -> 0 | AK18: =AA18+AF18+AG18+AH18+AI18+AJ18 -> 0 | AL18: =AA18+AF18 -> 0 | AM18: =IF(C18=0,0,MIN(5,MAX(1,INT(N(Scope!$G18))))) -> 0 | AN18: =IF(C18=0,0,IFERROR(INDEX(ConfPct,MATCH(Scope!$AH18,ConfNames,0)),MAX(ConfPct))) -> 0 | AO18: =IF(SUM($AL$7:$AL$26)>0,AL18/SUM($AL$7:$AL$26)*ProgSharedHrs,0) -> 0 | AP18: =AK18+AO18 -> 0 | AQ18: =AP18*AN18 -> 0 | AR18: =IF(C18=0,0,IF(OR(ABS(N(Scope!$L18)+N(Scope!$M18)+N(Scope!$N18)+N(Scope!$O18)-1)>0.001,AND(N(Scope!$X18)>0,ABS(N(Scope!$T18)+N(Scope!$U18)+N(Scope!$V18)+N(Scope!$W18)-1)>0.001)),1,0)) -> 0 | AS18: =IF(AND(C18=1,N(Scope!$P18)+N(Scope!$Q18)>1),1,0) -> 0 | AT18: =IF(AND(C18=1,OR(D18="Unmapped",E18="Unmapped")),1,0) -> 0 | AU18: =IF(AND(C18=1,N(Scope!$AC18)>0,ROUND(N(Scope!$AC18)-F18,4)<>0,Scope!$AD18=""),1,0) -> 0 | AV18: =IF(AND(C18=1,OR(N(Scope!$I18)<1,N(Scope!$X18)<1)),1,0) -> 0
... A26: =Scope!$A26 -> 20 | B26: =IF(Scope!$B26="","",Scope!$B26) | C26: =IF(AND(Scope!$C26<>"",Scope!$D26<>"",N(Scope!$H26)>0),1,0) -> 0 | D26: =IF(C26=0,"",IFERROR(INDEX(ToolArch,MATCH(Scope!$C26,ToolNames,0)),"Unmapped")) | E26: =IF(C26=0,"",IFERROR(INDEX(ToolArch,MATCH(Scope!$D26,ToolNames,0)),"Unmapped")) | F26: =IF(C26=0,0,IFERROR(INDEX(KnownFactor,MATCH(Scope!$C26&"|"&Scope!$D26,KnownKey,0)),IFERROR(INDEX(ArchFactor,MATCH(D26,ArchNames,0),MATCH(E26,ArchNames,0)),1))) -> 0 | G26: =IF(C26=0,0,IF(N(Scope!$AC26)>0,MIN(FactorMax,MAX(FactorMin,Scope!$AC26)),F26)) -> 0 | H26: =IF(C26=0,"",IFERROR(INDEX(ApproachMatrix,MATCH(D26,ArchNames,0),MATCH(E26,ArchNames,0)),"Redesign")) | I26: =IF(C26=0,0,IFERROR(INDEX(ApproachShares,MATCH(H26,ApproachNames,0)),1)) -> 0 | J26: =IF(AND(C26=1,Scope!$E26<>"",Scope!$F26<>"",Scope!$E26<>Scope!$F26),1,0) -> 0 | K26: =1+J26*N(Scope!$K26)*DPRepUplift -> 1 | L26: =1+J26*DPModelUplift -> 1 | M26: =1+N(Scope!$J26)*(PaginatedFactor-1) -> 1 | N26: =IF(Scope!$AE26="",AutoAssess,Scope!$AE26)*CapAssess -> 0 | O26: =IF(Scope!$AF26="",AutoSem,Scope!$AF26)*CapSem -> 0 | P26: =IF(Scope!$AG26="",AutoRep,Scope!$AG26)*CapRep -> 0 | Q26: =C26*N(Scope!$H26)*N(Scope!$I26) -> 0 | R26: =C26*N(Scope!$H26)*MAX(0,1-N(Scope!$P26)-N(Scope!$Q26)) -> 0 | S26: =R26*N(Scope!$R26) -> 0 | T26: =R26-S26 -> 0 | U26: =T26*N(Scope!$I26) -> 0 | V26: =S26*N(Scope!$I26) -> 0 | W26: =C26*N(Scope!$H26)*N(Scope!$Q26) -> 0 | X26: =N(Scope!$L26)*INDEX(HrsPage,1)+N(Scope!$M26)*INDEX(HrsPage,2)+N(Scope!$N26)*INDEX(HrsPage,3)+N(Scope!$O26)*INDEX(HrsPage,4) -> 0 | Y26: =(U26*X26*K26*M26+V26*HrsDerived)*G26 -> 0 | Z26: =W26*MergeHrs*G26 -> 0 | AA26: =Y26*(1-LearnAvg)*(1-P26)+Z26 -> 0 | AB26: =C26*N(Scope!$X26) -> 0 | AC26: =N(Scope!$T26)*INDEX(ModelHrs,1)+N(Scope!$U26)*INDEX(ModelHrs,2)+N(Scope!$V26)*INDEX(ModelHrs,3)+N(Scope!$W26)*INDEX(ModelHrs,4) -> 0 | AD26: =AB26*AC26*I26*G26*L26 -> 0 | AE26: =C26*MAX(0,N(Scope!$S26)-N(Scope!$X26))*ConsolHrs*G26 -> 0 | AF26: =(AD26+AE26)*(1-O26) -> 0 | AG26: =IF(C26=0,0,(IF(Q26<=INDEX(AnchorPages,1),INDEX(AnchorAnalysis,1),IF(Q26>=INDEX(AnchorPages,5),INDEX(AnchorAnalysis,5)+(Q26-INDEX(AnchorPages,5))*(INDEX(AnchorAnalysis,5)-INDEX(AnchorAnalysis,4))/(INDEX(AnchorPages,5)-INDEX(AnchorPages,4)),INDEX(AnchorAnalysis,MATCH(Q26,AnchorPages,1))+(Q26-INDEX(AnchorPages,MATCH(Q26,AnchorPages,1)))*(INDEX(AnchorAnalysis,MATCH(Q26,AnchorPages,1)+1)-INDEX(AnchorAnalysis,MATCH(Q26,AnchorPages,1)))/(INDEX(AnchorPages,MATCH(Q26,AnchorPages,1)+1)-INDEX(AnchorPages,MATCH(Q26,AnchorPages,1)))))*G26+N(Scope!$S26)*AssessPerModel)*(1-N26)) -> 0 | AH26: =IF(C26=0,0,AB26*IFERROR(INDEX(SecHrs,MATCH(Scope!$Y26,SecNames,0)),0)+N(Scope!$Z26)*SchedHrs+N(Scope!$AA26)*GroupHrs+HandoverHrs) -> 0 | AI26: =AB26*IFERROR(INDEX(AIHrs,MATCH(Scope!$AB26,AINames,0)),0) -> 0 | AJ26: =IF(AND(C26=1,MAX(N26,O26,P26,AutoSIT,AutoUAT,AutoDep)>0),AutoSetupHrs,0) -> 0 | AK26: =AA26+AF26+AG26+AH26+AI26+AJ26 -> 0 | AL26: =AA26+AF26 -> 0 | AM26: =IF(C26=0,0,MIN(5,MAX(1,INT(N(Scope!$G26))))) -> 0 | AN26: =IF(C26=0,0,IFERROR(INDEX(ConfPct,MATCH(Scope!$AH26,ConfNames,0)),MAX(ConfPct))) -> 0 | AO26: =IF(SUM($AL$7:$AL$26)>0,AL26/SUM($AL$7:$AL$26)*ProgSharedHrs,0) -> 0 | AP26: =AK26+AO26 -> 0 | AQ26: =AP26*AN26 -> 0 | AR26: =IF(C26=0,0,IF(OR(ABS(N(Scope!$L26)+N(Scope!$M26)+N(Scope!$N26)+N(Scope!$O26)-1)>0.001,AND(N(Scope!$X26)>0,ABS(N(Scope!$T26)+N(Scope!$U26)+N(Scope!$V26)+N(Scope!$W26)-1)>0.001)),1,0)) -> 0 | AS26: =IF(AND(C26=1,N(Scope!$P26)+N(Scope!$Q26)>1),1,0) -> 0 | AT26: =IF(AND(C26=1,OR(D26="Unmapped",E26="Unmapped")),1,0) -> 0 | AU26: =IF(AND(C26=1,N(Scope!$AC26)>0,ROUND(N(Scope!$AC26)-F26,4)<>0,Scope!$AD26=""),1,0) -> 0 | AV26: =IF(AND(C26=1,OR(N(Scope!$I26)<1,N(Scope!$X26)<1)),1,0) -> 0
B27: Total | C27: =SUM(C7:C26) -> 2 | Q27: =SUM(Q7:Q26) -> 1700 | R27: =SUM(R7:R26) -> 455 | S27: =SUM(S7:S26) -> 45.5 | U27: =SUM(U7:U26) -> 1071 | V27: =SUM(V7:V26) -> 119 | W27: =SUM(W7:W26) -> 52.5 | AA27: =SUM(AA7:AA26) -> 6206.6629 | AB27: =SUM(AB7:AB26) -> 18 | AF27: =SUM(AF7:AF26) -> 2377.94 | AG27: =SUM(AG7:AG26) -> 606 | AH27: =SUM(AH7:AH26) -> 351 | AI27: =SUM(AI7:AI26) -> 128 | AJ27: =SUM(AJ7:AJ26) -> 0 | AK27: =SUM(AK7:AK26) -> 9669.6029 | AL27: =SUM(AL7:AL26) -> 8584.6029 | AO27: =SUM(AO7:AO26) -> 4655 | AP27: =SUM(AP7:AP26) -> 14324.603 | AQ27: =SUM(AQ7:AQ26) -> 2596.1602 | AR27: =SUM(AR7:AR26) -> 0 | AS27: =SUM(AS7:AS26) -> 0 | AT27: =SUM(AT7:AT26) -> 0 | AU27: =SUM(AU7:AU26) -> 0 | AV27: =SUM(AV7:AV26) -> 0
A30: Programme-level effort (shared across pairs)
B31: Item | C31: Hours | D31: Basis
B32: Initiation (programme) | C32: =IF(InvPages<=INDEX(AnchorPages,1),INDEX(AnchorInit,1),IF(InvPages>=INDEX(AnchorPages,5),INDEX(AnchorInit,5)+(InvPages-INDEX(AnchorPages,5))*(INDEX(AnchorInit,5)-INDEX(AnchorInit,4))/(INDEX(AnchorPages,5)-INDEX(AnchorPages,4)),INDEX(AnchorInit,MATCH(InvPages,AnchorPages,1))+(InvPages-INDEX(AnchorPages,MATCH(InvPages,AnchorPages,1)))*(INDEX(AnchorInit,MATCH(InvPages,AnchorPages,1)+1)-INDEX(AnchorInit,MATCH(InvPages,AnchorPages,1)))/(INDEX(AnchorPages,MATCH(InvPages,AnchorPages,1)+1)-INDEX(AnchorPages,MATCH(InvPages,AnchorPages,1)))))*(1-AutoAssess*CapAssess) -> 87 | D32: Interpolated on total inventory pages; old E14 anchors
B33: Distinct target BI tools | C33: =SUMPRODUCT((Scope!$D$7:$D$26<>"")/COUNTIF(Scope!$D$7:$D$26,Scope!$D$7:$D$26&"")) -> 1 | D33: Count
B34: Architecture & design | C34: =TargetTools*ArchPerTool+ActivePairs*ArchPerPair -> 128 | D34: Per target tool + per pair
B35: SIT & optimization | C35: =((IterCount*SITWk+SITFinal)*SITEng*HrsWk+IterCount*SITFixed)*(1-AutoSIT*CapSIT) -> 1840 | D35: Per iteration crew x weeks + fixed + final regression
B36: UAT support | C36: =(IterCount*UATWk+UATFinal)*UATEng*HrsWk*(1-AutoUAT*CapUAT) -> 440 | D36: Per iteration: 1-2 engineers x 1-2 weeks by volume
B37: Deployment support | C37: =(IterCount*DepWk*DepEng*HrsWk+IF(Pipeline="No",ReportsBuilt*ManualDepHrs,0))*(1-AutoDep*CapDep) -> 400 | D37: Per iteration, plus manual deployment without a pipeline
B38: Hypercare | C38: =Releases*HCWk*HCCrew*HrsWk -> 320 | D38: Per go-live
B39: Project management | C39: =IF(EngType="Pure BI",PMFTE*DurationWeeks*HrsWk,0) -> 1440 | D39: PM FTE x duration; 0 when bundled
B40: Shared hours allocated to pairs by development hours | C40: =ProgInitHrs+ProgArchHrs+ProgSITHrs+ProgUATHrs+ProgDepHrs+ProgHCHrs+ProgPMHrs -> 4655
A43: Hours by phase
A44: # | B44: Phase | C44: Hours | D44: % of total
A45: 1 | B45: Initiation & assessment | C45: =ProgInitHrs+AnaHrs+AutoSetTotal -> 693 | D45: =IF(TotalBaseHrs>0,C45/TotalBaseHrs,0) -> 0.048378304
A46: 2 | B46: Architecture & design | C46: =ProgArchHrs -> 128 | D46: =IF(TotalBaseHrs>0,C46/TotalBaseHrs,0) -> 0.0089356753
A47: 3 | B47: Semantic model build & consolidation | C47: =SemHrs -> 2377.94 | D47: =IF(TotalBaseHrs>0,C47/TotalBaseHrs,0) -> 0.1660039
A48: 4 | B48: Report development & unit validation | C48: =RepHrs -> 6206.6629 | D48: =IF(TotalBaseHrs>0,C48/TotalBaseHrs,0) -> 0.43328691
A49: 5 | B49: SIT & optimization | C49: =ProgSITHrs -> 1840 | D49: =IF(TotalBaseHrs>0,C49/TotalBaseHrs,0) -> 0.12845033
A50: 6 | B50: UAT support | C50: =ProgUATHrs -> 440 | D50: =IF(TotalBaseHrs>0,C50/TotalBaseHrs,0) -> 0.030716384
A51: 7 | B51: Deployment support | C51: =ProgDepHrs -> 400 | D51: =IF(TotalBaseHrs>0,C51/TotalBaseHrs,0) -> 0.027923985
A52: 8 | B52: Hypercare | C52: =ProgHCHrs -> 320 | D52: =IF(TotalBaseHrs>0,C52/TotalBaseHrs,0) -> 0.022339188
A53: 9 | B53: Security, operations & handover | C53: =SecOpsHrs -> 351 | D53: =IF(TotalBaseHrs>0,C53/TotalBaseHrs,0) -> 0.024503297
A54: 10 | B54: AI readiness | C54: =AIHrsTotal -> 128 | D54: =IF(TotalBaseHrs>0,C54/TotalBaseHrs,0) -> 0.0089356753
A55: 11 | B55: Project management | C55: =ProgPMHrs -> 1440 | D55: =IF(TotalBaseHrs>0,C55/TotalBaseHrs,0) -> 0.10052635
B56: Total base hours | C56: =SUM(PhaseHours) -> 14324.603
B57: Contingency % (weighted by pair input confidence) | C57: =IF(SUM(EffTotal)>0,SUMPRODUCT(EffTotal,EffCont)/SUM(EffTotal),0) -> 0.18123785
B58: Contingency hours | C58: =TotalBaseHrs*ContPct -> 2596.1602
B59: Risk reserve hours (Risks tab) | C59: =RiskExpectedHrs -> 90
B60: TOTAL HOURS incl. contingency and risk | C60: =TotalBaseHrs+ContHrs+RiskHrs -> 17010.763

Sheet Schedule
A1: Schedule
A2: Iterations, windows and milestones (working weeks from the planned start). Locked.
B4: Development iterations
B5: Assessment weeks | C5: =MAX(1,ROUNDUP(INDEX(PhaseHours,1)/(AssessTeam*HrsWk),0)) -> 6
B6: Assessment end week | C6: =AssessLen -> 6
B7: Architecture start week | C7: =1+ROUND(AssessLen*(1-ArchOverlap),0) -> 4
B8: Architecture end week | C8: =ArchStart+MAX(1,ROUNDUP(INDEX(PhaseHours,2)/(ArchTeam*HrsWk),0))-1 -> 5
B9: Development start week (semantic models) | C9: =MAX(AssessEnd,ArchEnd)+1 -> 7
B10: First report iteration starts (week) | C10: =DevStart+ModelLead -> 9
B11: Development iterations | C11: =IF(SolveMode="Fix iterations, compute team",MAX(1,ROUND(IterIn,0)),MAX(1,ROUNDUP((RepHrs/(PeakTeamIn*HrsWk)+(RampUp+RampDown)/2)/IterLen,0))) -> 10
B12: Report development weeks | C12: =IterCount*IterLen -> 20
B13: Last report iteration ends (week) | C13: =RepStart+RepWeeks-1 -> 28
B14: Semantic model build ends (week) | C14: =MAX(DevStart,RepStart+ROUNDUP(RepWeeks/2,0)-1) -> 18
B15: Peak report-development team (FTE, before rounding) | C15: =IF(RampWeightSum>0,RepHrs/(HrsWk*RampWeightSum),0) -> 9.1274454
B16: Development hours per iteration | C16: =DevHrsTotal/IterCount -> 858.46029
B17: Report pages delivered per iteration | C17: =(PagesFull+PagesDerived)/IterCount -> 119
B18: SIT engineers per iteration | C18: =MAX(SITMin,ROUNDUP(SITPct*DevHrsPerIter/(MAX(SITWk,0.5)*HrsWk),0)) -> 4
B19: UAT support engineers per iteration | C19: =IF(PagesPerIter<=UATThreshold,UATLow,UATHigh) -> 1
B20: SIT window starts (one iteration behind) | C20: =RepStart+IterLen -> 11
B21: SIT window ends (incl. final regression) | C21: =RepEnd+IterLen+SITFinal -> 31
B22: UAT window starts (two iterations behind) | C22: =RepStart+2*IterLen -> 13
B23: Final go-live week | C23: =RepEnd+2*IterLen+SITFinal+UATFinal -> 34
B26: Release waves
B27: Wave | C27: Development hours | D27: Cumulative hours | E27: Cumulative iterations | F27: Has scope (wave no.) | G27: Go-live week
B28: 1 | C28: =SUMIFS(EffDev,EffWave,B28) -> 5963.3044 | D28: =SUM($C$28:C28) -> 5963.3044 | E28: =IF(DevHrsTotal>0,ROUND(IterCount*D28/DevHrsTotal,0),0) -> 7 | F28: =IF(C28>0,B28,0) -> 1 | G28: =IF(C28>0,IF(B28=LastWave,LastGoLive,RepStart-1+E28*IterLen+2*IterLen),"") -> 26
B29: 2 | C29: =SUMIFS(EffDev,EffWave,B29) -> 2621.2985 | D29: =SUM($C$28:C29) -> 8584.6029 | E29: =IF(DevHrsTotal>0,ROUND(IterCount*D29/DevHrsTotal,0),0) -> 10 | F29: =IF(C29>0,B29,0) -> 2 | G29: =IF(C29>0,IF(B29=LastWave,LastGoLive,RepStart-1+E29*IterLen+2*IterLen),"") -> 34
B30: 3 | C30: =SUMIFS(EffDev,EffWave,B30) -> 0 | D30: =SUM($C$28:C30) -> 8584.6029 | E30: =IF(DevHrsTotal>0,ROUND(IterCount*D30/DevHrsTotal,0),0) -> 10 | F30: =IF(C30>0,B30,0) -> 0 | G30: =IF(C30>0,IF(B30=LastWave,LastGoLive,RepStart-1+E30*IterLen+2*IterLen),"")
B31: 4 | C31: =SUMIFS(EffDev,EffWave,B31) -> 0 | D31: =SUM($C$28:C31) -> 8584.6029 | E31: =IF(DevHrsTotal>0,ROUND(IterCount*D31/DevHrsTotal,0),0) -> 10 | F31: =IF(C31>0,B31,0) -> 0 | G31: =IF(C31>0,IF(B31=LastWave,LastGoLive,RepStart-1+E31*IterLen+2*IterLen),"")
B32: 5 | C32: =SUMIFS(EffDev,EffWave,B32) -> 0 | D32: =SUM($C$28:C32) -> 8584.6029 | E32: =IF(DevHrsTotal>0,ROUND(IterCount*D32/DevHrsTotal,0),0) -> 10 | F32: =IF(C32>0,B32,0) -> 0 | G32: =IF(C32>0,IF(B32=LastWave,LastGoLive,RepStart-1+E32*IterLen+2*IterLen),"")
B34: Last wave with scope | C34: =MAX(F28:F32) -> 2
B35: Releases (go-lives) | C35: =COUNTIF(C28:C32,">0") -> 2
B36: First go-live week | C36: =IF(Releases>0,MIN(WaveGoLive),LastGoLive) -> 26
B37: Hypercare starts (week) | C37: =FirstGoLive+1 -> 27
B38: Programme end week (last go-live + hypercare) | C38: =LastGoLive+HCWk -> 36
B39: DURATION (working weeks) | C39: =ProgEnd -> 36
B40: Duration in calendar weeks (incl. holiday allowance) | C40: =ROUNDUP(DurationWeeks*(1+HolidayPct),0) -> 38
B41: Planned end date | C41: =StartDate+CalendarWeeks*7-3 -> 46654
B44: Phase windows (feed the weekly Plan)
B45: Phase | C45: Start week | D45: End week | E45: Profile | F45: Hours | G45: Weeks
B46: Initiation & assessment | C46: =1 -> 1 | D46: =AssessEnd -> 6 | E46: Flat | F46: =INDEX(PhaseHours,1) -> 693 | G46: =MAX(0,D46-C46+1) -> 6
B47: Architecture & design | C47: =ArchStart -> 4 | D47: =ArchEnd -> 5 | E47: Flat | F47: =INDEX(PhaseHours,2) -> 128 | G47: =MAX(0,D47-C47+1) -> 2
B48: Semantic model build & consolidation | C48: =DevStart -> 7 | D48: =SemEnd -> 18 | E48: Flat | F48: =INDEX(PhaseHours,3) -> 2377.94 | G48: =MAX(0,D48-C48+1) -> 12
B49: Report development & unit validation | C49: =RepStart -> 9 | D49: =RepEnd -> 28 | E49: Ramp | F49: =INDEX(PhaseHours,4) -> 6206.6629 | G49: =MAX(0,D49-C49+1) -> 20
B50: SIT & optimization | C50: =SITStart -> 11 | D50: =SITEnd -> 31 | E50: Flat | F50: =INDEX(PhaseHours,5) -> 1840 | G50: =MAX(0,D50-C50+1) -> 21
B51: UAT support | C51: =UATStart -> 13 | D51: =LastGoLive -> 34 | E51: Flat | F51: =INDEX(PhaseHours,6) -> 440 | G51: =MAX(0,D51-C51+1) -> 22
B52: Deployment support | C52: =UATStart -> 13 | D52: =LastGoLive -> 34 | E52: Flat | F52: =INDEX(PhaseHours,7) -> 400 | G52: =MAX(0,D52-C52+1) -> 22
B53: Hypercare | C53: =HCStart -> 27 | D53: =ProgEnd -> 36 | E53: Flat | F53: =INDEX(PhaseHours,8) -> 320 | G53: =MAX(0,D53-C53+1) -> 10
B54: Security, operations & handover | C54: =RepStart -> 9 | D54: =LastGoLive -> 34 | E54: Flat | F54: =INDEX(PhaseHours,9) -> 351 | G54: =MAX(0,D54-C54+1) -> 26
B55: AI readiness | C55: =RepStart -> 9 | D55: =RepEnd -> 28 | E55: Flat | F55: =INDEX(PhaseHours,10) -> 128 | G55: =MAX(0,D55-C55+1) -> 20
B56: Project management | C56: =1 -> 1 | D56: =ProgEnd -> 36 | E56: Flat | F56: =INDEX(PhaseHours,11) -> 1440 | G56: =MAX(0,D56-C56+1) -> 36
B59: Milestones
B60: Milestone | C60: Week | D60: Date (end of week)
B61: Assessment sign-off | C61: =AssessEnd -> 6 | D61: =IF(ISNUMBER(C61),StartDate+ROUNDUP(C61*(1+HolidayPct),0)*7-3,"") -> 46437
B62: Architecture sign-off | C62: =ArchEnd -> 5 | D62: =IF(ISNUMBER(C62),StartDate+ROUNDUP(C62*(1+HolidayPct),0)*7-3,"") -> 46430
B63: First semantic models ready | C63: =RepStart-1 -> 8 | D63: =IF(ISNUMBER(C63),StartDate+ROUNDUP(C63*(1+HolidayPct),0)*7-3,"") -> 46451
B64: First report iteration starts | C64: =RepStart -> 9 | D64: =IF(ISNUMBER(C64),StartDate+ROUNDUP(C64*(1+HolidayPct),0)*7-3,"") -> 46458
B65: Last report iteration ends | C65: =RepEnd -> 28 | D65: =IF(ISNUMBER(C65),StartDate+ROUNDUP(C65*(1+HolidayPct),0)*7-3,"") -> 46598
B66: Wave 1 go-live | C66: =G28 -> 26 | D66: =IF(ISNUMBER(C66),StartDate+ROUNDUP(C66*(1+HolidayPct),0)*7-3,"") -> 46584
B67: Wave 2 go-live | C67: =G29 -> 34 | D67: =IF(ISNUMBER(C67),StartDate+ROUNDUP(C67*(1+HolidayPct),0)*7-3,"") -> 46640
B68: Wave 3 go-live | C68: =G30 | D68: =IF(ISNUMBER(C68),StartDate+ROUNDUP(C68*(1+HolidayPct),0)*7-3,"")
B69: Wave 4 go-live | C69: =G31 | D69: =IF(ISNUMBER(C69),StartDate+ROUNDUP(C69*(1+HolidayPct),0)*7-3,"")
B70: Wave 5 go-live | C70: =G32 | D70: =IF(ISNUMBER(C70),StartDate+ROUNDUP(C70*(1+HolidayPct),0)*7-3,"")
B71: Hypercare exit / programme end | C71: =ProgEnd -> 36 | D71: =IF(ISNUMBER(C71),StartDate+ROUNDUP(C71*(1+HolidayPct),0)*7-3,"") -> 46654

Sheet Plan
A1: Plan
A2: Weekly resource loading for up to 104 working weeks. Phase hours are spread over their windows; report development ramps up, peaks and ramps down.
A4: Row | B4: Start wk | C4: End wk | D4: Hours | E4: Profile / label
A5: Working week | F5: 1 | G5: 2 | H5: 3 | I5: 4 | J5: 5 | K5: 6 | L5: 7 | M5: 8 | N5: 9 | O5: 10 | P5: 11 | Q5: 12 | R5: 13 | S5: 14 | T5: 15 | U5: 16 | V5: 17 | W5: 18 | X5: 19 | Y5: 20 | Z5: 21 | AA5: 22 | AB5: 23 | AC5: 24 | AD5: 25 | AE5: 26 | AF5: 27 | AG5: 28 | AH5: 29 | AI5: 30 | AJ5: 31 | AK5: 32 | AL5: 33 | AM5: 34 | AN5: 35 | AO5: 36 | AP5: 37 | AQ5: 38 | AR5: 39 | AS5: 40 | AT5: 41 | AU5: 42 | AV5: 43 | AW5: 44 | AX5: 45 | AY5: 46 | AZ5: 47 | BA5: 48 | BB5: 49 | BC5: 50 | BD5: 51 | BE5: 52 | BF5: 53 | BG5: 54 | BH5: 55 | BI5: 56 | BJ5: 57 | BK5: 58 | BL5: 59 | BM5: 60 | BN5: 61 | BO5: 62 | BP5: 63 | BQ5: 64 | BR5: 65 | BS5: 66 | BT5: 67 | BU5: 68 | BV5: 69 | BW5: 70 | BX5: 71 | BY5: 72 | BZ5: 73 | CA5: 74 | CB5: 75 | CC5: 76 | CD5: 77 | CE5: 78 | CF5: 79 | CG5: 80 | CH5: 81 | CI5: 82 | CJ5: 83 | CK5: 84 | CL5: 85 | CM5: 86 | CN5: 87 | CO5: 88 | CP5: 89 | CQ5: 90 | CR5: 91 | CS5: 92 | CT5: 93 | CU5: 94 | CV5: 95 | CW5: 96 | CX5: 97 | CY5: 98 | CZ5: 99 | DA5: 100 | DB5: 101 | DC5: 102 | DD5: 103 | DE5: 104
A6: Week starting | F6: =StartDate+(F5-1)*7 -> 46391 | G6: =StartDate+(G5-1)*7 -> 46398 | H6: =StartDate+(H5-1)*7 -> 46405 | I6: =StartDate+(I5-1)*7 -> 46412 | J6: =StartDate+(J5-1)*7 -> 46419 | K6: =StartDate+(K5-1)*7 -> 46426 | L6: =StartDate+(L5-1)*7 -> 46433 | M6: =StartDate+(M5-1)*7 -> 46440 | ... DE6: =StartDate+(DE5-1)*7 -> 47112
A7: Phase hours per week
A8: Initiation & assessment | B8: =INDEX(PhStart,1) -> 1 | C8: =INDEX(PhEnd,1) -> 6 | D8: =INDEX(PhaseHours,1) -> 693 | E8: =Schedule!E46 -> Flat | F8: =IF(AND(F$5>=$B8,F$5<=$C8,$C8>=$B8),IF($E8="Ramp",IF(RampWeightSum>0,$D8*F$20/RampWeightSum,0),$D8/($C8-$B8+1)),0) -> 115.5 | G8: =IF(AND(G$5>=$B8,G$5<=$C8,$C8>=$B8),IF($E8="Ramp",IF(RampWeightSum>0,$D8*G$20/RampWeightSum,0),$D8/($C8-$B8+1)),0) -> 115.5 | H8: =IF(AND(H$5>=$B8,H$5<=$C8,$C8>=$B8),IF($E8="Ramp",IF(RampWeightSum>0,$D8*H$20/RampWeightSum,0),$D8/($C8-$B8+1)),0) -> 115.5 | I8: =IF(AND(I$5>=$B8,I$5<=$C8,$C8>=$B8),IF($E8="Ramp",IF(RampWeightSum>0,$D8*I$20/RampWeightSum,0),$D8/($C8-$B8+1)),0) -> 115.5 | J8: =IF(AND(J$5>=$B8,J$5<=$C8,$C8>=$B8),IF($E8="Ramp",IF(RampWeightSum>0,$D8*J$20/RampWeightSum,0),$D8/($C8-$B8+1)),0) -> 115.5 | K8: =IF(AND(K$5>=$B8,K$5<=$C8,$C8>=$B8),IF($E8="Ramp",IF(RampWeightSum>0,$D8*K$20/RampWeightSum,0),$D8/($C8-$B8+1)),0) -> 115.5 | L8: =IF(AND(L$5>=$B8,L$5<=$C8,$C8>=$B8),IF($E8="Ramp",IF(RampWeightSum>0,$D8*L$20/RampWeightSum,0),$D8/($C8-$B8+1)),0) -> 0 | M8: =IF(AND(M$5>=$B8,M$5<=$C8,$C8>=$B8),IF($E8="Ramp",IF(RampWeightSum>0,$D8*M$20/RampWeightSum,0),$D8/($C8-$B8+1)),0) -> 0 | ... DE8: =IF(AND(DE$5>=$B8,DE$5<=$C8,$C8>=$B8),IF($E8="Ramp",IF(RampWeightSum>0,$D8*DE$20/RampWeightSum,0),$D8/($C8-$B8+1)),0) -> 0
A9: Architecture & design | B9: =INDEX(PhStart,2) -> 4 | C9: =INDEX(PhEnd,2) -> 5 | D9: =INDEX(PhaseHours,2) -> 128 | E9: =Schedule!E47 -> Flat | F9: =IF(AND(F$5>=$B9,F$5<=$C9,$C9>=$B9),IF($E9="Ramp",IF(RampWeightSum>0,$D9*F$20/RampWeightSum,0),$D9/($C9-$B9+1)),0) -> 0 | G9: =IF(AND(G$5>=$B9,G$5<=$C9,$C9>=$B9),IF($E9="Ramp",IF(RampWeightSum>0,$D9*G$20/RampWeightSum,0),$D9/($C9-$B9+1)),0) -> 0 | H9: =IF(AND(H$5>=$B9,H$5<=$C9,$C9>=$B9),IF($E9="Ramp",IF(RampWeightSum>0,$D9*H$20/RampWeightSum,0),$D9/($C9-$B9+1)),0) -> 0 | I9: =IF(AND(I$5>=$B9,I$5<=$C9,$C9>=$B9),IF($E9="Ramp",IF(RampWeightSum>0,$D9*I$20/RampWeightSum,0),$D9/($C9-$B9+1)),0) -> 64 | J9: =IF(AND(J$5>=$B9,J$5<=$C9,$C9>=$B9),IF($E9="Ramp",IF(RampWeightSum>0,$D9*J$20/RampWeightSum,0),$D9/($C9-$B9+1)),0) -> 64 | K9: =IF(AND(K$5>=$B9,K$5<=$C9,$C9>=$B9),IF($E9="Ramp",IF(RampWeightSum>0,$D9*K$20/RampWeightSum,0),$D9/($C9-$B9+1)),0) -> 0 | L9: =IF(AND(L$5>=$B9,L$5<=$C9,$C9>=$B9),IF($E9="Ramp",IF(RampWeightSum>0,$D9*L$20/RampWeightSum,0),$D9/($C9-$B9+1)),0) -> 0 | M9: =IF(AND(M$5>=$B9,M$5<=$C9,$C9>=$B9),IF($E9="Ramp",IF(RampWeightSum>0,$D9*M$20/RampWeightSum,0),$D9/($C9-$B9+1)),0) -> 0 | ... DE9: =IF(AND(DE$5>=$B9,DE$5<=$C9,$C9>=$B9),IF($E9="Ramp",IF(RampWeightSum>0,$D9*DE$20/RampWeightSum,0),$D9/($C9-$B9+1)),0) -> 0
A10: Semantic model build & consolidation | B10: =INDEX(PhStart,3) -> 7 | C10: =INDEX(PhEnd,3) -> 18 | D10: =INDEX(PhaseHours,3) -> 2377.94 | E10: =Schedule!E48 -> Flat | F10: =IF(AND(F$5>=$B10,F$5<=$C10,$C10>=$B10),IF($E10="Ramp",IF(RampWeightSum>0,$D10*F$20/RampWeightSum,0),$D10/($C10-$B10+1)),0) -> 0 | G10: =IF(AND(G$5>=$B10,G$5<=$C10,$C10>=$B10),IF($E10="Ramp",IF(RampWeightSum>0,$D10*G$20/RampWeightSum,0),$D10/($C10-$B10+1)),0) -> 0 | H10: =IF(AND(H$5>=$B10,H$5<=$C10,$C10>=$B10),IF($E10="Ramp",IF(RampWeightSum>0,$D10*H$20/RampWeightSum,0),$D10/($C10-$B10+1)),0) -> 0 | I10: =IF(AND(I$5>=$B10,I$5<=$C10,$C10>=$B10),IF($E10="Ramp",IF(RampWeightSum>0,$D10*I$20/RampWeightSum,0),$D10/($C10-$B10+1)),0) -> 0 | J10: =IF(AND(J$5>=$B10,J$5<=$C10,$C10>=$B10),IF($E10="Ramp",IF(RampWeightSum>0,$D10*J$20/RampWeightSum,0),$D10/($C10-$B10+1)),0) -> 0 | K10: =IF(AND(K$5>=$B10,K$5<=$C10,$C10>=$B10),IF($E10="Ramp",IF(RampWeightSum>0,$D10*K$20/RampWeightSum,0),$D10/($C10-$B10+1)),0) -> 0 | L10: =IF(AND(L$5>=$B10,L$5<=$C10,$C10>=$B10),IF($E10="Ramp",IF(RampWeightSum>0,$D10*L$20/RampWeightSum,0),$D10/($C10-$B10+1)),0) -> 198.16167 | M10: =IF(AND(M$5>=$B10,M$5<=$C10,$C10>=$B10),IF($E10="Ramp",IF(RampWeightSum>0,$D10*M$20/RampWeightSum,0),$D10/($C10-$B10+1)),0) -> 198.16167 | ... DE10: =IF(AND(DE$5>=$B10,DE$5<=$C10,$C10>=$B10),IF($E10="Ramp",IF(RampWeightSum>0,$D10*DE$20/RampWeightSum,0),$D10/($C10-$B10+1)),0) -> 0
A11: Report development & unit validation | B11: =INDEX(PhStart,4) -> 9 | C11: =INDEX(PhEnd,4) -> 28 | D11: =INDEX(PhaseHours,4) -> 6206.6629 | E11: =Schedule!E49 -> Ramp | F11: =IF(AND(F$5>=$B11,F$5<=$C11,$C11>=$B11),IF($E11="Ramp",IF(RampWeightSum>0,$D11*F$20/RampWeightSum,0),$D11/($C11-$B11+1)),0) -> 0 | G11: =IF(AND(G$5>=$B11,G$5<=$C11,$C11>=$B11),IF($E11="Ramp",IF(RampWeightSum>0,$D11*G$20/RampWeightSum,0),$D11/($C11-$B11+1)),0) -> 0 | H11: =IF(AND(H$5>=$B11,H$5<=$C11,$C11>=$B11),IF($E11="Ramp",IF(RampWeightSum>0,$D11*H$20/RampWeightSum,0),$D11/($C11-$B11+1)),0) -> 0 | I11: =IF(AND(I$5>=$B11,I$5<=$C11,$C11>=$B11),IF($E11="Ramp",IF(RampWeightSum>0,$D11*I$20/RampWeightSum,0),$D11/($C11-$B11+1)),0) -> 0 | J11: =IF(AND(J$5>=$B11,J$5<=$C11,$C11>=$B11),IF($E11="Ramp",IF(RampWeightSum>0,$D11*J$20/RampWeightSum,0),$D11/($C11-$B11+1)),0) -> 0 | K11: =IF(AND(K$5>=$B11,K$5<=$C11,$C11>=$B11),IF($E11="Ramp",IF(RampWeightSum>0,$D11*K$20/RampWeightSum,0),$D11/($C11-$B11+1)),0) -> 0 | L11: =IF(AND(L$5>=$B11,L$5<=$C11,$C11>=$B11),IF($E11="Ramp",IF(RampWeightSum>0,$D11*L$20/RampWeightSum,0),$D11/($C11-$B11+1)),0) -> 0 | M11: =IF(AND(M$5>=$B11,M$5<=$C11,$C11>=$B11),IF($E11="Ramp",IF(RampWeightSum>0,$D11*M$20/RampWeightSum,0),$D11/($C11-$B11+1)),0) -> 0 | ... DE11: =IF(AND(DE$5>=$B11,DE$5<=$C11,$C11>=$B11),IF($E11="Ramp",IF(RampWeightSum>0,$D11*DE$20/RampWeightSum,0),$D11/($C11-$B11+1)),0) -> 0
A12: SIT & optimization | B12: =INDEX(PhStart,5) -> 11 | C12: =INDEX(PhEnd,5) -> 31 | D12: =INDEX(PhaseHours,5) -> 1840 | E12: =Schedule!E50 -> Flat | F12: =IF(AND(F$5>=$B12,F$5<=$C12,$C12>=$B12),IF($E12="Ramp",IF(RampWeightSum>0,$D12*F$20/RampWeightSum,0),$D12/($C12-$B12+1)),0) -> 0 | G12: =IF(AND(G$5>=$B12,G$5<=$C12,$C12>=$B12),IF($E12="Ramp",IF(RampWeightSum>0,$D12*G$20/RampWeightSum,0),$D12/($C12-$B12+1)),0) -> 0 | H12: =IF(AND(H$5>=$B12,H$5<=$C12,$C12>=$B12),IF($E12="Ramp",IF(RampWeightSum>0,$D12*H$20/RampWeightSum,0),$D12/($C12-$B12+1)),0) -> 0 | I12: =IF(AND(I$5>=$B12,I$5<=$C12,$C12>=$B12),IF($E12="Ramp",IF(RampWeightSum>0,$D12*I$20/RampWeightSum,0),$D12/($C12-$B12+1)),0) -> 0 | J12: =IF(AND(J$5>=$B12,J$5<=$C12,$C12>=$B12),IF($E12="Ramp",IF(RampWeightSum>0,$D12*J$20/RampWeightSum,0),$D12/($C12-$B12+1)),0) -> 0 | K12: =IF(AND(K$5>=$B12,K$5<=$C12,$C12>=$B12),IF($E12="Ramp",IF(RampWeightSum>0,$D12*K$20/RampWeightSum,0),$D12/($C12-$B12+1)),0) -> 0 | L12: =IF(AND(L$5>=$B12,L$5<=$C12,$C12>=$B12),IF($E12="Ramp",IF(RampWeightSum>0,$D12*L$20/RampWeightSum,0),$D12/($C12-$B12+1)),0) -> 0 | M12: =IF(AND(M$5>=$B12,M$5<=$C12,$C12>=$B12),IF($E12="Ramp",IF(RampWeightSum>0,$D12*M$20/RampWeightSum,0),$D12/($C12-$B12+1)),0) -> 0 | ... DE12: =IF(AND(DE$5>=$B12,DE$5<=$C12,$C12>=$B12),IF($E12="Ramp",IF(RampWeightSum>0,$D12*DE$20/RampWeightSum,0),$D12/($C12-$B12+1)),0) -> 0
A13: UAT support | B13: =INDEX(PhStart,6) -> 13 | C13: =INDEX(PhEnd,6) -> 34 | D13: =INDEX(PhaseHours,6) -> 440 | E13: =Schedule!E51 -> Flat | F13: =IF(AND(F$5>=$B13,F$5<=$C13,$C13>=$B13),IF($E13="Ramp",IF(RampWeightSum>0,$D13*F$20/RampWeightSum,0),$D13/($C13-$B13+1)),0) -> 0 | G13: =IF(AND(G$5>=$B13,G$5<=$C13,$C13>=$B13),IF($E13="Ramp",IF(RampWeightSum>0,$D13*G$20/RampWeightSum,0),$D13/($C13-$B13+1)),0) -> 0 | H13: =IF(AND(H$5>=$B13,H$5<=$C13,$C13>=$B13),IF($E13="Ramp",IF(RampWeightSum>0,$D13*H$20/RampWeightSum,0),$D13/($C13-$B13+1)),0) -> 0 | I13: =IF(AND(I$5>=$B13,I$5<=$C13,$C13>=$B13),IF($E13="Ramp",IF(RampWeightSum>0,$D13*I$20/RampWeightSum,0),$D13/($C13-$B13+1)),0) -> 0 | J13: =IF(AND(J$5>=$B13,J$5<=$C13,$C13>=$B13),IF($E13="Ramp",IF(RampWeightSum>0,$D13*J$20/RampWeightSum,0),$D13/($C13-$B13+1)),0) -> 0 | K13: =IF(AND(K$5>=$B13,K$5<=$C13,$C13>=$B13),IF($E13="Ramp",IF(RampWeightSum>0,$D13*K$20/RampWeightSum,0),$D13/($C13-$B13+1)),0) -> 0 | L13: =IF(AND(L$5>=$B13,L$5<=$C13,$C13>=$B13),IF($E13="Ramp",IF(RampWeightSum>0,$D13*L$20/RampWeightSum,0),$D13/($C13-$B13+1)),0) -> 0 | M13: =IF(AND(M$5>=$B13,M$5<=$C13,$C13>=$B13),IF($E13="Ramp",IF(RampWeightSum>0,$D13*M$20/RampWeightSum,0),$D13/($C13-$B13+1)),0) -> 0 | ... DE13: =IF(AND(DE$5>=$B13,DE$5<=$C13,$C13>=$B13),IF($E13="Ramp",IF(RampWeightSum>0,$D13*DE$20/RampWeightSum,0),$D13/($C13-$B13+1)),0) -> 0
A14: Deployment support | B14: =INDEX(PhStart,7) -> 13 | C14: =INDEX(PhEnd,7) -> 34 | D14: =INDEX(PhaseHours,7) -> 400 | E14: =Schedule!E52 -> Flat | F14: =IF(AND(F$5>=$B14,F$5<=$C14,$C14>=$B14),IF($E14="Ramp",IF(RampWeightSum>0,$D14*F$20/RampWeightSum,0),$D14/($C14-$B14+1)),0) -> 0 | G14: =IF(AND(G$5>=$B14,G$5<=$C14,$C14>=$B14),IF($E14="Ramp",IF(RampWeightSum>0,$D14*G$20/RampWeightSum,0),$D14/($C14-$B14+1)),0) -> 0 | H14: =IF(AND(H$5>=$B14,H$5<=$C14,$C14>=$B14),IF($E14="Ramp",IF(RampWeightSum>0,$D14*H$20/RampWeightSum,0),$D14/($C14-$B14+1)),0) -> 0 | I14: =IF(AND(I$5>=$B14,I$5<=$C14,$C14>=$B14),IF($E14="Ramp",IF(RampWeightSum>0,$D14*I$20/RampWeightSum,0),$D14/($C14-$B14+1)),0) -> 0 | J14: =IF(AND(J$5>=$B14,J$5<=$C14,$C14>=$B14),IF($E14="Ramp",IF(RampWeightSum>0,$D14*J$20/RampWeightSum,0),$D14/($C14-$B14+1)),0) -> 0 | K14: =IF(AND(K$5>=$B14,K$5<=$C14,$C14>=$B14),IF($E14="Ramp",IF(RampWeightSum>0,$D14*K$20/RampWeightSum,0),$D14/($C14-$B14+1)),0) -> 0 | L14: =IF(AND(L$5>=$B14,L$5<=$C14,$C14>=$B14),IF($E14="Ramp",IF(RampWeightSum>0,$D14*L$20/RampWeightSum,0),$D14/($C14-$B14+1)),0) -> 0 | M14: =IF(AND(M$5>=$B14,M$5<=$C14,$C14>=$B14),IF($E14="Ramp",IF(RampWeightSum>0,$D14*M$20/RampWeightSum,0),$D14/($C14-$B14+1)),0) -> 0 | ... DE14: =IF(AND(DE$5>=$B14,DE$5<=$C14,$C14>=$B14),IF($E14="Ramp",IF(RampWeightSum>0,$D14*DE$20/RampWeightSum,0),$D14/($C14-$B14+1)),0) -> 0
A15: Hypercare | B15: =INDEX(PhStart,8) -> 27 | C15: =INDEX(PhEnd,8) -> 36 | D15: =INDEX(PhaseHours,8) -> 320 | E15: =Schedule!E53 -> Flat | F15: =IF(AND(F$5>=$B15,F$5<=$C15,$C15>=$B15),IF($E15="Ramp",IF(RampWeightSum>0,$D15*F$20/RampWeightSum,0),$D15/($C15-$B15+1)),0) -> 0 | G15: =IF(AND(G$5>=$B15,G$5<=$C15,$C15>=$B15),IF($E15="Ramp",IF(RampWeightSum>0,$D15*G$20/RampWeightSum,0),$D15/($C15-$B15+1)),0) -> 0 | H15: =IF(AND(H$5>=$B15,H$5<=$C15,$C15>=$B15),IF($E15="Ramp",IF(RampWeightSum>0,$D15*H$20/RampWeightSum,0),$D15/($C15-$B15+1)),0) -> 0 | I15: =IF(AND(I$5>=$B15,I$5<=$C15,$C15>=$B15),IF($E15="Ramp",IF(RampWeightSum>0,$D15*I$20/RampWeightSum,0),$D15/($C15-$B15+1)),0) -> 0 | J15: =IF(AND(J$5>=$B15,J$5<=$C15,$C15>=$B15),IF($E15="Ramp",IF(RampWeightSum>0,$D15*J$20/RampWeightSum,0),$D15/($C15-$B15+1)),0) -> 0 | K15: =IF(AND(K$5>=$B15,K$5<=$C15,$C15>=$B15),IF($E15="Ramp",IF(RampWeightSum>0,$D15*K$20/RampWeightSum,0),$D15/($C15-$B15+1)),0) -> 0 | L15: =IF(AND(L$5>=$B15,L$5<=$C15,$C15>=$B15),IF($E15="Ramp",IF(RampWeightSum>0,$D15*L$20/RampWeightSum,0),$D15/($C15-$B15+1)),0) -> 0 | M15: =IF(AND(M$5>=$B15,M$5<=$C15,$C15>=$B15),IF($E15="Ramp",IF(RampWeightSum>0,$D15*M$20/RampWeightSum,0),$D15/($C15-$B15+1)),0) -> 0 | ... DE15: =IF(AND(DE$5>=$B15,DE$5<=$C15,$C15>=$B15),IF($E15="Ramp",IF(RampWeightSum>0,$D15*DE$20/RampWeightSum,0),$D15/($C15-$B15+1)),0) -> 0
A16: Security, operations & handover | B16: =INDEX(PhStart,9) -> 9 | C16: =INDEX(PhEnd,9) -> 34 | D16: =INDEX(PhaseHours,9) -> 351 | E16: =Schedule!E54 -> Flat | F16: =IF(AND(F$5>=$B16,F$5<=$C16,$C16>=$B16),IF($E16="Ramp",IF(RampWeightSum>0,$D16*F$20/RampWeightSum,0),$D16/($C16-$B16+1)),0) -> 0 | G16: =IF(AND(G$5>=$B16,G$5<=$C16,$C16>=$B16),IF($E16="Ramp",IF(RampWeightSum>0,$D16*G$20/RampWeightSum,0),$D16/($C16-$B16+1)),0) -> 0 | H16: =IF(AND(H$5>=$B16,H$5<=$C16,$C16>=$B16),IF($E16="Ramp",IF(RampWeightSum>0,$D16*H$20/RampWeightSum,0),$D16/($C16-$B16+1)),0) -> 0 | I16: =IF(AND(I$5>=$B16,I$5<=$C16,$C16>=$B16),IF($E16="Ramp",IF(RampWeightSum>0,$D16*I$20/RampWeightSum,0),$D16/($C16-$B16+1)),0) -> 0 | J16: =IF(AND(J$5>=$B16,J$5<=$C16,$C16>=$B16),IF($E16="Ramp",IF(RampWeightSum>0,$D16*J$20/RampWeightSum,0),$D16/($C16-$B16+1)),0) -> 0 | K16: =IF(AND(K$5>=$B16,K$5<=$C16,$C16>=$B16),IF($E16="Ramp",IF(RampWeightSum>0,$D16*K$20/RampWeightSum,0),$D16/($C16-$B16+1)),0) -> 0 | L16: =IF(AND(L$5>=$B16,L$5<=$C16,$C16>=$B16),IF($E16="Ramp",IF(RampWeightSum>0,$D16*L$20/RampWeightSum,0),$D16/($C16-$B16+1)),0) -> 0 | M16: =IF(AND(M$5>=$B16,M$5<=$C16,$C16>=$B16),IF($E16="Ramp",IF(RampWeightSum>0,$D16*M$20/RampWeightSum,0),$D16/($C16-$B16+1)),0) -> 0 | ... DE16: =IF(AND(DE$5>=$B16,DE$5<=$C16,$C16>=$B16),IF($E16="Ramp",IF(RampWeightSum>0,$D16*DE$20/RampWeightSum,0),$D16/($C16-$B16+1)),0) -> 0
A17: AI readiness | B17: =INDEX(PhStart,10) -> 9 | C17: =INDEX(PhEnd,10) -> 28 | D17: =INDEX(PhaseHours,10) -> 128 | E17: =Schedule!E55 -> Flat | F17: =IF(AND(F$5>=$B17,F$5<=$C17,$C17>=$B17),IF($E17="Ramp",IF(RampWeightSum>0,$D17*F$20/RampWeightSum,0),$D17/($C17-$B17+1)),0) -> 0 | G17: =IF(AND(G$5>=$B17,G$5<=$C17,$C17>=$B17),IF($E17="Ramp",IF(RampWeightSum>0,$D17*G$20/RampWeightSum,0),$D17/($C17-$B17+1)),0) -> 0 | H17: =IF(AND(H$5>=$B17,H$5<=$C17,$C17>=$B17),IF($E17="Ramp",IF(RampWeightSum>0,$D17*H$20/RampWeightSum,0),$D17/($C17-$B17+1)),0) -> 0 | I17: =IF(AND(I$5>=$B17,I$5<=$C17,$C17>=$B17),IF($E17="Ramp",IF(RampWeightSum>0,$D17*I$20/RampWeightSum,0),$D17/($C17-$B17+1)),0) -> 0 | J17: =IF(AND(J$5>=$B17,J$5<=$C17,$C17>=$B17),IF($E17="Ramp",IF(RampWeightSum>0,$D17*J$20/RampWeightSum,0),$D17/($C17-$B17+1)),0) -> 0 | K17: =IF(AND(K$5>=$B17,K$5<=$C17,$C17>=$B17),IF($E17="Ramp",IF(RampWeightSum>0,$D17*K$20/RampWeightSum,0),$D17/($C17-$B17+1)),0) -> 0 | L17: =IF(AND(L$5>=$B17,L$5<=$C17,$C17>=$B17),IF($E17="Ramp",IF(RampWeightSum>0,$D17*L$20/RampWeightSum,0),$D17/($C17-$B17+1)),0) -> 0 | M17: =IF(AND(M$5>=$B17,M$5<=$C17,$C17>=$B17),IF($E17="Ramp",IF(RampWeightSum>0,$D17*M$20/RampWeightSum,0),$D17/($C17-$B17+1)),0) -> 0 | ... DE17: =IF(AND(DE$5>=$B17,DE$5<=$C17,$C17>=$B17),IF($E17="Ramp",IF(RampWeightSum>0,$D17*DE$20/RampWeightSum,0),$D17/($C17-$B17+1)),0) -> 0
A18: Project management | B18: =INDEX(PhStart,11) -> 1 | C18: =INDEX(PhEnd,11) -> 36 | D18: =INDEX(PhaseHours,11) -> 1440 | E18: =Schedule!E56 -> Flat | F18: =IF(AND(F$5>=$B18,F$5<=$C18,$C18>=$B18),IF($E18="Ramp",IF(RampWeightSum>0,$D18*F$20/RampWeightSum,0),$D18/($C18-$B18+1)),0) -> 40 | G18: =IF(AND(G$5>=$B18,G$5<=$C18,$C18>=$B18),IF($E18="Ramp",IF(RampWeightSum>0,$D18*G$20/RampWeightSum,0),$D18/($C18-$B18+1)),0) -> 40 | H18: =IF(AND(H$5>=$B18,H$5<=$C18,$C18>=$B18),IF($E18="Ramp",IF(RampWeightSum>0,$D18*H$20/RampWeightSum,0),$D18/($C18-$B18+1)),0) -> 40 | I18: =IF(AND(I$5>=$B18,I$5<=$C18,$C18>=$B18),IF($E18="Ramp",IF(RampWeightSum>0,$D18*I$20/RampWeightSum,0),$D18/($C18-$B18+1)),0) -> 40 | J18: =IF(AND(J$5>=$B18,J$5<=$C18,$C18>=$B18),IF($E18="Ramp",IF(RampWeightSum>0,$D18*J$20/RampWeightSum,0),$D18/($C18-$B18+1)),0) -> 40 | K18: =IF(AND(K$5>=$B18,K$5<=$C18,$C18>=$B18),IF($E18="Ramp",IF(RampWeightSum>0,$D18*K$20/RampWeightSum,0),$D18/($C18-$B18+1)),0) -> 40 | L18: =IF(AND(L$5>=$B18,L$5<=$C18,$C18>=$B18),IF($E18="Ramp",IF(RampWeightSum>0,$D18*L$20/RampWeightSum,0),$D18/($C18-$B18+1)),0) -> 40 | M18: =IF(AND(M$5>=$B18,M$5<=$C18,$C18>=$B18),IF($E18="Ramp",IF(RampWeightSum>0,$D18*M$20/RampWeightSum,0),$D18/($C18-$B18+1)),0) -> 40 | ... DE18: =IF(AND(DE$5>=$B18,DE$5<=$C18,$C18>=$B18),IF($E18="Ramp",IF(RampWeightSum>0,$D18*DE$20/RampWeightSum,0),$D18/($C18-$B18+1)),0) -> 0
A19: Total phase hours | F19: =SUM(F8:F18) -> 155.5 | G19: =SUM(G8:G18) -> 155.5 | H19: =SUM(H8:H18) -> 155.5 | I19: =SUM(I8:I18) -> 219.5 | J19: =SUM(J8:J18) -> 219.5 | K19: =SUM(K8:K18) -> 155.5 | L19: =SUM(L8:L18) -> 238.16167 | M19: =SUM(M8:M18) -> 238.16167 | ... DE19: =SUM(DE8:DE18) -> 0
A20: Ramp weight (report development) | D20: =SUM(F20:DE20) -> 17 | F20: =IF(AND(F$5>=RepStart,F$5<=RepEnd),MIN(1,(F$5-RepStart+1)/(RampUp+1),(RepEnd-F$5+1)/(RampDown+1)),0) -> 0 | G20: =IF(AND(G$5>=RepStart,G$5<=RepEnd),MIN(1,(G$5-RepStart+1)/(RampUp+1),(RepEnd-G$5+1)/(RampDown+1)),0) -> 0 | H20: =IF(AND(H$5>=RepStart,H$5<=RepEnd),MIN(1,(H$5-RepStart+1)/(RampUp+1),(RepEnd-H$5+1)/(RampDown+1)),0) -> 0 | I20: =IF(AND(I$5>=RepStart,I$5<=RepEnd),MIN(1,(I$5-RepStart+1)/(RampUp+1),(RepEnd-I$5+1)/(RampDown+1)),0) -> 0 | J20: =IF(AND(J$5>=RepStart,J$5<=RepEnd),MIN(1,(J$5-RepStart+1)/(RampUp+1),(RepEnd-J$5+1)/(RampDown+1)),0) -> 0 | K20: =IF(AND(K$5>=RepStart,K$5<=RepEnd),MIN(1,(K$5-RepStart+1)/(RampUp+1),(RepEnd-K$5+1)/(RampDown+1)),0) -> 0 | L20: =IF(AND(L$5>=RepStart,L$5<=RepEnd),MIN(1,(L$5-RepStart+1)/(RampUp+1),(RepEnd-L$5+1)/(RampDown+1)),0) -> 0 | M20: =IF(AND(M$5>=RepStart,M$5<=RepEnd),MIN(1,(M$5-RepStart+1)/(RampUp+1),(RepEnd-M$5+1)/(RampDown+1)),0) -> 0 | ... DE20: =IF(AND(DE$5>=RepStart,DE$5<=RepEnd),MIN(1,(DE$5-RepStart+1)/(RampUp+1),(RepEnd-DE$5+1)/(RampDown+1)),0) -> 0
A22: Hours by role per week
A23: =Roles!B6 -> Delivery manager / PM | D23: =SUM(F23:DE23) -> 1440 | F23: =SUMPRODUCT(F$8:F$18,Roles!$C$18:$C$28) -> 40 | G23: =SUMPRODUCT(G$8:G$18,Roles!$C$18:$C$28) -> 40 | H23: =SUMPRODUCT(H$8:H$18,Roles!$C$18:$C$28) -> 40 | I23: =SUMPRODUCT(I$8:I$18,Roles!$C$18:$C$28) -> 40 | J23: =SUMPRODUCT(J$8:J$18,Roles!$C$18:$C$28) -> 40 | K23: =SUMPRODUCT(K$8:K$18,Roles!$C$18:$C$28) -> 40 | L23: =SUMPRODUCT(L$8:L$18,Roles!$C$18:$C$28) -> 40 | M23: =SUMPRODUCT(M$8:M$18,Roles!$C$18:$C$28) -> 40 | ... DE23: =SUMPRODUCT(DE$8:DE$18,Roles!$C$18:$C$28) -> 0
A24: =Roles!B7 -> Onsite architect | D24: =SUM(F24:DE24) -> 170.6 | F24: =SUMPRODUCT(F$8:F$18,Roles!$D$18:$D$28) -> 23.1 | G24: =SUMPRODUCT(G$8:G$18,Roles!$D$18:$D$28) -> 23.1 | H24: =SUMPRODUCT(H$8:H$18,Roles!$D$18:$D$28) -> 23.1 | I24: =SUMPRODUCT(I$8:I$18,Roles!$D$18:$D$28) -> 39.1 | J24: =SUMPRODUCT(J$8:J$18,Roles!$D$18:$D$28) -> 39.1 | K24: =SUMPRODUCT(K$8:K$18,Roles!$D$18:$D$28) -> 23.1 | L24: =SUMPRODUCT(L$8:L$18,Roles!$D$18:$D$28) -> 0 | M24: =SUMPRODUCT(M$8:M$18,Roles!$D$18:$D$28) -> 0 | ... DE24: =SUMPRODUCT(DE$8:DE$18,Roles!$D$18:$D$28) -> 0
A25: =Roles!B8 -> Solution architect | D25: =SUM(F25:DE25) -> 259.1 | F25: =SUMPRODUCT(F$8:F$18,Roles!$E$18:$E$28) -> 34.65 | G25: =SUMPRODUCT(G$8:G$18,Roles!$E$18:$E$28) -> 34.65 | H25: =SUMPRODUCT(H$8:H$18,Roles!$E$18:$E$28) -> 34.65 | I25: =SUMPRODUCT(I$8:I$18,Roles!$E$18:$E$28) -> 60.25 | J25: =SUMPRODUCT(J$8:J$18,Roles!$E$18:$E$28) -> 60.25 | K25: =SUMPRODUCT(K$8:K$18,Roles!$E$18:$E$28) -> 34.65 | L25: =SUMPRODUCT(L$8:L$18,Roles!$E$18:$E$28) -> 0 | M25: =SUMPRODUCT(M$8:M$18,Roles!$E$18:$E$28) -> 0 | ... DE25: =SUMPRODUCT(DE$8:DE$18,Roles!$E$18:$E$28) -> 0
A26: =Roles!B9 -> BI architect | D26: =SUM(F26:DE26) -> 765.891 | F26: =SUMPRODUCT(F$8:F$18,Roles!$F$18:$F$28) -> 34.65 | G26: =SUMPRODUCT(G$8:G$18,Roles!$F$18:$F$28) -> 34.65 | H26: =SUMPRODUCT(H$8:H$18,Roles!$F$18:$F$28) -> 34.65 | I26: =SUMPRODUCT(I$8:I$18,Roles!$F$18:$F$28) -> 57.05 | J26: =SUMPRODUCT(J$8:J$18,Roles!$F$18:$F$28) -> 57.05 | K26: =SUMPRODUCT(K$8:K$18,Roles!$F$18:$F$28) -> 34.65 | L26: =SUMPRODUCT(L$8:L$18,Roles!$F$18:$F$28) -> 29.72425 | M26: =SUMPRODUCT(M$8:M$18,Roles!$F$18:$F$28) -> 29.72425 | ... DE26: =SUMPRODUCT(DE$8:DE$18,Roles!$F$18:$F$28) -> 0
A27: =Roles!B10 -> Lead | D27: =SUM(F27:DE27) -> 1693.2573 | F27: =SUMPRODUCT(F$8:F$18,Roles!$G$18:$G$28) -> 23.1 | G27: =SUMPRODUCT(G$8:G$18,Roles!$G$18:$G$28) -> 23.1 | H27: =SUMPRODUCT(H$8:H$18,Roles!$G$18:$G$28) -> 23.1 | I27: =SUMPRODUCT(I$8:I$18,Roles!$G$18:$G$28) -> 23.1 | J27: =SUMPRODUCT(J$8:J$18,Roles!$G$18:$G$28) -> 23.1 | K27: =SUMPRODUCT(K$8:K$18,Roles!$G$18:$G$28) -> 23.1 | L27: =SUMPRODUCT(L$8:L$18,Roles!$G$18:$G$28) -> 29.72425 | M27: =SUMPRODUCT(M$8:M$18,Roles!$G$18:$G$28) -> 29.72425 | ... DE27: =SUMPRODUCT(DE$8:DE$18,Roles!$G$18:$G$28) -> 0
A28: =Roles!B11 -> Sr. engineer | D28: =SUM(F28:DE28) -> 3884.1689 | F28: =SUMPRODUCT(F$8:F$18,Roles!$H$18:$H$28) -> 0 | G28: =SUMPRODUCT(G$8:G$18,Roles!$H$18:$H$28) -> 0 | H28: =SUMPRODUCT(H$8:H$18,Roles!$H$18:$H$28) -> 0 | I28: =SUMPRODUCT(I$8:I$18,Roles!$H$18:$H$28) -> 0 | J28: =SUMPRODUCT(J$8:J$18,Roles!$H$18:$H$28) -> 0 | K28: =SUMPRODUCT(K$8:K$18,Roles!$H$18:$H$28) -> 0 | L28: =SUMPRODUCT(L$8:L$18,Roles!$H$18:$H$28) -> 99.080833 | M28: =SUMPRODUCT(M$8:M$18,Roles!$H$18:$H$28) -> 99.080833 | ... DE28: =SUMPRODUCT(DE$8:DE$18,Roles!$H$18:$H$28) -> 0
A29: =Roles!B12 -> Engineer | D29: =SUM(F29:DE29) -> 4823.5857 | F29: =SUMPRODUCT(F$8:F$18,Roles!$I$18:$I$28) -> 0 | G29: =SUMPRODUCT(G$8:G$18,Roles!$I$18:$I$28) -> 0 | H29: =SUMPRODUCT(H$8:H$18,Roles!$I$18:$I$28) -> 0 | I29: =SUMPRODUCT(I$8:I$18,Roles!$I$18:$I$28) -> 0 | J29: =SUMPRODUCT(J$8:J$18,Roles!$I$18:$I$28) -> 0 | K29: =SUMPRODUCT(K$8:K$18,Roles!$I$18:$I$28) -> 0 | L29: =SUMPRODUCT(L$8:L$18,Roles!$I$18:$I$28) -> 39.632333 | M29: =SUMPRODUCT(M$8:M$18,Roles!$I$18:$I$28) -> 39.632333 | ... DE29: =SUMPRODUCT(DE$8:DE$18,Roles!$I$18:$I$28) -> 0
A30: =Roles!B13 -> QA engineer | D30: =SUM(F30:DE30) -> 1288 | F30: =SUMPRODUCT(F$8:F$18,Roles!$J$18:$J$28) -> 0 | G30: =SUMPRODUCT(G$8:G$18,Roles!$J$18:$J$28) -> 0 | H30: =SUMPRODUCT(H$8:H$18,Roles!$J$18:$J$28) -> 0 | I30: =SUMPRODUCT(I$8:I$18,Roles!$J$18:$J$28) -> 0 | J30: =SUMPRODUCT(J$8:J$18,Roles!$J$18:$J$28) -> 0 | K30: =SUMPRODUCT(K$8:K$18,Roles!$J$18:$J$28) -> 0 | L30: =SUMPRODUCT(L$8:L$18,Roles!$J$18:$J$28) -> 0 | M30: =SUMPRODUCT(M$8:M$18,Roles!$J$18:$J$28) -> 0 | ... DE30: =SUMPRODUCT(DE$8:DE$18,Roles!$J$18:$J$28) -> 0
A32: Computed headcount (FTE)
A33: =Roles!B6 -> Delivery manager / PM | F33: =IF(RoundStep>0,ROUND(F23/HrsWk/RoundStep,0)*RoundStep,F23/HrsWk) -> 1 | G33: =IF(RoundStep>0,ROUND(G23/HrsWk/RoundStep,0)*RoundStep,G23/HrsWk) -> 1 | H33: =IF(RoundStep>0,ROUND(H23/HrsWk/RoundStep,0)*RoundStep,H23/HrsWk) -> 1 | I33: =IF(RoundStep>0,ROUND(I23/HrsWk/RoundStep,0)*RoundStep,I23/HrsWk) -> 1 | J33: =IF(RoundStep>0,ROUND(J23/HrsWk/RoundStep,0)*RoundStep,J23/HrsWk) -> 1 | K33: =IF(RoundStep>0,ROUND(K23/HrsWk/RoundStep,0)*RoundStep,K23/HrsWk) -> 1 | L33: =IF(RoundStep>0,ROUND(L23/HrsWk/RoundStep,0)*RoundStep,L23/HrsWk) -> 1 | M33: =IF(RoundStep>0,ROUND(M23/HrsWk/RoundStep,0)*RoundStep,M23/HrsWk) -> 1 | ... DE33: =IF(RoundStep>0,ROUND(DE23/HrsWk/RoundStep,0)*RoundStep,DE23/HrsWk) -> 0
A34: =Roles!B7 -> Onsite architect | F34: =IF(RoundStep>0,ROUND(F24/HrsWk/RoundStep,0)*RoundStep,F24/HrsWk) -> 0.5 | G34: =IF(RoundStep>0,ROUND(G24/HrsWk/RoundStep,0)*RoundStep,G24/HrsWk) -> 0.5 | H34: =IF(RoundStep>0,ROUND(H24/HrsWk/RoundStep,0)*RoundStep,H24/HrsWk) -> 0.5 | I34: =IF(RoundStep>0,ROUND(I24/HrsWk/RoundStep,0)*RoundStep,I24/HrsWk) -> 1 | J34: =IF(RoundStep>0,ROUND(J24/HrsWk/RoundStep,0)*RoundStep,J24/HrsWk) -> 1 | K34: =IF(RoundStep>0,ROUND(K24/HrsWk/RoundStep,0)*RoundStep,K24/HrsWk) -> 0.5 | L34: =IF(RoundStep>0,ROUND(L24/HrsWk/RoundStep,0)*RoundStep,L24/HrsWk) -> 0 | M34: =IF(RoundStep>0,ROUND(M24/HrsWk/RoundStep,0)*RoundStep,M24/HrsWk) -> 0 | ... DE34: =IF(RoundStep>0,ROUND(DE24/HrsWk/RoundStep,0)*RoundStep,DE24/HrsWk) -> 0
A35: =Roles!B8 -> Solution architect | F35: =IF(RoundStep>0,ROUND(F25/HrsWk/RoundStep,0)*RoundStep,F25/HrsWk) -> 1 | G35: =IF(RoundStep>0,ROUND(G25/HrsWk/RoundStep,0)*RoundStep,G25/HrsWk) -> 1 | H35: =IF(RoundStep>0,ROUND(H25/HrsWk/RoundStep,0)*RoundStep,H25/HrsWk) -> 1 | I35: =IF(RoundStep>0,ROUND(I25/HrsWk/RoundStep,0)*RoundStep,I25/HrsWk) -> 1.5 | J35: =IF(RoundStep>0,ROUND(J25/HrsWk/RoundStep,0)*RoundStep,J25/HrsWk) -> 1.5 | K35: =IF(RoundStep>0,ROUND(K25/HrsWk/RoundStep,0)*RoundStep,K25/HrsWk) -> 1 | L35: =IF(RoundStep>0,ROUND(L25/HrsWk/RoundStep,0)*RoundStep,L25/HrsWk) -> 0 | M35: =IF(RoundStep>0,ROUND(M25/HrsWk/RoundStep,0)*RoundStep,M25/HrsWk) -> 0 | ... DE35: =IF(RoundStep>0,ROUND(DE25/HrsWk/RoundStep,0)*RoundStep,DE25/HrsWk) -> 0
A36: =Roles!B9 -> BI architect | F36: =IF(RoundStep>0,ROUND(F26/HrsWk/RoundStep,0)*RoundStep,F26/HrsWk) -> 1 | G36: =IF(RoundStep>0,ROUND(G26/HrsWk/RoundStep,0)*RoundStep,G26/HrsWk) -> 1 | H36: =IF(RoundStep>0,ROUND(H26/HrsWk/RoundStep,0)*RoundStep,H26/HrsWk) -> 1 | I36: =IF(RoundStep>0,ROUND(I26/HrsWk/RoundStep,0)*RoundStep,I26/HrsWk) -> 1.5 | J36: =IF(RoundStep>0,ROUND(J26/HrsWk/RoundStep,0)*RoundStep,J26/HrsWk) -> 1.5 | K36: =IF(RoundStep>0,ROUND(K26/HrsWk/RoundStep,0)*RoundStep,K26/HrsWk) -> 1 | L36: =IF(RoundStep>0,ROUND(L26/HrsWk/RoundStep,0)*RoundStep,L26/HrsWk) -> 0.5 | M36: =IF(RoundStep>0,ROUND(M26/HrsWk/RoundStep,0)*RoundStep,M26/HrsWk) -> 0.5 | ... DE36: =IF(RoundStep>0,ROUND(DE26/HrsWk/RoundStep,0)*RoundStep,DE26/HrsWk) -> 0
A37: =Roles!B10 -> Lead | F37: =IF(RoundStep>0,ROUND(F27/HrsWk/RoundStep,0)*RoundStep,F27/HrsWk) -> 0.5 | G37: =IF(RoundStep>0,ROUND(G27/HrsWk/RoundStep,0)*RoundStep,G27/HrsWk) -> 0.5 | H37: =IF(RoundStep>0,ROUND(H27/HrsWk/RoundStep,0)*RoundStep,H27/HrsWk) -> 0.5 | I37: =IF(RoundStep>0,ROUND(I27/HrsWk/RoundStep,0)*RoundStep,I27/HrsWk) -> 0.5 | J37: =IF(RoundStep>0,ROUND(J27/HrsWk/RoundStep,0)*RoundStep,J27/HrsWk) -> 0.5 | K37: =IF(RoundStep>0,ROUND(K27/HrsWk/RoundStep,0)*RoundStep,K27/HrsWk) -> 0.5 | L37: =IF(RoundStep>0,ROUND(L27/HrsWk/RoundStep,0)*RoundStep,L27/HrsWk) -> 0.5 | M37: =IF(RoundStep>0,ROUND(M27/HrsWk/RoundStep,0)*RoundStep,M27/HrsWk) -> 0.5 | ... DE37: =IF(RoundStep>0,ROUND(DE27/HrsWk/RoundStep,0)*RoundStep,DE27/HrsWk) -> 0
A38: =Roles!B11 -> Sr. engineer | F38: =IF(RoundStep>0,ROUND(F28/HrsWk/RoundStep,0)*RoundStep,F28/HrsWk) -> 0 | G38: =IF(RoundStep>0,ROUND(G28/HrsWk/RoundStep,0)*RoundStep,G28/HrsWk) -> 0 | H38: =IF(RoundStep>0,ROUND(H28/HrsWk/RoundStep,0)*RoundStep,H28/HrsWk) -> 0 | I38: =IF(RoundStep>0,ROUND(I28/HrsWk/RoundStep,0)*RoundStep,I28/HrsWk) -> 0 | J38: =IF(RoundStep>0,ROUND(J28/HrsWk/RoundStep,0)*RoundStep,J28/HrsWk) -> 0 | K38: =IF(RoundStep>0,ROUND(K28/HrsWk/RoundStep,0)*RoundStep,K28/HrsWk) -> 0 | L38: =IF(RoundStep>0,ROUND(L28/HrsWk/RoundStep,0)*RoundStep,L28/HrsWk) -> 2.5 | M38: =IF(RoundStep>0,ROUND(M28/HrsWk/RoundStep,0)*RoundStep,M28/HrsWk) -> 2.5 | ... DE38: =IF(RoundStep>0,ROUND(DE28/HrsWk/RoundStep,0)*RoundStep,DE28/HrsWk) -> 0
A39: =Roles!B12 -> Engineer | F39: =IF(RoundStep>0,ROUND(F29/HrsWk/RoundStep,0)*RoundStep,F29/HrsWk) -> 0 | G39: =IF(RoundStep>0,ROUND(G29/HrsWk/RoundStep,0)*RoundStep,G29/HrsWk) -> 0 | H39: =IF(RoundStep>0,ROUND(H29/HrsWk/RoundStep,0)*RoundStep,H29/HrsWk) -> 0 | I39: =IF(RoundStep>0,ROUND(I29/HrsWk/RoundStep,0)*RoundStep,I29/HrsWk) -> 0 | J39: =IF(RoundStep>0,ROUND(J29/HrsWk/RoundStep,0)*RoundStep,J29/HrsWk) -> 0 | K39: =IF(RoundStep>0,ROUND(K29/HrsWk/RoundStep,0)*RoundStep,K29/HrsWk) -> 0 | L39: =IF(RoundStep>0,ROUND(L29/HrsWk/RoundStep,0)*RoundStep,L29/HrsWk) -> 1 | M39: =IF(RoundStep>0,ROUND(M29/HrsWk/RoundStep,0)*RoundStep,M29/HrsWk) -> 1 | ... DE39: =IF(RoundStep>0,ROUND(DE29/HrsWk/RoundStep,0)*RoundStep,DE29/HrsWk) -> 0
A40: =Roles!B13 -> QA engineer | F40: =IF(RoundStep>0,ROUND(F30/HrsWk/RoundStep,0)*RoundStep,F30/HrsWk) -> 0 | G40: =IF(RoundStep>0,ROUND(G30/HrsWk/RoundStep,0)*RoundStep,G30/HrsWk) -> 0 | H40: =IF(RoundStep>0,ROUND(H30/HrsWk/RoundStep,0)*RoundStep,H30/HrsWk) -> 0 | I40: =IF(RoundStep>0,ROUND(I30/HrsWk/RoundStep,0)*RoundStep,I30/HrsWk) -> 0 | J40: =IF(RoundStep>0,ROUND(J30/HrsWk/RoundStep,0)*RoundStep,J30/HrsWk) -> 0 | K40: =IF(RoundStep>0,ROUND(K30/HrsWk/RoundStep,0)*RoundStep,K30/HrsWk) -> 0 | L40: =IF(RoundStep>0,ROUND(L30/HrsWk/RoundStep,0)*RoundStep,L30/HrsWk) -> 0 | M40: =IF(RoundStep>0,ROUND(M30/HrsWk/RoundStep,0)*RoundStep,M30/HrsWk) -> 0 | ... DE40: =IF(RoundStep>0,ROUND(DE30/HrsWk/RoundStep,0)*RoundStep,DE30/HrsWk) -> 0
A42: Manual adjustments (+/- FTE) - optional inputs
A43: =Roles!B6 -> Delivery manager / PM
A44: =Roles!B7 -> Onsite architect
A45: =Roles!B8 -> Solution architect
A46: =Roles!B9 -> BI architect
A47: =Roles!B10 -> Lead
A48: =Roles!B11 -> Sr. engineer
A49: =Roles!B12 -> Engineer
A50: =Roles!B13 -> QA engineer
A52: Final headcount (FTE) - plan of record | D52: Plan hours
A53: =Roles!B6 -> Delivery manager / PM | D53: =SUM(F53:DE53)*HrsWk -> 1440 | E53: =A53 -> Delivery manager / PM | F53: =MAX(0,F33+N(F43)) -> 1 | G53: =MAX(0,G33+N(G43)) -> 1 | H53: =MAX(0,H33+N(H43)) -> 1 | I53: =MAX(0,I33+N(I43)) -> 1 | J53: =MAX(0,J33+N(J43)) -> 1 | K53: =MAX(0,K33+N(K43)) -> 1 | L53: =MAX(0,L33+N(L43)) -> 1 | M53: =MAX(0,M33+N(M43)) -> 1 | ... DE53: =MAX(0,DE33+N(DE43)) -> 0
A54: =Roles!B7 -> Onsite architect | D54: =SUM(F54:DE54)*HrsWk -> 160 | E54: =A54 -> Onsite architect | F54: =MAX(0,F34+N(F44)) -> 0.5 | G54: =MAX(0,G34+N(G44)) -> 0.5 | H54: =MAX(0,H34+N(H44)) -> 0.5 | I54: =MAX(0,I34+N(I44)) -> 1 | J54: =MAX(0,J34+N(J44)) -> 1 | K54: =MAX(0,K34+N(K44)) -> 0.5 | L54: =MAX(0,L34+N(L44)) -> 0 | M54: =MAX(0,M34+N(M44)) -> 0 | ... DE54: =MAX(0,DE34+N(DE44)) -> 0
A55: =Roles!B8 -> Solution architect | D55: =SUM(F55:DE55)*HrsWk -> 280 | E55: =A55 -> Solution architect | F55: =MAX(0,F35+N(F45)) -> 1 | G55: =MAX(0,G35+N(G45)) -> 1 | H55: =MAX(0,H35+N(H45)) -> 1 | I55: =MAX(0,I35+N(I45)) -> 1.5 | J55: =MAX(0,J35+N(J45)) -> 1.5 | K55: =MAX(0,K35+N(K45)) -> 1 | L55: =MAX(0,L35+N(L45)) -> 0 | M55: =MAX(0,M35+N(M45)) -> 0 | ... DE55: =MAX(0,DE35+N(DE45)) -> 0
A56: =Roles!B9 -> BI architect | D56: =SUM(F56:DE56)*HrsWk -> 720 | E56: =A56 -> BI architect | F56: =MAX(0,F36+N(F46)) -> 1 | G56: =MAX(0,G36+N(G46)) -> 1 | H56: =MAX(0,H36+N(H46)) -> 1 | I56: =MAX(0,I36+N(I46)) -> 1.5 | J56: =MAX(0,J36+N(J46)) -> 1.5 | K56: =MAX(0,K36+N(K46)) -> 1 | L56: =MAX(0,L36+N(L46)) -> 0.5 | M56: =MAX(0,M36+N(M46)) -> 0.5 | ... DE56: =MAX(0,DE36+N(DE46)) -> 0
A57: =Roles!B10 -> Lead | D57: =SUM(F57:DE57)*HrsWk -> 1600 | E57: =A57 -> Lead | F57: =MAX(0,F37+N(F47)) -> 0.5 | G57: =MAX(0,G37+N(G47)) -> 0.5 | H57: =MAX(0,H37+N(H47)) -> 0.5 | I57: =MAX(0,I37+N(I47)) -> 0.5 | J57: =MAX(0,J37+N(J47)) -> 0.5 | K57: =MAX(0,K37+N(K47)) -> 0.5 | L57: =MAX(0,L37+N(L47)) -> 0.5 | M57: =MAX(0,M37+N(M47)) -> 0.5 | ... DE57: =MAX(0,DE37+N(DE47)) -> 0
A58: =Roles!B11 -> Sr. engineer | D58: =SUM(F58:DE58)*HrsWk -> 3920 | E58: =A58 -> Sr. engineer | F58: =MAX(0,F38+N(F48)) -> 0 | G58: =MAX(0,G38+N(G48)) -> 0 | H58: =MAX(0,H38+N(H48)) -> 0 | I58: =MAX(0,I38+N(I48)) -> 0 | J58: =MAX(0,J38+N(J48)) -> 0 | K58: =MAX(0,K38+N(K48)) -> 0 | L58: =MAX(0,L38+N(L48)) -> 2.5 | M58: =MAX(0,M38+N(M48)) -> 2.5 | ... DE58: =MAX(0,DE38+N(DE48)) -> 0
A59: =Roles!B12 -> Engineer | D59: =SUM(F59:DE59)*HrsWk -> 4760 | E59: =A59 -> Engineer | F59: =MAX(0,F39+N(F49)) -> 0 | G59: =MAX(0,G39+N(G49)) -> 0 | H59: =MAX(0,H39+N(H49)) -> 0 | I59: =MAX(0,I39+N(I49)) -> 0 | J59: =MAX(0,J39+N(J49)) -> 0 | K59: =MAX(0,K39+N(K49)) -> 0 | L59: =MAX(0,L39+N(L49)) -> 1 | M59: =MAX(0,M39+N(M49)) -> 1 | ... DE59: =MAX(0,DE39+N(DE49)) -> 0
A60: =Roles!B13 -> QA engineer | D60: =SUM(F60:DE60)*HrsWk -> 1260 | E60: =A60 -> QA engineer | F60: =MAX(0,F40+N(F50)) -> 0 | G60: =MAX(0,G40+N(G50)) -> 0 | H60: =MAX(0,H40+N(H50)) -> 0 | I60: =MAX(0,I40+N(I50)) -> 0 | J60: =MAX(0,J40+N(J50)) -> 0 | K60: =MAX(0,K40+N(K50)) -> 0 | L60: =MAX(0,L40+N(L50)) -> 0 | M60: =MAX(0,M40+N(M50)) -> 0 | ... DE60: =MAX(0,DE40+N(DE50)) -> 0
A61: Total headcount | D61: =SUM(D53:D60) -> 14140 | F61: =SUM(F53:F60) -> 4 | G61: =SUM(G53:G60) -> 4 | H61: =SUM(H53:H60) -> 4 | I61: =SUM(I53:I60) -> 5.5 | J61: =SUM(J53:J60) -> 5.5 | K61: =SUM(K53:K60) -> 4 | L61: =SUM(L53:L60) -> 5.5 | M61: =SUM(M53:M60) -> 5.5 | ... DE61: =SUM(DE53:DE60) -> 0
A64: Team summary
A65: Peak team (FTE) | D65: =MAX(PlanHeadcount) -> 18.5
A66: Average team over the engagement (FTE) | D66: =IF(DurationWeeks>0,SUM(PlanHeadcount)/DurationWeeks,0) -> 9.8194444
A67: Average team during report iterations (FTE) | D67: =IF(RepWeeks>0,SUMIFS(PlanHeadcount,PlanWeeks,">="&RepStart,PlanWeeks,"<="&RepEnd)/RepWeeks,0) -> 14.35
A68: Total person-weeks | D68: =SUM(PlanHeadcount) -> 353.5
A69: Plan hours vs estimate (variance) | D69: =IF(TotalBaseHrs>0,PlanHrs/TotalBaseHrs-1,0) -> -0.012887121

Sheet Cost
A1: Cost
A2: Cost by role and phase, and the price build-up. Locked.
A4: Cost by role (estimate hours x role mix x rate card)
A5: # | B5: Plan role | C5: Location | D5: Hours | E5: Rate (USD/h) | F5: Cost (USD) | G5: Plan hours
A6: 1 | B6: =Roles!B6 -> Delivery manager / PM | C6: =Roles!E6 -> India | D6: =SUMPRODUCT(PhaseHours,Roles!$C$18:$C$28) -> 1440 | E6: =Roles!D6 -> 82 | F6: =D6*E6 -> 118080 | G6: =Plan!D53 -> 1440
A7: 2 | B7: =Roles!B7 -> Onsite architect | C7: =Roles!E7 -> USA | D7: =SUMPRODUCT(PhaseHours,Roles!$D$18:$D$28) -> 170.6 | E7: =Roles!D7 -> 185 | F7: =D7*E7 -> 31561 | G7: =Plan!D54 -> 160
A8: 3 | B8: =Roles!B8 -> Solution architect | C8: =Roles!E8 -> India | D8: =SUMPRODUCT(PhaseHours,Roles!$E$18:$E$28) -> 259.1 | E8: =Roles!D8 -> 87 | F8: =D8*E8 -> 22541.7 | G8: =Plan!D55 -> 280
A9: 4 | B9: =Roles!B9 -> BI architect | C9: =Roles!E9 -> India | D9: =SUMPRODUCT(PhaseHours,Roles!$F$18:$F$28) -> 765.891 | E9: =Roles!D9 -> 70 | F9: =D9*E9 -> 53612.37 | G9: =Plan!D56 -> 720
A10: 5 | B10: =Roles!B10 -> Lead | C10: =Roles!E10 -> India | D10: =SUMPRODUCT(PhaseHours,Roles!$G$18:$G$28) -> 1693.2573 | E10: =Roles!D10 -> 70 | F10: =D10*E10 -> 118528.01 | G10: =Plan!D57 -> 1600
A11: 6 | B11: =Roles!B11 -> Sr. engineer | C11: =Roles!E11 -> India | D11: =SUMPRODUCT(PhaseHours,Roles!$H$18:$H$28) -> 3884.1689 | E11: =Roles!D11 -> 62 | F11: =D11*E11 -> 240818.47 | G11: =Plan!D58 -> 3920
A12: 7 | B12: =Roles!B12 -> Engineer | C12: =Roles!E12 -> India | D12: =SUMPRODUCT(PhaseHours,Roles!$I$18:$I$28) -> 4823.5857 | E12: =Roles!D12 -> 50 | F12: =D12*E12 -> 241179.29 | G12: =Plan!D59 -> 4760
A13: 8 | B13: =Roles!B13 -> QA engineer | C13: =Roles!E13 -> India | D13: =SUMPRODUCT(PhaseHours,Roles!$J$18:$J$28) -> 1288 | E13: =Roles!D13 -> 57.5 | F13: =D13*E13 -> 74060 | G13: =Plan!D60 -> 1260
B14: Total | D14: =SUM(D6:D13) -> 14324.603 | F14: =SUM(F6:F13) -> 900380.84 | G14: =SUM(G6:G13) -> 14140
B15: Implied blended rate from role mix | F15: =IF(RoleHrsTotal>0,RoleCostTotal/RoleHrsTotal,0) -> 62.855553
B16: Onsite (USA) share of hours | F16: =IF(RoleHrsTotal>0,SUMIFS(RoleHrs,RoleLocCol,"USA")/RoleHrsTotal,0) -> 0.01190958
A19: Cost by phase
A20: # | B20: Phase | C20: Hours | D20: Rate used (USD/h) | E20: Cost (USD)
A21: 1 | B21: Initiation & assessment | C21: =INDEX(PhaseHours,1) -> 693 | D21: =IF(CostMode="Blended",BlendedRate,SUMPRODUCT(MMULT(Roles!$C$18:$J$18,RoleRates))) -> 98.1 | E21: =C21*D21 -> 67983.3
A22: 2 | B22: Architecture & design | C22: =INDEX(PhaseHours,2) -> 128 | D22: =IF(CostMode="Blended",BlendedRate,SUMPRODUCT(MMULT(Roles!$C$19:$J$19,RoleRates))) -> 105.55 | E22: =C22*D22 -> 13510.4
A23: 3 | B23: Semantic model build & consolidation | C23: =INDEX(PhaseHours,3) -> 2377.94 | D23: =IF(CostMode="Blended",BlendedRate,SUMPRODUCT(MMULT(Roles!$C$20:$J$20,RoleRates))) -> 62 | E23: =C23*D23 -> 147432.28
A24: 4 | B24: Report development & unit validation | C24: =INDEX(PhaseHours,4) -> 6206.6629 | D24: =IF(CostMode="Blended",BlendedRate,SUMPRODUCT(MMULT(Roles!$C$21:$J$21,RoleRates))) -> 55.6 | E24: =C24*D24 -> 345090.46
A25: 5 | B25: SIT & optimization | C25: =INDEX(PhaseHours,5) -> 1840 | D25: =IF(CostMode="Blended",BlendedRate,SUMPRODUCT(MMULT(Roles!$C$22:$J$22,RoleRates))) -> 57.25 | E25: =C25*D25 -> 105340
A26: 6 | B26: UAT support | C26: =INDEX(PhaseHours,6) -> 440 | D26: =IF(CostMode="Blended",BlendedRate,SUMPRODUCT(MMULT(Roles!$C$23:$J$23,RoleRates))) -> 58.8 | E26: =C26*D26 -> 25872
A27: 7 | B27: Deployment support | C27: =INDEX(PhaseHours,7) -> 400 | D27: =IF(CostMode="Blended",BlendedRate,SUMPRODUCT(MMULT(Roles!$C$24:$J$24,RoleRates))) -> 64.4 | E27: =C27*D27 -> 25760
A28: 8 | B28: Hypercare | C28: =INDEX(PhaseHours,8) -> 320 | D28: =IF(CostMode="Blended",BlendedRate,SUMPRODUCT(MMULT(Roles!$C$25:$J$25,RoleRates))) -> 61 | E28: =C28*D28 -> 19520
A29: 9 | B29: Security, operations & handover | C29: =INDEX(PhaseHours,9) -> 351 | D29: =IF(CostMode="Blended",BlendedRate,SUMPRODUCT(MMULT(Roles!$C$26:$J$26,RoleRates))) -> 66.8 | E29: =C29*D29 -> 23446.8
A30: 10 | B30: AI readiness | C30: =INDEX(PhaseHours,10) -> 128 | D30: =IF(CostMode="Blended",BlendedRate,SUMPRODUCT(MMULT(Roles!$C$27:$J$27,RoleRates))) -> 65.2 | E30: =C30*D30 -> 8345.6
A31: 11 | B31: Project management | C31: =INDEX(PhaseHours,11) -> 1440 | D31: =IF(CostMode="Blended",BlendedRate,SUMPRODUCT(MMULT(Roles!$C$28:$J$28,RoleRates))) -> 82 | E31: =C31*D31 -> 118080
B32: Total | C32: =SUM(C21:C31) -> 14324.603 | E32: =SUM(E21:E31) -> 900380.84
A35: Price build-up
B36: 1. Base cost (selected cost mode) | F36: =IF(CostMode="Blended",TotalBaseHrs*BlendedRate,RoleCostTotal) -> 900380.84
B37: Effective rate (USD/h) | F37: =IF(TotalBaseHrs>0,BaseCost/TotalBaseHrs,0) -> 62.855553
B38: 2. Contingency (by input confidence) | F38: =ContHrs*EffRate -> 163183.08
B39: 3. Risk reserve (Risks tab) | F39: =RiskHrs*EffRate -> 5656.9998
B40: Services before discount | F40: =BaseCost+ContCost+RiskCost -> 1069220.9
B41: Discount on bill rates | F41: =-ServicesGross*DiscountPct -> 0
B42: Services price | F42: =ServicesGross+DiscountAmt -> 1069220.9
B43: 4. Pass-throughs (tools, travel, other) | F43: =PassTools+PassTravel+PassOther -> 0
B44: 5. FIXED PRICE | F44: =ServicesNet+PassThrough -> 1069220.9
A47: Payment milestones
A48: # | B48: Milestone | C48: % | D48: Amount (USD)
A49: 1 | B49: =IF(INDEX(MilestoneNames,1)="","",INDEX(MilestoneNames,1)) -> Contract signature | C49: =INDEX(MilestonePct,1) -> 0.1 | D49: =FixedPrice*C49 -> 106922.09
A50: 2 | B50: =IF(INDEX(MilestoneNames,2)="","",INDEX(MilestoneNames,2)) -> Assessment sign-off | C50: =INDEX(MilestonePct,2) -> 0.15 | D50: =FixedPrice*C50 -> 160383.14
A51: 3 | B51: =IF(INDEX(MilestoneNames,3)="","",INDEX(MilestoneNames,3)) -> Architecture sign-off | C51: =INDEX(MilestonePct,3) -> 0.1 | D51: =FixedPrice*C51 -> 106922.09
A52: 4 | B52: =IF(INDEX(MilestoneNames,4)="","",INDEX(MilestoneNames,4)) -> Mid-development | C52: =INDEX(MilestonePct,4) -> 0.25 | D52: =FixedPrice*C52 -> 267305.23
A53: 5 | B53: =IF(INDEX(MilestoneNames,5)="","",INDEX(MilestoneNames,5)) -> Final go-live | C53: =INDEX(MilestonePct,5) -> 0.3 | D53: =FixedPrice*C53 -> 320766.28
A54: 6 | B54: =IF(INDEX(MilestoneNames,6)="","",INDEX(MilestoneNames,6)) -> Hypercare exit | C54: =INDEX(MilestonePct,6) -> 0.1 | D54: =FixedPrice*C54 -> 106922.09

Sheet Assumptions
A1: Assumptions & exclusions
A2: Attach to the proposal. Every value is live from the input and reference tabs.
B5: Engagement
B6: Client / opportunity | C6: =Client&" - "&Opportunity -> Example Client - BI modernisation programme
B7: Estimate version and date | C7: =EstVersion&" - "&TEXT(EstDate,"dd-mmm-yyyy") -> v2.0-draft - 13-Oct-2026
B8: Planned start | C8: =StartDate -> 46391
B9: Engagement type | C9: =EngType -> Pure BI | D9: Bundled engagements carry PM in the ETL/EDW programme
B11: Delivery assumptions
B12: Productive hours per person-week | C12: =HrsWk -> 40
B13: Iteration length (weeks) | C13: =IterLen -> 2
B14: Development iterations | C14: =IterCount -> 10
B15: Solve mode | C15: =SolveMode -> Fix team, compute iterations
B16: Peak report-development team (FTE) | C16: =PeakRepTeam -> 9.1274454
B17: Ramp-up / ramp-down weeks | C17: =RampUp&" / "&RampDown -> 3 / 3
B18: Model lead time before report iterations (weeks) | C18: =ModelLead -> 2
B19: SIT: weeks per iteration / engineers / fixed h per iteration | C19: =SITWk&" / "&SITEng&" / "&SITFixed -> 1 / 4 / 8
B20: UAT support: weeks per iteration / engineers | C20: =UATWk&" / "&UATEng -> 1 / 1 | D20: 1 engineer up to the volume threshold, 2 above it
B21: Deployment support: weeks per iteration / engineers | C21: =DepWk&" / "&DepEng -> 1 / 1
B22: Deployment pipeline available | C22: =Pipeline -> Yes
B23: Hypercare weeks per go-live / crew | C23: =HCWk&" / "&HCCrew -> 2 / 2
B24: Holiday allowance (calendar dates) | C24: =HolidayPct -> 0.04
B26: Automation (global % x automatable cap = saving)
B27: Assessment | C27: =TEXT(AutoAssess,"0%")&" x "&TEXT(CapAssess,"0%")&" = "&TEXT(AutoAssess*CapAssess,"0.0%") -> 0% x 60% = 0.0%
B28: Semantic model | C28: =TEXT(AutoSem,"0%")&" x "&TEXT(CapSem,"0%")&" = "&TEXT(AutoSem*CapSem,"0.0%") -> 0% x 40% = 0.0%
B29: Report development | C29: =TEXT(AutoRep,"0%")&" x "&TEXT(CapRep,"0%")&" = "&TEXT(AutoRep*CapRep,"0.0%") -> 0% x 60% = 0.0%
B30: SIT | C30: =TEXT(AutoSIT,"0%")&" x "&TEXT(CapSIT,"0%")&" = "&TEXT(AutoSIT*CapSIT,"0.0%") -> 0% x 30% = 0.0%
B31: UAT support | C31: =TEXT(AutoUAT,"0%")&" x "&TEXT(CapUAT,"0%")&" = "&TEXT(AutoUAT*CapUAT,"0.0%") -> 0% x 20% = 0.0%
B32: Deployment support | C32: =TEXT(AutoDep,"0%")&" x "&TEXT(CapDep,"0%")&" = "&TEXT(AutoDep*CapDep,"0.0%") -> 0% x 60% = 0.0%
B34: Estimation basis
B35: Hours per report page (S / M / C / VC / Derived) | C35: =INDEX(HrsPage,1)&" / "&INDEX(HrsPage,2)&" / "&INDEX(HrsPage,3)&" / "&INDEX(HrsPage,4)&" / "&HrsDerived -> 3.625 / 6.625 / 9.125 / 12.625 / 1 | D35: Carried from the previous calculator
B36: Learning gain by quarter of iterations | C36: =TEXT(INDEX(LearnQ,1),"0%")&" / "&TEXT(INDEX(LearnQ,2),"0%")&" / "&TEXT(INDEX(LearnQ,3),"0%")&" / "&TEXT(INDEX(LearnQ,4),"0%") -> 0% / 10% / 15% / 20%
B37: Semantic model hours (S / M / C / VC) | C37: =INDEX(ModelHrs,1)&" / "&INDEX(ModelHrs,2)&" / "&INDEX(ModelHrs,3)&" / "&INDEX(ModelHrs,4) -> 80 / 120 / 200 / 320
B38: Contingency (weighted by input confidence) | C38: =ContPct -> 0.18123785
B39: Risk reserve hours | C39: =RiskHrs -> 90
B40: Cost mode / discount | C40: =CostMode&" / "&TEXT(DiscountPct,"0%") -> Role mix / 0%
B42: Pair overrides (factor overrides must carry a reason)
B43: Pair | C43: Suggested -> used factor | D43: Reason
B44: =IF(Effort!C7=1,Effort!B7,"") -> Finance OBIEE to Power BI | C44: =IF(Effort!C7=1,TEXT(Effort!F7,"0.00")&" -> "&TEXT(Effort!G7,"0.00"),"") -> 1.00 -> 1.00 | D44: =IF(Effort!C7=1,IF(Scope!$AD7="","",Scope!$AD7),"")
B45: =IF(Effort!C8=1,Effort!B8,"") -> Sales Tableau to Power BI | C45: =IF(Effort!C8=1,TEXT(Effort!F8,"0.00")&" -> "&TEXT(Effort!G8,"0.00"),"") -> 0.95 -> 0.95 | D45: =IF(Effort!C8=1,IF(Scope!$AD8="","",Scope!$AD8),"")
B46: =IF(Effort!C9=1,Effort!B9,"") | C46: =IF(Effort!C9=1,TEXT(Effort!F9,"0.00")&" -> "&TEXT(Effort!G9,"0.00"),"") | D46: =IF(Effort!C9=1,IF(Scope!$AD9="","",Scope!$AD9),"")
B47: =IF(Effort!C10=1,Effort!B10,"") | C47: =IF(Effort!C10=1,TEXT(Effort!F10,"0.00")&" -> "&TEXT(Effort!G10,"0.00"),"") | D47: =IF(Effort!C10=1,IF(Scope!$AD10="","",Scope!$AD10),"")
B48: =IF(Effort!C11=1,Effort!B11,"") | C48: =IF(Effort!C11=1,TEXT(Effort!F11,"0.00")&" -> "&TEXT(Effort!G11,"0.00"),"") | D48: =IF(Effort!C11=1,IF(Scope!$AD11="","",Scope!$AD11),"")
B49: =IF(Effort!C12=1,Effort!B12,"") | C49: =IF(Effort!C12=1,TEXT(Effort!F12,"0.00")&" -> "&TEXT(Effort!G12,"0.00"),"") | D49: =IF(Effort!C12=1,IF(Scope!$AD12="","",Scope!$AD12),"")
B50: =IF(Effort!C13=1,Effort!B13,"") | C50: =IF(Effort!C13=1,TEXT(Effort!F13,"0.00")&" -> "&TEXT(Effort!G13,"0.00"),"") | D50: =IF(Effort!C13=1,IF(Scope!$AD13="","",Scope!$AD13),"")
B51: =IF(Effort!C14=1,Effort!B14,"") | C51: =IF(Effort!C14=1,TEXT(Effort!F14,"0.00")&" -> "&TEXT(Effort!G14,"0.00"),"") | D51: =IF(Effort!C14=1,IF(Scope!$AD14="","",Scope!$AD14),"")
B52: =IF(Effort!C15=1,Effort!B15,"") | C52: =IF(Effort!C15=1,TEXT(Effort!F15,"0.00")&" -> "&TEXT(Effort!G15,"0.00"),"") | D52: =IF(Effort!C15=1,IF(Scope!$AD15="","",Scope!$AD15),"")
B53: =IF(Effort!C16=1,Effort!B16,"") | C53: =IF(Effort!C16=1,TEXT(Effort!F16,"0.00")&" -> "&TEXT(Effort!G16,"0.00"),"") | D53: =IF(Effort!C16=1,IF(Scope!$AD16="","",Scope!$AD16),"")
B54: =IF(Effort!C17=1,Effort!B17,"") | C54: =IF(Effort!C17=1,TEXT(Effort!F17,"0.00")&" -> "&TEXT(Effort!G17,"0.00"),"") | D54: =IF(Effort!C17=1,IF(Scope!$AD17="","",Scope!$AD17),"")
B55: =IF(Effort!C18=1,Effort!B18,"") | C55: =IF(Effort!C18=1,TEXT(Effort!F18,"0.00")&" -> "&TEXT(Effort!G18,"0.00"),"") | D55: =IF(Effort!C18=1,IF(Scope!$AD18="","",Scope!$AD18),"")
... B63: =IF(Effort!C26=1,Effort!B26,"") | C63: =IF(Effort!C26=1,TEXT(Effort!F26,"0.00")&" -> "&TEXT(Effort!G26,"0.00"),"") | D63: =IF(Effort!C26=1,IF(Scope!$AD26="","",Scope!$AD26),"")
B65: Exclusions
B66: Data / ETL / EDW migration and data reconciliation of the underlying platform (estimated separately).
B67: BI and data-platform licences and infrastructure, unless entered as a pass-through.
B68: Remediation of source data quality issues.
B69: Reports retired or consolidated by rationalisation (only merge effort is included).
B70: End-user training beyond the training and handover allowance per pair.
B71: Work outside the scope rows and risk register in this workbook.

Sheet Checks
A1: Checks
A2: Every check must PASS before the estimate is quoted. The Summary banner reads from here.
A4: # | B4: Check | C4: Result | D4: Detail
A5: 1 | B5: At least one active migration pair | C5: =IF(IFERROR(ActivePairs>=1,FALSE()),"PASS","FAIL") -> PASS | D5: =IFERROR(ActivePairs&" active pair(s)","") -> 2 active pair(s)
A6: 2 | B6: Every active pair maps to source and target archetypes | C6: =IF(IFERROR(FlagMap=0,FALSE()),"PASS","FAIL") -> PASS | D6: =IFERROR(FlagMap&" pair(s) with an unmapped tool - add the tool on Lists","") -> 0 pair(s) with an unmapped tool - add the tool on Lists
A7: 3 | B7: Report and semantic-model complexity mixes total 100% | C7: =IF(IFERROR(FlagMix=0,FALSE()),"PASS","FAIL") -> PASS | D7: =IFERROR(FlagMix&" pair(s) with a mix that does not total 100%","") -> 0 pair(s) with a mix that does not total 100%
A8: 4 | B8: Retired + Consolidated <= 100% per pair | C8: =IF(IFERROR(FlagRat=0,FALSE()),"PASS","FAIL") -> PASS | D8: =IFERROR(FlagRat&" pair(s) over 100%","") -> 0 pair(s) over 100%
A9: 5 | B9: Every pair-factor override has a reason | C9: =IF(IFERROR(FlagWhy=0,FALSE()),"PASS","FAIL") -> PASS | D9: =IFERROR(FlagWhy&" override(s) without a reason","") -> 0 override(s) without a reason
A10: 6 | B10: Pages per report >= 1 and at least one target model per pair | C10: =IF(IFERROR(FlagPpr=0,FALSE()),"PASS","FAIL") -> PASS | D10: =IFERROR(FlagPpr&" pair(s) to fix","") -> 0 pair(s) to fix
A11: 7 | B11: Role mix rows each total 100% | C11: =IF(IFERROR(SUMPRODUCT(--(ABS(RoleMixTotals-1)>0.0001))=0,FALSE()),"PASS","FAIL") -> PASS | D11: =IFERROR(SUMPRODUCT(--(ABS(RoleMixTotals-1)>0.0001))&" phase row(s) off","") -> 0 phase row(s) off
A12: 8 | B12: Every plan role has a rate | C12: =IF(IFERROR(COUNTIF(RoleRates,">0")=COUNTA(RoleNames),FALSE()),"PASS","FAIL") -> PASS | D12: =IFERROR(COUNTIF(RoleRates,">0")&" of "&COUNTA(RoleNames)&" roles priced","") -> 8 of 8 roles priced
A13: 9 | B13: Payment milestones total 100% | C13: =IF(IFERROR(ABS(MilestoneTotal-1)<0.0001,FALSE()),"PASS","FAIL") -> PASS | D13: =IFERROR(TEXT(MilestoneTotal,"0%"),"") -> 100%
A14: 10 | B14: Plan reconciles to estimate within tolerance | C14: =IF(IFERROR(ABS(ReconVar)<=ReconTol,FALSE()),"PASS","FAIL") -> PASS | D14: =IFERROR("Variance "&TEXT(ReconVar,"0.0%")&" (tolerance "&TEXT(ReconTol,"0%")&")","") -> Variance -1.3% (tolerance 5%)
A15: 11 | B15: Duration fits the 104-week plan horizon | C15: =IF(IFERROR(DurationWeeks<=104,FALSE()),"PASS","FAIL") -> PASS | D15: =IFERROR(DurationWeeks&" weeks","") -> 36 weeks
A16: 12 | B16: Totals tie: phases = pairs + shared | C16: =IF(IFERROR(ABS(TotalBaseHrs-PairTotalHrs)<1,FALSE()),"PASS","FAIL") -> PASS | D16: =IFERROR("Phases "&TEXT(TotalBaseHrs,"#,##0")&" h vs pairs "&TEXT(PairTotalHrs,"#,##0")&" h","") -> Phases 14,325 h vs pairs 14,325 h
A17: 13 | B17: Totals tie: role hours = phase hours | C17: =IF(IFERROR(ABS(RoleHrsTotal-TotalBaseHrs)<1,FALSE()),"PASS","FAIL") -> PASS | D17: =IFERROR("Roles "&TEXT(RoleHrsTotal,"#,##0")&" h","") -> Roles 14,325 h
A18: 14 | B18: Totals tie: cost by phase = cost by role (role-mix mode) | C18: =IF(IFERROR(OR(CostMode="Blended",ABS(PhaseCostTotal-RoleCostTotal)<1),FALSE()),"PASS","FAIL") -> PASS | D18: =IFERROR("Phase cost "&TEXT(PhaseCostTotal,"$#,##0"),"") -> Phase cost $900,381
A19: 15 | B19: No error values in calculation tabs | C19: =IF(IFERROR(SUMPRODUCT(--ISERROR(Effort!A7:AV60))+SUMPRODUCT(--ISERROR(Schedule!B5:H80))+SUMPRODUCT(--ISERROR(Plan!A5:DE70))+SUMPRODUCT(--ISERROR(Cost!A5:G60))=0,FALSE()),"PASS","FAIL") -> PASS | D19: =IFERROR(SUMPRODUCT(--ISERROR(Effort!A7:AV60))+SUMPRODUCT(--ISERROR(Schedule!B5:H80))+SUMPRODUCT(--ISERROR(Plan!A5:DE70))+SUMPRODUCT(--ISERROR(Cost!A5:G60))&" error cell(s)","") -> 0 error cell(s)
B21: Failed checks | C21: =COUNTIF(C5:C19,"FAIL") -> 0

Sheet Scenarios
A1: Scenarios
A2: Compare options: copy the Current column and Paste Special > Values into Scenario A, B or C, then change inputs.
B4: Measure | C4: Current | D4: Scenario A | E4: Scenario B | F4: Scenario C
B5: Scenario name | C5: ="Current" -> Current
B6: Fixed price (USD) | C6: =FixedPrice -> 1069220.9
B7: Total hours | C7: =TotalHrs -> 17010.763
B8: Base hours | C8: =TotalBaseHrs -> 14324.603
B9: Duration (weeks) | C9: =DurationWeeks -> 36
B10: Development iterations | C10: =IterCount -> 10
B11: Peak team (FTE) | C11: =PeakTeam -> 18.5
B12: Average team (FTE) | C12: =AvgTeam -> 9.8194444
B13: Report automation | C13: =AutoRep -> 0
B14: Contingency % | C14: =ContPct -> 0.18123785
B15: Cost mode | C15: =CostMode -> Role mix

Sheet ChangeLog
A1: Change log
A2: Record every change to inputs, baseline values or formulas.
A4: Version | B4: Date | C4: Author | D4: Change
A5: v2.0 | B5: 46308 | C5: BI Estimator build | D5: First release of v2, built from the approved requirements document.
